Workbook

Sheet How_to_use
A1: ATPL Vector — Coverage Tracker
A2: Single source of truth for ECQB 2026 ATPL(A) coverage
A4: 1. What this is
A5: The canonical inventory of every Learning Objective (LO) in scope for ATPL(A).
A6: Built from the EASA TK Syllabus Comparison Document v6 (ECQB 2026), filtered to ATPL(A) only.
A7: Helicopter-only subjects (034, 082) and helicopter-only LOs in other subjects are excluded.
A8: Total in-scope leaf LOs: 4,045 (415 BK-only, 110 affected by ECQB 2026 changes).
A10: 2. The 5-level hierarchy
A11: Level 1: subject e.g. 010.00.00.00 AIR LAW
A12: Level 2: section e.g. 010.01.00.00 INTERNATIONAL LAW: CONVENTIONS, AGREEMENTS...
A13: Level 3: subsection e.g. 010.01.01.00 The Convention on International Civil Aviation...
A14: Level 4: topic e.g. 010.01.01.01 Establishment of the Chicago Convention
... A53: ECQB Update January 2026 PDF (notable developments §2).

Sheet Dashboard
A1: ATPL Vector — Coverage Tracker
A2: Single source of truth for ECQB 2026 ATPL(A) coverage. Filter / sort to plan next batches.
A4: Status legend
A5: NOT_STARTED | B5: No content yet on platform
A6: IN_PROGRESS | B6: Agent assigned, draft underway
A7: DRAFT_DONE | B7: Text exists, no visual/interactive yet
A8: VISUAL_DONE | B8: Has visual/diagram, no interactive
A9: INTERACTIVE_DONE | B9: Full interactive component built
A10: REVIEWED | B10: Content + visual + accuracy review passed
A11: NEEDS_UPDATE | B11: Content exists but ECQB 2026 says update needed
A12: OUT_OF_SCOPE | B12: Not required for ATPL(A) — skip
A14: Subject rollup
A15: Subject | B15: Name | C15: Leaf LOs | D15: BK-only | E15: ECQB 2026 | F15: NOT_STARTED | G15: IN_PROGRESS | H15: DRAFT_DONE | I15: VISUAL_DONE | J15: INTERACTIVE_DONE | K15: REVIEWED | L15: NEEDS_UPDATE | M15: % Done
A16: 010 | B16: Air Law and ATC Procedures | C16: 505 | D16: 55 | E16: 3 | F16: =COUNTIF('S010'!$K$4:$K$2000,"NOT_STARTED") | G16: =COUNTIF('S010'!$K$4:$K$2000,"IN_PROGRESS") | H16: =COUNTIF('S010'!$K$4:$K$2000,"DRAFT_DONE") | I16: =COUNTIF('S010'!$K$4:$K$2000,"VISUAL_DONE") | J16: =COUNTIF('S010'!$K$4:$K$2000,"INTERACTIVE_DONE") | K16: =COUNTIF('S010'!$K$4:$K$2000,"REVIEWED") | L16: =COUNTIF('S010'!$K$4:$K$2000,"NEEDS_UPDATE") | M16: =IFERROR((K16+J16)/C16,0)
A17: 021 | B17: Aircraft General Knowledge — Airframe, Systems, Powerplant | C17: 509 | D17: 26 | E17: 0 | F17: =COUNTIF('S021'!$K$4:$K$2000,"NOT_STARTED") | G17: =COUNTIF('S021'!$K$4:$K$2000,"IN_PROGRESS") | H17: =COUNTIF('S021'!$K$4:$K$2000,"DRAFT_DONE") | I17: =COUNTIF('S021'!$K$4:$K$2000,"VISUAL_DONE") | J17: =COUNTIF('S021'!$K$4:$K$2000,"INTERACTIVE_DONE") | K17: =COUNTIF('S021'!$K$4:$K$2000,"REVIEWED") | L17: =COUNTIF('S021'!$K$4:$K$2000,"NEEDS_UPDATE") | M17: =IFERROR((K17+J17)/C17,0)
A18: 022 | B18: Aircraft General Knowledge — Instrumentation | C18: 409 | D18: 30 | E18: 0 | F18: =COUNTIF('S022'!$K$4:$K$2000,"NOT_STARTED") | G18: =COUNTIF('S022'!$K$4:$K$2000,"IN_PROGRESS") | H18: =COUNTIF('S022'!$K$4:$K$2000,"DRAFT_DONE") | I18: =COUNTIF('S022'!$K$4:$K$2000,"VISUAL_DONE") | J18: =COUNTIF('S022'!$K$4:$K$2000,"INTERACTIVE_DONE") | K18: =COUNTIF('S022'!$K$4:$K$2000,"REVIEWED") | L18: =COUNTIF('S022'!$K$4:$K$2000,"NEEDS_UPDATE") | M18: =IFERROR((K18+J18)/C18,0)
A19: 031 | B19: Mass and Balance | C19: 84 | D19: 27 | E19: 13 | F19: =COUNTIF('S031'!$K$4:$K$2000,"NOT_STARTED") | G19: =COUNTIF('S031'!$K$4:$K$2000,"IN_PROGRESS") | H19: =COUNTIF('S031'!$K$4:$K$2000,"DRAFT_DONE") | I19: =COUNTIF('S031'!$K$4:$K$2000,"VISUAL_DONE") | J19: =COUNTIF('S031'!$K$4:$K$2000,"INTERACTIVE_DONE") | K19: =COUNTIF('S031'!$K$4:$K$2000,"REVIEWED") | L19: =COUNTIF('S031'!$K$4:$K$2000,"NEEDS_UPDATE") | M19: =IFERROR((K19+J19)/C19,0)
A20: 032 | B20: Performance — Aeroplanes | C20: 241 | D20: 32 | E20: 9 | F20: =COUNTIF('S032'!$K$4:$K$2000,"NOT_STARTED") | G20: =COUNTIF('S032'!$K$4:$K$2000,"IN_PROGRESS") | H20: =COUNTIF('S032'!$K$4:$K$2000,"DRAFT_DONE") | I20: =COUNTIF('S032'!$K$4:$K$2000,"VISUAL_DONE") | J20: =COUNTIF('S032'!$K$4:$K$2000,"INTERACTIVE_DONE") | K20: =COUNTIF('S032'!$K$4:$K$2000,"REVIEWED") | L20: =COUNTIF('S032'!$K$4:$K$2000,"NEEDS_UPDATE") | M20: =IFERROR((K20+J20)/C20,0)
A21: 033 | B21: Flight Planning and Monitoring | C21: 118 | D21: 9 | E21: 47 | F21: =COUNTIF('S033'!$K$4:$K$2000,"NOT_STARTED") | G21: =COUNTIF('S033'!$K$4:$K$2000,"IN_PROGRESS") | H21: =COUNTIF('S033'!$K$4:$K$2000,"DRAFT_DONE") | I21: =COUNTIF('S033'!$K$4:$K$2000,"VISUAL_DONE") | J21: =COUNTIF('S033'!$K$4:$K$2000,"INTERACTIVE_DONE") | K21: =COUNTIF('S033'!$K$4:$K$2000,"REVIEWED") | L21: =COUNTIF('S033'!$K$4:$K$2000,"NEEDS_UPDATE") | M21: =IFERROR((K21+J21)/C21,0)
A22: 040 | B22: Human Performance and Limitations | C22: 362 | D22: 0 | E22: 0 | F22: =COUNTIF('S040'!$K$4:$K$2000,"NOT_STARTED") | G22: =COUNTIF('S040'!$K$4:$K$2000,"IN_PROGRESS") | H22: =COUNTIF('S040'!$K$4:$K$2000,"DRAFT_DONE") | I22: =COUNTIF('S040'!$K$4:$K$2000,"VISUAL_DONE") | J22: =COUNTIF('S040'!$K$4:$K$2000,"INTERACTIVE_DONE") | K22: =COUNTIF('S040'!$K$4:$K$2000,"REVIEWED") | L22: =COUNTIF('S040'!$K$4:$K$2000,"NEEDS_UPDATE") | M22: =IFERROR((K22+J22)/C22,0)
A23: 050 | B23: Meteorology | C23: 464 | D23: 15 | E23: 5 | F23: =COUNTIF('S050'!$K$4:$K$2000,"NOT_STARTED") | G23: =COUNTIF('S050'!$K$4:$K$2000,"IN_PROGRESS") | H23: =COUNTIF('S050'!$K$4:$K$2000,"DRAFT_DONE") | I23: =COUNTIF('S050'!$K$4:$K$2000,"VISUAL_DONE") | J23: =COUNTIF('S050'!$K$4:$K$2000,"INTERACTIVE_DONE") | K23: =COUNTIF('S050'!$K$4:$K$2000,"REVIEWED") | L23: =COUNTIF('S050'!$K$4:$K$2000,"NEEDS_UPDATE") | M23: =IFERROR((K23+J23)/C23,0)
A24: 061 | B24: General Navigation | C24: 117 | D24: 24 | E24: 0 | F24: =COUNTIF('S061'!$K$4:$K$2000,"NOT_STARTED") | G24: =COUNTIF('S061'!$K$4:$K$2000,"IN_PROGRESS") | H24: =COUNTIF('S061'!$K$4:$K$2000,"DRAFT_DONE") | I24: =COUNTIF('S061'!$K$4:$K$2000,"VISUAL_DONE") | J24: =COUNTIF('S061'!$K$4:$K$2000,"INTERACTIVE_DONE") | K24: =COUNTIF('S061'!$K$4:$K$2000,"REVIEWED") | L24: =COUNTIF('S061'!$K$4:$K$2000,"NEEDS_UPDATE") | M24: =IFERROR((K24+J24)/C24,0)
A25: 062 | B25: Radio Navigation | C25: 322 | D25: 101 | E25: 0 | F25: =COUNTIF('S062'!$K$4:$K$2000,"NOT_STARTED") | G25: =COUNTIF('S062'!$K$4:$K$2000,"IN_PROGRESS") | H25: =COUNTIF('S062'!$K$4:$K$2000,"DRAFT_DONE") | I25: =COUNTIF('S062'!$K$4:$K$2000,"VISUAL_DONE") | J25: =COUNTIF('S062'!$K$4:$K$2000,"INTERACTIVE_DONE") | K25: =COUNTIF('S062'!$K$4:$K$2000,"REVIEWED") | L25: =COUNTIF('S062'!$K$4:$K$2000,"NEEDS_UPDATE") | M25: =IFERROR((K25+J25)/C25,0)
A26: 070 | B26: Operational Procedures | C26: 346 | D26: 2 | E26: 33 | F26: =COUNTIF('S070'!$K$4:$K$2000,"NOT_STARTED") | G26: =COUNTIF('S070'!$K$4:$K$2000,"IN_PROGRESS") | H26: =COUNTIF('S070'!$K$4:$K$2000,"DRAFT_DONE") | I26: =COUNTIF('S070'!$K$4:$K$2000,"VISUAL_DONE") | J26: =COUNTIF('S070'!$K$4:$K$2000,"INTERACTIVE_DONE") | K26: =COUNTIF('S070'!$K$4:$K$2000,"REVIEWED") | L26: =COUNTIF('S070'!$K$4:$K$2000,"NEEDS_UPDATE") | M26: =IFERROR((K26+J26)/C26,0)
A27: 081 | B27: Principles of Flight — Aeroplanes | C27: 489 | D27: 91 | E27: 0 | F27: =COUNTIF('S081'!$K$4:$K$2000,"NOT_STARTED") | G27: =COUNTIF('S081'!$K$4:$K$2000,"IN_PROGRESS") | H27: =COUNTIF('S081'!$K$4:$K$2000,"DRAFT_DONE") | I27: =COUNTIF('S081'!$K$4:$K$2000,"VISUAL_DONE") | J27: =COUNTIF('S081'!$K$4:$K$2000,"INTERACTIVE_DONE") | K27: =COUNTIF('S081'!$K$4:$K$2000,"REVIEWED") | L27: =COUNTIF('S081'!$K$4:$K$2000,"NEEDS_UPDATE") | M27: =IFERROR((K27+J27)/C27,0)
A28: 090 | B28: Communications | C28: 79 | D28: 3 | E28: 0 | F28: =COUNTIF('S090'!$K$4:$K$2000,"NOT_STARTED") | G28: =COUNTIF('S090'!$K$4:$K$2000,"IN_PROGRESS") | H28: =COUNTIF('S090'!$K$4:$K$2000,"DRAFT_DONE") | I28: =COUNTIF('S090'!$K$4:$K$2000,"VISUAL_DONE") | J28: =COUNTIF('S090'!$K$4:$K$2000,"INTERACTIVE_DONE") | K28: =COUNTIF('S090'!$K$4:$K$2000,"REVIEWED") | L28: =COUNTIF('S090'!$K$4:$K$2000,"NEEDS_UPDATE") | M28: =IFERROR((K28+J28)/C28,0)
A29: TOTAL | C29: =SUM(C16:C28) | D29: =SUM(D16:D28) | E29: =SUM(E16:E28) | F29: =SUM(F16:F28) | G29: =SUM(G16:G28) | H29: =SUM(H16:H28) | I29: =SUM(I16:I28) | J29: =SUM(J16:J28) | ... L29: =SUM(L16:L28) | M29: =IFERROR((K29+J29)/C29,0)

Sheet All_LOs
A1: LO_ID | B1: Subject_Code | C1: Subject_Name | D1: LO_Text | E1: BK_Only | F1: ECQB_2026_Change_Flag | G1: ECQB_2026_Source_Note | H1: Priority | I1: Coverage_Status | J1: Content_Type_Planned | K1: Repo_Path | L1: Last_Updated | M1: Agent_Assigned | N1: Reviewed_By | O1: Notes
A2: 010.01.01.01.01 | B2: 010 | C2: Air Law and ATC Procedures | D2: Explain the circumstances that led to the establishment of the Convention on International Civil Aviation, Chicago, 7 December 1944. | E2: Y | G2: ICAO Doc 7300/9 Preamble | H2: LOW | I2: NOT_STARTED
A3: 010.01.01.02.01 | B3: 010 | C3: Air Law and ATC Procedures | D3: Recall the general contents of relevant parts of the following chapters: general principles and application of the Convention; flight over territory of Contracting States; nationality of aircraft; international standards and recommended practices (SARPs), especially notification of differences and validity of endorsed certificates and licences. | E3: Y | G3: ICAO Doc 7300/9 Part 1, Articles 1, 2, 3, 4, 5, 6, 7, 8, 9, 10, 11, 12, 16, 17, 18, 19, 20, 37, 38, 39, 40 | H3: LOW | I3: NOT_STARTED
A4: 010.01.01.02.02 | B4: 010 | C4: Air Law and ATC Procedures | D4: General principles - Describe the application of the following terms in civil aviation: sovereignty; territory and high seas according to the UN Convention on the High Seas. | E4: Y | G4: Convention on the High Seas (Geneva, 29 April 1958) Articles 1, 2; ICAO Doc 7300/9 Part 1, Articles 1, 2 | H4: LOW | I4: NOT_STARTED
A5: 010.01.01.02.03 | B5: 010 | C5: Air Law and ATC Procedures | D5: Explain the following terms and how they apply to international air traffic: right of non-scheduled flight (including the two technical freedoms of the air); scheduled air services; cabotage; landing at customs airports; Rules of the Air; search of aircraft. | E5: N | G5: ICAO Doc 7300/9, Articles 5, 6, 7, 10, 12, 16 | H5: MED | I5: NOT_STARTED
A6: 010.01.01.02.04 | B6: 010 | C6: Air Law and ATC Procedures | D6: Explain the duties of Contracting States in relation to: documents carried on board the aircraft: certificate of registration; certificates of airworthiness; licences of personnel; recognition of certificates and licences; cargo restrictions; photographic apparatus. | E6: Y | G6: ICAO Doc 7300/9, Articles 29, 31, 32, 33, 35, 36 | H6: LOW | I6: NOT_STARTED
A7: 010.01.01.03.01 | B7: 010 | C7: Air Law and ATC Procedures | D7: Describe the objectives of ICAO. | E7: Y | G7: ICAO Doc 7300/9, Article 44 | H7: LOW | I7: NOT_STARTED
A8: 010.01.01.03.02 | B8: 010 | C8: Air Law and ATC Procedures | D8: Recognise the organisation and duties of the ICAO Assembly, Council and Air Navigation Commission (ANC). | E8: Y | G8: ICAO Doc 7300/9, Articles 48, 49, 50, 54, 56, 57 | H8: LOW | I8: NOT_STARTED
A9: 010.01.01.03.03 | B9: 010 | C9: Air Law and ATC Procedures | D9: Describe the annexes to the Convention. | E9: Y | G9: ICAO Doc 7300/9, Articles 54, 90, 94, 95 | H9: LOW | I9: NOT_STARTED
A10: 010.01.02.01.01 | B10: 010 | C10: Air Law and ATC Procedures | D10: Explain the two technical freedoms of the air. | E10: N | G10: ICAO Doc 7500, Art. 1 | H10: MED | I10: NOT_STARTED
A11: 010.01.02.02.01 | B11: 010 | C11: Air Law and ATC Procedures | D11: Explain the three commercial freedoms of the air. | E11: N | G11: ICAO Doc 9626, Part IV, Chapter 2 'Basic market access' | H11: MED | I11: NOT_STARTED
A12: 010.01.02.03.01 | B12: 010 | C12: Air Law and ATC Procedures | D12: Describe the measures and actions to be taken by the pilot-in-command (PIC) of an aircraft in order to suppress unlawful acts against the safety of the aircraft. | E12: N | G12: ICAO Doc 8364 — Convention on Offences and Certain Other Acts Committed on Board Aircraft, signed in Tokyo on 14 September 1963, Chapter III 'Powers of the Commander' | H12: MED | I12: NOT_STARTED
A13: 010.01.02.05.01 | B13: 010 | C13: Air Law and ATC Procedures | D13: Explain the legal significance of the issue of a passenger ticket or of baggage/cargo documents (that the issue is a form of contract). | E13: N | G13: ICAO Doc 9740 Convention for the Unification of Certain Rules for International Carriage — The Montreal Convention of 1999 | H13: MED | I13: NOT_STARTED
... A17: 010.01.03.01.01 | B17: 010 | C17: Air Law and ATC Procedures | D17: Describe the objectives of IATA. | E17: N | G17: Available via https://www.iata.org/en/about/mission/ | H17: MED | I17: NOT_STARTED
A18: 010.01.04.01.01 | B18: 010 | C18: Air Law and ATC Procedures | D18: Describe the objectives of EASA. | E18: Y | H18: LOW | I18: NOT_STARTED
A19: 010.01.04.01.02 | B19: 010 | C19: Air Law and ATC Procedures | D19: Describe the role of EASA in European civil aviation. | E19: N | H19: MED | I19: NOT_STARTED
A20: 010.01.04.01.03 | B20: 010 | C20: Air Law and ATC Procedures | D20: State that the structure of the regulatory material related to EASA involves: hard law (regulations, delegated acts, implementing acts, and implementing rules); soft law (certification specifications, acceptable means of compliance, and guidance material). | E20: N | G20: See https://www.easa.europa.eu/en/light/topics/easas-regulatory-role-increasing-safety-environmental-protection-and-enabling | H20: MED | I20: NOT_STARTED
A21: 010.01.04.01.04 | B21: 010 | C21: Air Law and ATC Procedures | D21: State the meaning of the terminology associated with the structure of the regulatory material related to EASA, specifically: regulations, delegated acts, implementing acts, and implementing rules, as applicable until 11 September 2023; and certification specifications, acceptable means of compliance, and guidance material. | E21: N | G21: See https://commission.europa.eu/law/law-making-process/adopting-eu-law/implementing-and-delegated-acts_en and https://www.easa.europa.eu/en/light/topics/easas-regulatory-role-increasing-safety-environmental-protection-and-enabling | H21: MED | I21: NOT_STARTED
A22: 010.01.04.02.01 | B22: 010 | C22: Air Law and ATC Procedures | D22: Describe the Single European Sky (SES) regulations. | E22: Y | G22: See https://eur-lex.europa.eu/EN/legal-content/summary/single-european-sky-ses.html | H22: LOW | I22: NOT_STARTED
A23: 010.02.02.01.01 | B23: 010 | C23: Air Law and ATC Procedures | D23: State the issuing authority of a CofA. | E23: N | G23: ICAO Annex 8, Part II, Chapter 3.2 Eligibility, issuance and continued validity of a Certificate of Airworthiness; Reg. (EU) 748/2012, Part-21, 21.B.326; Appendix IV to Part-21. | H23: MED | I23: NOT_STARTED
A24: 010.02.02.01.02 | B24: 010 | C24: Air Law and ATC Procedures | D24: State the necessity to hold a CofA. | E24: N | G24: ICAO Doc 7300, Article 31 | H24: MED | I24: NOT_STARTED
A25: 010.02.02.01.03 | B25: 010 | C25: Air Law and ATC Procedures | D25: Explain the prerequisites for the issue of a CofA according to Commission Regulation (EU) No 748/2012. | E25: Y | G25: Reg. (EU) 748/2012, Part 21, Subpart H | H25: LOW | I25: NOT_STARTED
A26: 010.02.02.01.04 | B26: 010 | C26: Air Law and ATC Procedures | D26: State who shall determine an aircraft’s continuing airworthiness. | E26: N | G26: ICAO Annex 8, Part II, Chapter 3.2 Eligibility, issuance and continued validity of a Certificate of Airworthiness; Reg. (EU) 748/2012, Part-21, 21.B.325; Appendix IV to Part-21 | H26: MED | I26: NOT_STARTED
A27: 010.02.02.01.05 | B27: 010 | C27: Air Law and ATC Procedures | D27: Describe how a CofA can be renewed or may remain valid. | E27: N | G27: Note ICAO Annex 8 refers to renewal, EU Regulation refers to continuing validity. ICAO Annex 8, Part II, Chapter 3.2 Eligibility, issuance and continued validity of a Certificate of Airworthiness; Chapter 3.5 Temporary loss of airworthiness; Chapter 3.6 Damage to aircraft; Reg. (EU) 2018/1139, Arti. 14; Reg. (EU) 748/2012 as amended, Part-21, 21.B.325, 21.B.326; Appendix IV to Part-21 | H27: MED | I27: NOT_STARTED
A28: 010.02.03.01.01 | B28: 010 | C28: Air Law and ATC Procedures | D28: Recall the definition of the following terms: aircraft; heavier-than-air aircraft; State of Registry. | E28: Y | G28: ICAO Annex 7, Chapter 1 Definitions | H28: LOW | I28: NOT_STARTED
A29: 010.02.04.01.01 | B29: 010 | C29: Air Law and ATC Procedures | D29: State the location of nationality marks, common marks and registration marks. | E29: N | G29: ICAO Annex 7, Chapter 4.3 Heavier-than-air aircraft; ICAO Annex 7, Chapter 10 Identification plate | H29: MED | I29: NOT_STARTED
A30: 010.02.04.01.02 | B30: 010 | C30: Air Law and ATC Procedures | D30: Explain who is responsible for assigning nationality marks, common marks and registration marks. | E30: N | G30: ICAO Annex 7, Chapter 3 Nationality, common and registration marks to be used | H30: MED | I30: NOT_STARTED
A31: 010.04.01.01.01 | B31: 010 | C31: Air Law and ATC Procedures | D31: Describe the relationship and differences between ICAO Annex 1 and the Aircrew Regulation. | E31: Y | G31: Note: awareness of the differences in scope, non-ICAO licence/ratings as per the Aircrew Regulation: ICAO Annex 1, 1.2, Note; Reg. (EU) 2018/1139 Art. 2 'Scope'; Reg. (EU) 1178/2011 as amended as amended, Appendix I to Part-ARA licence template | H31: LOW | I31: NOT_STARTED
... A102: 010.06.04.01.05 | B102: 010 | C102: Air Law and ATC Procedures | D102: State the minimum obstacle clearance (MOC) provided by the minimum sector altitudes (MSAs) established for an aerodrome. | E102: N | G102: ICAO Doc 8168, Volume I, Part II, Section 4, Chapter 1, 1.3 Minimum sector altitudes (MSA)/terminal arrival altitudes (TAA) | H102: MED | I102: NOT_STARTED
A103: 010.06.04.01.06 | B103: 010 | C103: Air Law and ATC Procedures | D103: State that a pilot shall apply wind corrections when carrying out an instrument approach procedure. | E103: Y | H103: LOW | I103: NOT_STARTED
A104: 010.06.04.01.07 | B104: 010 | C104: Air Law and ATC Procedures | D104: State the most significant factor influencing the conduct of instrument approach procedures. | E104: N | G104: ICAO Doc 8168, Volume II, Part I, Section 2, Chapter 1 | H104: MED | I104: NOT_STARTED
A105: 010.06.04.01.08 | B105: 010 | C105: Air Law and ATC Procedures | D105: Explain why a pilot should not descend below obstacle clearance altitude/height (OCA/H), which are established for: precision approach procedures; non-precision approach procedures; visual (circling) procedures; APV approach procedures. | E105: N | G105: ICAO Doc 8168, Volume I, Part II, Section 5, Chapter 1, 1.6 Obstacle clearance altitude/height (OCA/H) | H105: MED | I105: NOT_STARTED
A106: 010.06.04.01.09 | B106: 010 | C106: Air Law and ATC Procedures | D106: Describe in general terms the relevant factors for the calculation of operational minima. | E106: N | G106: ICAO Doc 8168, Volume I, Part II Section 5, Chapter 1, 1.7 Factors affecting operational minima | H106: MED | I106: NOT_STARTED
A107: 010.06.04.01.10 | B107: 010 | C107: Air Law and ATC Procedures | D107: State the following acronyms in plain language: DA, DH, OCA, OCH, MDA, MDH, MOC, DA/H, OCA/H, MDA/H. | E107: N | G107: ICAO Doc 8168, Volume I, Part I, Section 1, Chapters 1 and 2 | H107: MED | I107: NOT_STARTED
A108: 010.06.04.01.11 | B108: 010 | C108: Air Law and ATC Procedures | D108: Explain the relationship between the terms: DA, DH, OCA, OCH, MDA, MDH, MOC, DA/H, OCA/H, and MDA/H. | E108: N | G108: ICAO Doc 8168, Volume I, Part II, Section 5, Chapter 1 General requirements, including Figures II-5-1-2, II-5-1-3. II-5-1-4 | H108: MED | I108: NOT_STARTED
A109: 010.06.04.02.01 | B109: 010 | C109: Air Law and ATC Procedures | D109: Describe how the vertical cross section for each of the five approach segments is broken down into the various areas. | E109: N | G109: ICAO Doc 8168, Volume I, Part II, Section 5, Chapter 1 General requirements | H109: MED | I109: NOT_STARTED
A110: 010.06.04.02.02 | B110: 010 | C110: Air Law and ATC Procedures | D110: State within which area of the cross section the minimum obstacle clearance (MOC) is provided for the whole width of the area. | E110: N | G110: ICAO Doc 8168, Volume I, Part II, Section 1, Chapter 1, 1.3 Areas, 1.3.1 | H110: MED | I110: NOT_STARTED
A111: 010.06.04.02.03 | B111: 010 | C111: Air Law and ATC Procedures | D111: Define the terms ‘IAF’, ‘IF’, ‘FAF’, ‘FAP’, ‘MAPt’ and ‘TP’. | E111: N | G111: ICAO Doc 8168, Volume I, Part I, Section 1 Definitions, abbreviations and acronyms and units of measurement | H111: MED | I111: NOT_STARTED
A112: 010.06.04.02.04 | B112: 010 | C112: Air Law and ATC Procedures | D112: State the accuracy of facilities providing track (VHF omnidirectional radio range (VOR), instrument landing system (ILS), non-directional beacon (NDB)). | E112: Y | G112: ICAO Doc 8168, Volume I, Attachment A, Section 2, Table A-2-1. System use accuracy (2 SD) of facility providing track guidance and facility not providing track guidance | H112: LOW | I112: NOT_STARTED
A113: 010.06.04.02.05 | B113: 010 | C113: Air Law and ATC Procedures | D113: State the optimum descent gradient (preferred for a precision approach) in degrees and per cent. | E113: N | G113: ICAO Doc 8168, Volume I, Part II, Section 5, Chapter 1, 1.10 Descent gradient | H113: MED | I113: NOT_STARTED
A114: 010.06.04.03.01 | B114: 010 | C114: Air Law and ATC Procedures | D114: Name the five standard segments of an instrument approach procedure, and state the beginning and end for each of them. | E114: N | G114: ICAO Doc 8168, Volume I, Part II, Section 5, Chapter 1, 1.2 Instrument approach procedure | H114: MED | I114: NOT_STARTED
A115: 010.06.04.03.02 | B115: 010 | C115: Air Law and ATC Procedures | D115: Describe where an arrival route normally ends. | E115: N | G115: ICAO Doc 8168, Volume I, Part II, Section 4 Arrival procedures, Chapter 1 General requirements | H115: MED | I115: NOT_STARTED
... A190: 010.06.08.01.04 | B190: 010 | C190: Air Law and ATC Procedures | D190: State when the pilot shall ‘SQUAWK IDENT’. | E190: N | G190: ICAO Doc 8168, Volume III, Section 4, Chapter 1; Reg. (EU) 923/2912 as amended, SERA.13001 and associated GM | H190: MED | I190: NOT_STARTED
A191: 010.06.08.01.05 | B191: 010 | C191: Air Law and ATC Procedures | D191: State the transponder code to indicate: a state of emergency; a COM failure; unlawful interference. | E191: N | F191: Loss of comms — SERA 2024/404: 7601 added, 20-min rule replaces 7-min | G191: ICAO Doc 8168, Volume III, Section 4, Chapter 1; Reg. (EU) 923/2912 as amended, SERA.13005 and associated AMC/GM (Note code 7601 for specific conditions under radio comms failure is covered in LO 010.05.03.01.20) | H191: HIGH | I191: NOT_STARTED
A192: 010.06.08.01.06 | B192: 010 | C192: Air Law and ATC Procedures | D192: Describe the consequences of a transponder failure in flight. | E192: N | G192: ICAO Doc 8168, Volume III, Section 4, Chapter 1; see also Reg. (EU) 923/2912 as amended, SERA.13020 and associated GM | H192: MED | I192: NOT_STARTED
A193: 010.06.08.01.07 | B193: 010 | C193: Air Law and ATC Procedures | D193: State the primary action of the pilot in the case of an unserviceable transponder before departure when no repair or replacement at the given AD is possible. | E193: N | G193: ICAO Doc 8168, Volume III, Section 4, Chapter 1; Reg. (EU) 923/2912 as amended, SERA.13020 and associated GM | H193: MED | I193: NOT_STARTED
A194: 010.06.08.02.01 | B194: 010 | C194: Air Law and ATC Procedures | D194: Describe the main reason for using ACAS. | E194: N | G194: ICAO Doc 8168, Volume III, Section 4, Chapter 3, 3.1 ACAS overview | H194: MED | I194: NOT_STARTED
A195: 010.06.08.02.02 | B195: 010 | C195: Air Law and ATC Procedures | D195: State whether the ‘use of ACAS indications’ described in ICAO Doc 8168 is absolutely mandatory. | E195: N | G195: ICAO Doc 8168, Volume III, Section 4, Chapter 3, 3.2 Use of ACAS indications; see also Reg. (EU) 923/2912 as amended, SERA.11014 | H195: MED | I195: NOT_STARTED
A196: 010.06.08.02.03 | B196: 010 | C196: Air Law and ATC Procedures | D196: Explain the pilots’ reaction required to allow ACAS to fulfil its role of assisting pilots in the avoidance of potential collisions. | E196: N | G196: ICAO Doc 8168, Volume III, Section 4, Chapter 3, 3.2 Use of ACAS indications; see also Reg. (EU) 923/2912 as amended, SERA.11014 and associated GM | H196: MED | I196: NOT_STARTED
A197: 010.06.08.02.04 | B197: 010 | C197: Air Law and ATC Procedures | D197: Explain why pilots shall not manoeuvre their aircraft in response to traffic advisories (TAs) only. | E197: N | G197: ICAO Doc 8168, Volume III, Section 4, Chapter 3, 3.2 Use of ACAS indications; see also Reg. (EU) 923/2912 as amended, SERA.11014 and associated GM | H197: MED | I197: NOT_STARTED
A198: 010.06.08.02.05 | B198: 010 | C198: Air Law and ATC Procedures | D198: Explain the significance of TAs in view of possible resolution advisories (RAs). | E198: N | G198: ICAO Doc 8168, Volume III, Section 4, Chapter 3, 3.2 Use of ACAS indications; see also Reg. (EU) 923/2912 as amended, SERA.11014 and associated GM | H198: MED | I198: NOT_STARTED
A199: 010.06.08.02.06 | B199: 010 | C199: Air Law and ATC Procedures | D199: State why a pilot should follow RAs immediately. | E199: N | G199: ICAO Doc 8168, Volume III, Section 4, Chapter 3, 3.2 Use of ACAS indications; see also Reg. (EU) 923/2912 as amended, SERA.11014 and associated GM | H199: MED | I199: NOT_STARTED
A200: 010.06.08.02.07 | B200: 010 | C200: Air Law and ATC Procedures | D200: List the reasons which may force a pilot to disregard an RA. | E200: N | G200: ICAO Doc 8168, Volume III, Section 4, Chapter 3, 3.2 Use of ACAS indications; see also Reg. (EU) 923/2912 as amended, SERA.11014 and associated GM | H200: MED | I200: NOT_STARTED
A201: 010.06.08.02.08 | B201: 010 | C201: Air Law and ATC Procedures | D201: Explain the importance of instructing ATC immediately that an RA has been followed. | E201: N | G201: ICAO Doc 8168, Volume III, Section 4, Chapter 3, 3.2 Use of ACAS indications; see also Reg. (EU) 923/2912 as amended, SERA.11014 and associated GM | H201: MED | I201: NOT_STARTED
A202: 010.06.08.02.09 | B202: 010 | C202: Air Law and ATC Procedures | D202: Explain the duties of a pilot with regard to ATC when an RA situation is resolved. | E202: N | G202: ICAO Doc 8168, Volume III, Section 4, Chapter 3, 3.2 Use of ACAS indications; see also Reg. (EU) 923/2912 as amended, SERA.11014 and associated GM | H202: MED | I202: NOT_STARTED
A203: 010.06.09.01.01 | B203: 010 | C203: Air Law and ATC Procedures | D203: Describe the subject matter and scope of that Regulation. | E203: N | G203: Reg. (EU) 965/2012 as amended, Article 1 Subject matter and scope | H203: MED | I203: NOT_STARTED
A204: 010.06.09.01.02 | B204: 010 | C204: Air Law and ATC Procedures | D204: State that Reg. (EU) 965/2012 covers all types of commercial and non-commercial operations. | E204: Y | H204: LOW | I204: NOT_STARTED
A205: 010.06.09.02.01 | B205: 010 | C205: Air Law and ATC Procedures | D205: Recall the definitions in the Regulation not already given in ICAO PAN-OPS. | E205: N | G205: Reg. (EU) 965/2012 as amended, Article 2 Definitions | H205: MED | I205: NOT_STARTED
A206: 010.06.09.03.01 | B206: 010 | C206: Air Law and ATC Procedures | D206: Describe the scope of these Parts. | E206: N | H206: MED | I206: NOT_STARTED
A207: 010.06.09.03.02 | B207: 010 | C207: Air Law and ATC Procedures | D207: Explain the main content of these Parts, except the operational procedures. | E207: Y | H207: LOW | I207: NOT_STARTED
A208: 010.07.01.01.01 | B208: 010 | C208: Air Law and ATC Procedures | D208: Recall the definitions given in ICAO Annex 11. | E208: Y | G208: ICAO Annex 11, Chapter 1 Definitions | H208: LOW | I208: NOT_STARTED
A209: 010.07.01.02.01 | B209: 010 | C209: Air Law and ATC Procedures | D209: State the objectives of ATS. | E209: Y | G209: ICAO Annex 11, Chapter 2, 2.2 Objectives of ATS | H209: LOW | I209: NOT_STARTED
A210: 010.07.01.02.02 | B210: 010 | C210: Air Law and ATC Procedures | D210: Describe the three basic types of ATS. | E210: Y | G210: ICAO Annex 11, Chapter 2, 2.3 Divisions of the air traffic services | H210: LOW | I210: NOT_STARTED
A211: 010.07.01.02.03 | B211: 010 | C211: Air Law and ATC Procedures | D211: Describe the three basic types of ATC services. | E211: Y | G211: ICAO Annex 11, Chapter 2, 2.3 Divisions of the air traffic services | H211: LOW | I211: NOT_STARTED
A212: 010.07.01.02.04 | B212: 010 | C212: Air Law and ATC Procedures | D212: State on which frequencies a pilot can expect ATC to contact them in case of an emergency. | E212: N | G212: ICAO Annex 11, Chapter 2, 2.24 Service to aircraft in the event of an emergency, 2.25 In-flight contingencies, Chapter 5, 5.3 Use of communication facilities, and Chapter 6, 6.1.1.1 (referring to Annex 10, Volumes II and V), Chapter 4, 4.1.3.1 | H212: MED | I212: NOT_STARTED
A213: 010.07.01.02.05 | B213: 010 | C213: Air Law and ATC Procedures | D213: Describe the procedure for the transfer of an aircraft from one ATC unit to another. | E213: N | G213: ICAO Annex 11, Chapter 3, 3.6.1 Transfer of responsibility for control | H213: MED | I213: NOT_STARTED
A214: 010.07.01.03.01 | B214: 010 | C214: Air Law and ATC Procedures | D214: Describe the purpose for establishing flight information regions (FIRs) including upper flight information regions (UIRs). | E214: N | G214: ICAO Annex 11, Chapter 2: 2.5; 2.10; 2.11 | H214: MED | I214: NOT_STARTED
A215: 010.07.01.03.02 | B215: 010 | C215: Air Law and ATC Procedures | D215: Describe the various rules and services that apply to the various classes of airspace. | E215: N | G215: ICAO Annex 11, Chapter 2, 2.6 Classification of airspaces and Annex 11, Appendix 4; Reg. (EU) 923/2912 as amended, SERA.6001 and associated AMC/GM; SERA Appendix 4 | H215: MED | I215: NOT_STARTED
A216: 010.07.01.03.03 | B216: 010 | C216: Air Law and ATC Procedures | D216: Explain which airspace shall be included in an FIR or UIR. | E216: N | G216: ICAO Annex 11, Chapter 2, 2.11 Specifications for flight information regions, control areas and control zones | H216: MED | I216: NOT_STARTED
A217: 010.07.01.03.04 | B217: 010 | C217: Air Law and ATC Procedures | D217: State the designation for those portions of the airspace where flight information service (FIS) and alerting service shall be provided. | E217: N | G217: ICAO Annex 11, Chapter 2, 2.5 Designation of the portions of the airspace and controlled aerodromes where air traffic services will be provided | H217: MED | I217: NOT_STARTED
A218: 010.07.01.03.05 | B218: 010 | C218: Air Law and ATC Procedures | D218: State the designations for those portions of the airspace where ATC services shall be provided. | E218: N | G218: ICAO Annex 11, Chapter 2, 2.5 Designation of the portions of the airspace and controlled aerodromes where air traffic services will be provided | H218: MED | I218: NOT_STARTED
A219: 010.07.01.03.06 | B219: 010 | C219: Air Law and ATC Procedures | D219: Identify whether or not control areas (CTAs) and control zones (CTRs) designated within an FIR shall form part of that FIR. | E219: N | G219: ICAO Annex 11, Chapter 2, 2.5 Designation of the portions of the airspace and controlled aerodromes where air traffic services will be provided | H219: MED | I219: NOT_STARTED
... A370: 010.08.04.02.03 | B370: 010 | C370: Air Law and ATC Procedures | D370: State how NOTAMs shall be distributed. | E370: N | G370: ICAO Annex 15, Chapter 5.4.2 | H370: MED | I370: NOT_STARTED
A371: 010.08.04.02.04 | B371: 010 | C371: Air Law and ATC Procedures | D371: Explain how information regarding snow, ice and standing water on AD pavements shall be reported. | E371: N | F371: Pavement strength (EU still ACN/PCN, not aligned to ICAO Annex 14 Ch 2.6) | G371: ICAO Annex 15, Chapter 5, 5.2.6 Note; PANS-AIM (ICAO Doc 10066), Appendix 4 Instructions for the completion of the SNOWTAM format; Reg. (EU) 2017/373 as amended, Appendix 3 to Part-AIS; ADR.OPS.A.065 and Appendix 2, ADR Regulation | H371: HIGH | I371: NOT_STARTED
A372: 010.08.04.02.05 | B372: 010 | C372: Air Law and ATC Procedures | D372: Describe the means by which NOTAMs shall be distributed. | E372: N | G372: ICAO Annex 15, Chapter 5, 5.4 Distribution services; PANS-AIM (ICAO Doc 10066), 5.2.5 NOTAM, 5.2.5.1.3, and Appendix 7 | H372: MED | I372: NOT_STARTED
A373: 010.08.04.02.06 | B373: 010 | C373: Air Law and ATC Procedures | D373: Define and state which information an ASHTAM may contain. | E373: N | G373: ICAO Annex 15, Chapter 5, 5.2.6 Note; PANS-AIM (ICAO Doc 10066), Appendix 5 ASHTAM format; Reg. (EU) 2017/373 as amended, Appendix 4 to Part-AIS | H373: MED | I373: NOT_STARTED
A374: 010.08.04.03.01 | B374: 010 | C374: Air Law and ATC Procedures | D374: List the circumstances under which the information concerned shall or should be distributed as an AIRAC. | E374: Y | G374: ICAO Annex 15, Chapter 6, 6.2; Reg. (EU) 2017/373 as amended, AIS.OR.505, AIS.TR.505 and associated AMC/GM | H374: LOW | I374: NOT_STARTED
A375: 010.08.04.04.01 | B375: 010 | C375: Air Law and ATC Procedures | D375: Describe the type of information that may be published in AICs. | E375: Y | G375: ICAO Annex 15, Chapter 5, 5.2.4 Aeronautical Information Circulars; PANS-AIM (ICAO Doc 10066), Chapter 5, 5.2.2 Aeronautical Information Circulars (AIC); Reg. (EU) 2017/373 as amended, AIS.OR.320, AIS.TR.320 | H375: LOW | I375: NOT_STARTED
A376: 010.08.04.04.02 | B376: 010 | C376: Air Law and ATC Procedures | D376: Explain the organisation of AICs. | E376: N | G376: ICAO Annex 15, Chapter 5, 5.2.4, Note; PANS-AIM (ICAO Doc 10066), Chapter 5, 5.2.2 Aeronautical Information Circulars (AIC), 5.2.2.3 to 5.2.2.9; Reg. (EU) 2017/373 as amended, AIS.TR.320 | H376: MED | I376: NOT_STARTED
A377: 010.08.04.05.01 | B377: 010 | C377: Air Law and ATC Procedures | D377: Summarise, in addition to the elements of the integrated AIP and maps/charts, the additional current information relating to the AD of departure that shall be provided as pre-flight information. | E377: N | G377: ICAO Annex 15, Chapter 5, 5.5 Pre-flight information service; PANS-AIM (ICAO Doc 10066), Chapter 5, 5.5 Pre-flight information; ICAO Doc 4444, 7.5 Essential information on aerodrome conditions; see also Reg. (EU) 2017/373 as amended, AIS.OR.405 | H377: MED | I377: NOT_STARTED
A378: 010.08.04.05.02 | B378: 010 | C378: Air Law and ATC Procedures | D378: Describe how a recapitulation of current NOTAM and other information of urgent character shall be made available to flight crew. | E378: N | G378: ICAO Annex 15, Chapter 5, 5.5 Pre-flight information service, Note 2; see also GM1 AIS.OR.405(b) | H378: MED | I378: NOT_STARTED
A379: 010.08.04.05.03 | B379: 010 | C379: Air Law and ATC Procedures | D379: State which post-flight information from flight crew shall be submitted to AIS for distribution as required by the circumstances. | E379: N | G379: ICAO Annex 15, Chapter 5, 5.6 Post-flight information service | H379: MED | I379: NOT_STARTED
A380: 010.08.05.01.01 | B380: 010 | C380: Air Law and ATC Procedures | D380: State that Commission Implementing Regulation (EU) 2017/373 provides: general requirements for the provision of air navigation services; specific requirements for the provision of air traffic services; specific requirements for the provision of meteorological services; specific requirements for the provision of aeronautical information services; specific requirements for the provision of communication, navigation or surveillance services. | E380: N | H380: MED | I380: NOT_STARTED
A381: 010.09.01.01.01 | B381: 010 | C381: Air Law and ATC Procedures | D381: Describe the intent of the AD reference code and state the functions of the two code elements. | E381: N | G381: ICAO Annex 14, Volume 1, Chapter 1, 1.6 Aerodrome Reference Code; see also CS ADR-DSN, Chapter A (CS ADR-DSN.A.005) | H381: MED | I381: NOT_STARTED
A382: 010.09.02.01.01 | B382: 010 | C382: Air Law and ATC Procedures | D382: Describe where the AD reference point shall be located and where it shall normally remain. | E382: N | G382: ICAO Annex 14, Volume 1, Chapter 2, 2.2 Aerodrome reference point; AMC/GM to Reg. (EU) 139/2014 as amended, GM1 ADR.OPS.A.005 | H382: MED | I382: NOT_STARTED
A383: 010.09.02.02.01 | B383: 010 | C383: Air Law and ATC Procedures | D383: Explain the terms: ‘pavement classification number (PCN)’ and ‘aircraft classification number (ACN)’, and describe their mutual dependence. | E383: N | F383: Pavement strength (EU still ACN/PCN, not aligned to ICAO Annex 14 Ch 2.6) | G383: The LO is no longer in line with the current provisions of ICAO Annex 14, Volume 1, Chapter 2, 2.6 Strength of pavements. The ECQB/Subject 010 does not cover this LO. | H383: HIGH | I383: NOT_STARTED
A384: 010.09.02.02.02 | B384: 010 | C384: Air Law and ATC Procedures | D384: Describe how the bearing strength for an aircraft with an apron mass equal to or less than 5 700 kg shall be reported. | E384: N | G384: ICAO Annex 14, Volume 1, Chapter 2, 2.6.8. This aspect of the ICAO Annex 14 provisions has not been amended | H384: MED | I384: NOT_STARTED
A385: 010.09.02.03.01 | B385: 010 | C385: Air Law and ATC Procedures | D385: State that ICAO Annex 14 provides guidance on the calculation of declared distances (TORA, TODA, ASDA, LDA). | E385: N | G385: ICAO Annex 14, Volume 1, Attachment A, 3. Calculation of declared distances; AMC/GM to Reg. (EU) 139/2014 as amended, GM1 ADR.OPS.A.005 | H385: MED | I385: NOT_STARTED
A386: 010.09.02.03.02 | B386: 010 | C386: Air Law and ATC Procedures | D386: Recall the definitions for the four main declared distances. | E386: N | G386: ICAO Annex 14, Volume 1, Chapter 1, 1.1 Definitions; Reg. (EU) 139/2014 as amended, Annex I Definitions | H386: MED | I386: NOT_STARTED
A387: 010.09.02.04.01 | B387: 010 | C387: Air Law and ATC Procedures | D387: State the purpose of informing AIS and ATS units about the condition of the movement area and related facilities. | E387: N | G387: ICAO Annex 14, Volume 1, Chapter 2, 2.9 Condition of the movement area and related facilities; Reg. (EU) 139/2014 as amended, ADR.OPS.A.015; ADR.OPS.B.015 | H387: MED | I387: NOT_STARTED
A388: 010.09.02.04.02 | B388: 010 | C388: Air Law and ATC Procedures | D388: List the matters of operational significance or affecting aircraft performance which should be reported to AIS and ATS units to be transmitted to aircraft involved. | E388: N | G388: ICAO Annex 14, Volume 1, Chapter 2, 2.9.2 Condition of the movement area and related facilities; AMC/GM to Reg. (EU) 139/2014 AMC1 ADR.OPS.A.015 | H388: MED | I388: NOT_STARTED
A389: 010.09.02.04.03 | B389: 010 | C389: Air Law and ATC Procedures | D389: Describe the different types of contaminant on RWYs. | E389: N | G389: ICAO Annex 14, Volume 1, Chapter 2, 2.9.5 Condition of the movement area and related facilities; Reg. (EU) 139/2014 as amended, ADR.OPS.A.065 | H389: MED | I389: NOT_STARTED
A390: 010.09.02.04.04 | B390: 010 | C390: Air Law and ATC Procedures | D390: Explain the different types of frozen water on the RWY and their impact on aircraft braking performance. | E390: N | G390: ICAO Annex 14, Volume 1, Chapter 1, 1.1 Definitions and Chapter 2, 2.9 Condition of the movement area and related facilities Reg. (EU) 139/2014 as amended, Annex I Definitions; ICAO Doc 9981, Part II, Table II-2-5; AMC/GM to Reg. (EU) 139/2014 AMC1 ADR.OPS.B.037(a) | H390: MED | I390: NOT_STARTED
A391: 010.09.02.04.05 | B391: 010 | C391: Air Law and ATC Procedures | D391: Describe the runway condition codes and the associated runway braking action. | E391: N | G391: ICAO Annex 14, Volume 1, Attachment A, 6. Runway condition report for reporting runway surface condition; ICAO Doc 9981, Part II, Table II-2-5; AMC/GM to Reg. (EU) 139/2014 as amended, AMC1 ADR.OPS.B.037(a); AMC/GM to Part-CAT, AMC1 CAT.OP.MPA.311 | H391: MED | I391: NOT_STARTED
A392: 010.09.03.01.01 | B392: 010 | C392: Air Law and ATC Procedures | D392: Describe where a THR should normally be located. | E392: N | G392: ICAO Annex 14, Volume 1, Chapter 3, 3.1.5 and 3.1.6 Location of threshold; CS ADR-DSN.B.030; GM1 ADR-DSN.B.030, (a) - (c) | H392: MED | I392: NOT_STARTED
A393: 010.09.03.01.02 | B393: 010 | C393: Air Law and ATC Procedures | D393: Describe the general considerations concerning RWYs associated with a stopway (SWY) or clearway (CWY). | E393: N | G393: ICAO Annex 14, Volume 1, Chapter 3, 3.1.9 Runways with stopways or clearways; GM1 ADR-DSN.B.035, CS ADR-DSN.B.040; GM1 ADR-DSN.B.040; GM1 ADR.OPS.A.005 | H393: MED | I393: NOT_STARTED
A394: 010.09.03.02.01 | B394: 010 | C394: Air Law and ATC Procedures | D394: Explain the term ‘runway strip’. | E394: N | G394: ICAO Annex 14, Volume 1, Chapter 1 Definitions; Chapter 3, 3.4 General, 3.4.1; see also Reg. (EU) 139/2014 Annex I Definitions; CS ADR-DSN, CS ADR.DSN.A.002 Definitions; Chapter B, CS ADR-DSN.B.150 | H394: MED | I394: NOT_STARTED
A395: 010.09.03.03.01 | B395: 010 | C395: Air Law and ATC Procedures | D395: Explain the term ‘runway-end safety area’. | E395: N | G395: ICAO Annex 14, Volume 1, Chapter 1, Definitions; Chapter 3, 3.5 Runway end safety area 3.5.1 and 3.5.2; see also Reg. (EU) 139/2014 Annex I Definitions; CS ADR.DSN.A.002 Definitions; Chapter C, CS ADR-DSN.C.210 | H395: MED | I395: NOT_STARTED
... A405: 010.09.04.01.02 | B405: 010 | C405: Air Law and ATC Procedures | D405: Describe a landing-direction indicator. | E405: N | G405: ICAO Annex 14, Volume 1, Chapter 5, 5.1.2 Landing direction indicator; CS ADR-DSN.K.495 | H405: MED | I405: NOT_STARTED
A406: 010.09.04.01.03 | B406: 010 | C406: Air Law and ATC Procedures | D406: Explain the capabilities of a signalling lamp. | E406: N | H406: MED | I406: NOT_STARTED
...

Sheet S010
A1: 010 Air Law and ATC Procedures
A3: LO_ID | B3: Level | C3: LO_Text | D3: BK_Only | E3: ECQB_2026_Change_Flag | F3: ECQB_2026_Source_Note | G3: Priority | H3: Content_Type_Planned | I3: Repo_Path | J3: Agent_Assigned | K3: Coverage_Status | L3: Last_Updated | M3: Reviewed_By | N3: Notes
A4: 010.01.00.00 | B4: 2 | C4: INTERNATIONAL LAW: CONVENTIONS, AGREEMENTS AND ORGANISATIONS
A5: 010.01.01.00 | B5: 3 | C5: The Convention on International Civil Aviation (Chicago) - ICAO Doc 7300/9 - Convention on the High Seas (Geneva, 29 April 1958)
A6: 010.01.01.01 | B6: 4 | C6: The establishment of the Convention on International Civil Aviation, Chicago, 7 December 1944
A7: 010.01.01.01.01 | B7: 5 | C7: Explain the circumstances that led to the establishment of the Convention on International Civil Aviation, Chicago, 7 December 1944. | D7: Y | F7: ICAO Doc 7300/9 Preamble | G7: LOW | K7: NOT_STARTED
A8: 010.01.01.02 | B8: 4 | C8: Part I - Air navigation
A9: 010.01.01.02.01 | B9: 5 | C9: Recall the general contents of relevant parts of the following chapters: general principles and application of the Convention; flight over territory of Contracting States; nationality of aircraft; international standards and recommended practices (SARPs), especially notification of differences and validity of endorsed certificates and licences. | D9: Y | F9: ICAO Doc 7300/9 Part 1, Articles 1, 2, 3, 4, 5, 6, 7, 8, 9, 10, 11, 12, 16, 17, 18, 19, 20, 37, 38, 39, 40 | G9: LOW | K9: NOT_STARTED
A10: 010.01.01.02.02 | B10: 5 | C10: General principles - Describe the application of the following terms in civil aviation: sovereignty; territory and high seas according to the UN Convention on the High Seas. | D10: Y | F10: Convention on the High Seas (Geneva, 29 April 1958) Articles 1, 2; ICAO Doc 7300/9 Part 1, Articles 1, 2 | G10: LOW | K10: NOT_STARTED
A11: 010.01.01.02.03 | B11: 5 | C11: Explain the following terms and how they apply to international air traffic: right of non-scheduled flight (including the two technical freedoms of the air); scheduled air services; cabotage; landing at customs airports; Rules of the Air; search of aircraft. | D11: N | F11: ICAO Doc 7300/9, Articles 5, 6, 7, 10, 12, 16 | G11: MED | K11: NOT_STARTED
A12: 010.01.01.02.04 | B12: 5 | C12: Explain the duties of Contracting States in relation to: documents carried on board the aircraft: certificate of registration; certificates of airworthiness; licences of personnel; recognition of certificates and licences; cargo restrictions; photographic apparatus. | D12: Y | F12: ICAO Doc 7300/9, Articles 29, 31, 32, 33, 35, 36 | G12: LOW | K12: NOT_STARTED
A13: 010.01.01.03 | B13: 4 | C13: Part II - The International Civil Aviation Organization (ICAO)
A14: 010.01.01.03.01 | B14: 5 | C14: Describe the objectives of ICAO. | D14: Y | F14: ICAO Doc 7300/9, Article 44 | G14: LOW | K14: NOT_STARTED
A15: 010.01.01.03.02 | B15: 5 | C15: Recognise the organisation and duties of the ICAO Assembly, Council and Air Navigation Commission (ANC). | D15: Y | F15: ICAO Doc 7300/9, Articles 48, 49, 50, 54, 56, 57 | G15: LOW | K15: NOT_STARTED
A16: 010.01.01.03.03 | B16: 5 | C16: Describe the annexes to the Convention. | D16: Y | F16: ICAO Doc 7300/9, Articles 54, 90, 94, 95 | G16: LOW | K16: NOT_STARTED
A17: 010.01.02.00 | B17: 3 | C17: Other conventions and agreements
A18: 010.01.02.01 | B18: 4 | C18: The International Air Services Transit Agreement (ICAO Doc 7500)
A19: 010.01.02.01.01 | B19: 5 | C19: Explain the two technical freedoms of the air. | D19: N | F19: ICAO Doc 7500, Art. 1 | G19: MED | K19: NOT_STARTED
A20: 010.01.02.02 | B20: 4 | C20: The International Air Transport Agreement (ICAO Doc 9626)
A21: 010.01.02.02.01 | B21: 5 | C21: Explain the three commercial freedoms of the air. | D21: N | F21: ICAO Doc 9626, Part IV, Chapter 2 'Basic market access' | G21: MED | K21: NOT_STARTED
A22: 010.01.02.03 | B22: 4 | C22: Suppression of Unlawful Acts Against the Safety of Civil Aviation - The Tokyo Convention of 1963
A23: 010.01.02.03.01 | B23: 5 | C23: Describe the measures and actions to be taken by the pilot-in-command (PIC) of an aircraft in order to suppress unlawful acts against the safety of the aircraft. | D23: N | F23: ICAO Doc 8364 — Convention on Offences and Certain Other Acts Committed on Board Aircraft, signed in Tokyo on 14 September 1963, Chapter III 'Powers of the Commander' | G23: MED | K23: NOT_STARTED
A24: 010.01.02.04 | B24: 4 | C24: Intentionally left blank
A25: 010.01.02.05 | B25: 4 | C25: Private international law
A26: 010.01.02.05.01 | B26: 5 | C26: Explain the legal significance of the issue of a passenger ticket or of baggage/cargo documents (that the issue is a form of contract). | D26: N | F26: ICAO Doc 9740 Convention for the Unification of Certain Rules for International Carriage — The Montreal Convention of 1999 | G26: MED | K26: NOT_STARTED
A27: 010.01.02.05.02 | B27: 5 | C27: Describe the consequences for an airline or the PIC when a document of carriage is not issued (that the contract is unaffected). | D27: N | F27: ICAO Doc 9740 Convention for the Unification of Certain Rules for International Carriage — The Montreal Convention of 1999 | G27: MED | K27: NOT_STARTED
A28: 010.01.02.05.03 | B28: 5 | C28: Explain the consequences for an airline operator of Regulation (EC) No 261/2004 on passenger rights in the event of delay, cancellation or denial of boarding. | D28: Y | F28: Regulation (EC) No 261/2004 | G28: LOW | K28: NOT_STARTED
A29: 010.01.02.05.04 | B29: 5 | C29: Explain the liability limit in relation to destruction, loss, damage or delay of baggage. | D29: N | F29: ICAO Doc 9740 Convention for the Unification of Certain Rules for International Carriage - The Montreal Convention of 1999, Chapter III, Art. 17, 19, 22 | G29: MED | K29: NOT_STARTED
A30: 010.01.03.00 | B30: 3 | C30: World organisations
A31: 010.01.03.01 | B31: 4 | C31: The International Air Transport Association (IATA)
A32: 010.01.03.01.01 | B32: 5 | C32: Describe the objectives of IATA. | D32: N | F32: Available via https://www.iata.org/en/about/mission/ | G32: MED | K32: NOT_STARTED
A33: 010.01.04.00 | B33: 3 | C33: European organisations
A34: 010.01.04.01 | B34: 4 | C34: European Union Aviation Safety Agency (EASA) Regulation (EU) 2018/1139 | F34: https://www.easa.europa.eu/en/the-agency/the-agency
A35: 010.01.04.01.01 | B35: 5 | C35: Describe the objectives of EASA. | D35: Y | G35: LOW | K35: NOT_STARTED
A36: 010.01.04.01.02 | B36: 5 | C36: Describe the role of EASA in European civil aviation. | D36: N | G36: MED | K36: NOT_STARTED
A37: 010.01.04.01.03 | B37: 5 | C37: State that the structure of the regulatory material related to EASA involves: hard law (regulations, delegated acts, implementing acts, and implementing rules); soft law (certification specifications, acceptable means of compliance, and guidance material). | D37: N | F37: See https://www.easa.europa.eu/en/light/topics/easas-regulatory-role-increasing-safety-environmental-protection-and-enabling | G37: MED | K37: NOT_STARTED
A38: 010.01.04.01.04 | B38: 5 | C38: State the meaning of the terminology associated with the structure of the regulatory material related to EASA, specifically: regulations, delegated acts, implementing acts, and implementing rules, as applicable until 11 September 2023; and certification specifications, acceptable means of compliance, and guidance material. | D38: N | F38: See https://commission.europa.eu/law/law-making-process/adopting-eu-law/implementing-and-delegated-acts_en and https://www.easa.europa.eu/en/light/topics/easas-regulatory-role-increasing-safety-environmental-protection-and-enabling | G38: MED | K38: NOT_STARTED
A39: 010.01.04.02 | B39: 4 | C39: EUROCONTROL
A40: 010.01.04.02.01 | B40: 5 | C40: Describe the Single European Sky (SES) regulations. | D40: Y | F40: See https://eur-lex.europa.eu/EN/legal-content/summary/single-european-sky-ses.html | G40: LOW | K40: NOT_STARTED
A41: 010.02.00.00 | B41: 2 | C41: AIRWORTHINESS OF AIRCRAFT, AIRCRAFT NATIONALITY AND REGISTRATION MARKS
A42: 010.02.01.00 | B42: 3 | C42: Intentionally left blank
A43: 010.02.02.00 | B43: 3 | C43: Certificate of Airworthiness (CofA)
A44: 010.02.02.01 | B44: 4 | C44: Certificate of Airworthiness (CofA) - Details
A45: 010.02.02.01.01 | B45: 5 | C45: State the issuing authority of a CofA. | D45: N | F45: ICAO Annex 8, Part II, Chapter 3.2 Eligibility, issuance and continued validity of a Certificate of Airworthiness; Reg. (EU) 748/2012, Part-21, 21.B.326; Appendix IV to Part-21. | G45: MED | K45: NOT_STARTED
A46: 010.02.02.01.02 | B46: 5 | C46: State the necessity to hold a CofA. | D46: N | F46: ICAO Doc 7300, Article 31 | G46: MED | K46: NOT_STARTED
A47: 010.02.02.01.03 | B47: 5 | C47: Explain the prerequisites for the issue of a CofA according to Commission Regulation (EU) No 748/2012. | D47: Y | F47: Reg. (EU) 748/2012, Part 21, Subpart H | G47: LOW | K47: NOT_STARTED
A48: 010.02.02.01.04 | B48: 5 | C48: State who shall determine an aircraft’s continuing airworthiness. | D48: N | F48: ICAO Annex 8, Part II, Chapter 3.2 Eligibility, issuance and continued validity of a Certificate of Airworthiness; Reg. (EU) 748/2012, Part-21, 21.B.325; Appendix IV to Part-21 | G48: MED | K48: NOT_STARTED
A49: 010.02.02.01.05 | B49: 5 | C49: Describe how a CofA can be renewed or may remain valid. | D49: N | F49: Note ICAO Annex 8 refers to renewal, EU Regulation refers to continuing validity. ICAO Annex 8, Part II, Chapter 3.2 Eligibility, issuance and continued validity of a Certificate of Airworthiness; Chapter 3.5 Temporary loss of airworthiness; Chapter 3.6 Damage to aircraft; Reg. (EU) 2018/1139, Arti. 14; Reg. (EU) 748/2012 as amended, Part-21, 21.B.325, 21.B.326; Appendix IV to Part-21 | G49: MED | K49: NOT_STARTED
A50: 010.02.03.00 | B50: 3 | C50: ICAO Annex 7 - Aircraft Nationality and Registration Marks
A51: 010.02.03.01 | B51: 4 | C51: ICAO Annex 7 - Definitions
A52: 010.02.03.01.01 | B52: 5 | C52: Recall the definition of the following terms: aircraft; heavier-than-air aircraft; State of Registry. | D52: Y | F52: ICAO Annex 7, Chapter 1 Definitions | G52: LOW | K52: NOT_STARTED
A53: 010.02.04.00 | B53: 3 | C53: Nationality marks, common marks and registration marks
A54: 010.02.04.01 | B54: 4 | C54: Nationality marks, common marks and registration marks - assignment and location | F54: ICAO Annex 7
A55: 010.02.04.01.01 | B55: 5 | C55: State the location of nationality marks, common marks and registration marks. | D55: N | F55: ICAO Annex 7, Chapter 4.3 Heavier-than-air aircraft; ICAO Annex 7, Chapter 10 Identification plate | G55: MED | K55: NOT_STARTED
A56: 010.02.04.01.02 | B56: 5 | C56: Explain who is responsible for assigning nationality marks, common marks and registration marks. | D56: N | F56: ICAO Annex 7, Chapter 3 Nationality, common and registration marks to be used | G56: MED | K56: NOT_STARTED
A57: 010.03.00.00 | B57: 2 | C57: Intentionally left blank
A58: 010.04.00.00 | B58: 2 | C58: PERSONNEL LICENSING
A59: 010.04.01.00 | B59: 3 | C59: ICAO Annex 1
A60: 010.04.01.01 | B60: 4 | C60: Differences between ICAO Annex 1 and Regulation (EU) No 1178/2011 (hereinafter: Aircrew Regulation)
A61: 010.04.01.01.01 | B61: 5 | C61: Describe the relationship and differences between ICAO Annex 1 and the Aircrew Regulation. | D61: Y | F61: Note: awareness of the differences in scope, non-ICAO licence/ratings as per the Aircrew Regulation: ICAO Annex 1, 1.2, Note; Reg. (EU) 2018/1139 Art. 2 'Scope'; Reg. (EU) 1178/2011 as amended as amended, Appendix I to Part-ARA licence template | G61: LOW | K61: NOT_STARTED
A62: 010.04.02.00 | B62: 3 | C62: Aircrew Regulation - Annex I (Part-FCL) Source: Aircrew Regulation
A63: 010.04.02.01 | B63: 4 | C63: Definitions
A64: 010.04.02.01.01 | B64: 5 | C64: Define the following: Category, class and type of aircraft, cross-country, dual instruction time, flight time, student pilot-in-command (SPIC), instrument time, instrument flight time, instrument ground time, night, private pilot, proficiency check, renewal, revalidation, skill test, solo flight time. | D64: N | F64: Reg. (EU) 1178/2011 as amended, FCL.010 Definitions | G64: MED | K64: NOT_STARTED
A65: 010.04.02.01.02 | B65: 5 | C65: Define the following: multi-crew cooperation (MCC), multi-pilot aircraft, rating. | D65: N | F65: Reg. (EU) 1178/2011 as amended, FCL.010 Definitions; Note: 'rating' is defined in point 1.1 Definitions of ICAO Annex 1 | G65: MED | K65: NOT_STARTED
A66: 010.04.02.02 | B66: 4 | C66: Content and structure
A67: 010.04.02.02.01 | B67: 5 | C67: Explain the structure of Part-FCL. | D67: Y | F67: Reg. (EU) 1178/2011 as amended, Article 1 Subject matter | G67: LOW | K67: NOT_STARTED
A68: 010.04.02.02.02 | B68: 5 | C68: Explain the requirements to act as a flight crew member of a civil aircraft registered in a Member State, and know the general principles of the licensing system (light aircraft pilot licence (LAPL), private pilot licence (PPL), commercial pilot licence (CPL), multi-crew pilot licence (MPL), airline transport pilot licence (ATPL)). | D68: N | F68: Reg. (EU) 2018/1139, Article 21 and point 2 of Annex IV ‘Essential requirements for aircrew’ to this Regulation; Reg. (EU) 1178/2011 as amended, FCL.015 Application and issue, revalidation and renewal of licences, ratings and certificates | G68: MED | K68: NOT_STARTED
A69: 010.04.02.02.03 | B69: 5 | C69: List the two factors that are relevant to the exercise of the privileges of a licence. | D69: Y | F69: Reg. (EU) 1178/2011 as amended, FCL.040 Exercise of the privileges of licences | G69: LOW | K69: NOT_STARTED
A70: 010.04.02.02.04 | B70: 5 | C70: State the circumstances in which a language proficiency endorsement is required. | D70: Y | F70: Reg. (EU) 1178/2011 as amended, FCL.055 Language proficiency | G70: LOW | K70: NOT_STARTED
A71: 010.04.02.02.05 | B71: 5 | C71: List the restrictions for licence holders with an age of 60 years or more. | D71: Y | F71: Reg. (EU) 1178/2011 as amended, FCL.065 Curtailment of privileges of licence holders aged 60 years or more in commercial air transport | G71: LOW | K71: NOT_STARTED
A72: 010.04.02.02.06 | B72: 5 | C72: Explain the term ‘competent authority’. | D72: Y | F72: Reg. (EU) 1178/2011 as amended, FCL.001 Competent authority | G72: LOW | K72: NOT_STARTED
A73: 010.04.02.02.07 | B73: 5 | C73: Describe the obligation to carry and present documents (e.g. a flight crew licence) under Part-FCL. | D73: N | F73: Reg. (EU) 1178/2011 as amended, FCL.045 Obligation to carry and present documents | G73: MED | K73: NOT_STARTED
A74: 010.04.02.03 | B74: 4 | C74: Commercial pilot licence (CPL)
A75: 010.04.02.03.01 | B75: 5 | C75: State the requirements for the issue of a CPL. | D75: Y | F75: Reg. (EU) 1178/2011 as amended, FCL.300 CPL — Minimum age; Appendix 3, D. CPL integrated course — Aeroplanes, Flying Training (8, a–f); Appendix 3, E. CPL modular course — Aeroplanes, Experience (12, a–e) | G75: LOW | K75: NOT_STARTED
A76: 010.04.02.03.02 | B76: 5 | C76: State the privileges of a CPL. | D76: N | F76: Reg. (EU) 1178/2011 as amended, FCL.305 CPL — Privileges and conditions | G76: MED | K76: NOT_STARTED
A77: 010.04.02.04 | B77: 4 | C77: Airline transport pilot licence (ATPL) and multi-crew pilot licence (MPL)
A78: 010.04.02.04.01 | B78: 5 | C78: State the requirements for the issue of an ATPL. | D78: Y | F78: Reg. (EU) 1178/2011 as amended, FCL.500 ATPL — Minimum age; FCL.510.A ATPL(A) — Prerequisites, experience and crediting ((a) and (b)); FCL.510.H ATPL(H) — Prerequisites, experience and crediting | G78: LOW | K78: NOT_STARTED
A79: 010.04.02.04.02 | B79: 5 | C79: State the privileges of an ATPL. | D79: N | F79: Reg. (EU) 1178/2011 as amended, FCL.505 ATPL — Privileges | G79: MED | K79: NOT_STARTED
A80: 010.04.02.04.03 | B80: 5 | C80: State the requirements for the issue of an MPL. | D80: Y | F80: Reg. (EU) 1178/2011 as amended, FCL.400.A MPL — Minimum age; FCL.410.A MPL — Training course and theoretical knowledge examinations and Appendix 5 (items 1 to 8) | G80: LOW | K80: NOT_STARTED
A81: 010.04.02.04.04 | B81: 5 | C81: State the privileges of an MPL. | D81: N | F81: Reg. (EU) 1178/2011 as amended, FCL.405.A MPL — Privileges | G81: MED | K81: NOT_STARTED
A82: 010.04.02.05 | B82: 4 | C82: Ratings
A83: 010.04.02.05.01 | B83: 5 | C83: State the requirements for class ratings, their validity and privileges. | D83: N | F83: Reg. (EU) 1178/2011 as amended, FCL.740 Validity and renewal of class and type ratings; FCL.705 Privileges of the holder of a class or type rating; FCL.720.A Experience requirements and prerequisites for the issue of class or type ratings — aeroplanes | G83: MED | K83: NOT_STARTED
A84: 010.04.02.05.02 | B84: 5 | C84: State the requirements for type ratings, their validity and privileges. | D84: N | F84: Reg. (EU) 1178/2011 as amended, FCL.705 Privileges of the holder of a class or type rating; FCL.720.A / FCL.720.H Experience requirements and prerequisites for the issue; FCL.740 Validity and renewal of class and type ratings; FCL.740.A / FCL.740.H Revalidation | G84: MED | K84: NOT_STARTED
A85: 010.04.02.05.03 | B85: 5 | C85: State the requirements for instrument ratings, their validity and privileges (instrument rating (IR), competency-based instrument rating (CB-IR) and basic instrument rating (BIR). | D85: N | F85: Reg. (EU) 1178/2011 as amended, FCL.610 IR — Prerequisites and crediting; FCL.605 IR — Privileges and conditions; FCL.625 IR — Validity, revalidation and renewal FCL.835 Basic instrument rating (BIR) | G85: MED | K85: NOT_STARTED
A86: 010.04.02.05.04 | B86: 5 | C86: State the requirements for other ratings, their validity and privileges according to Part-FCL. | D86: N | F86: Reg. (EU) 1178/2011 as amended, FCL.800 Aerobatic rating; FCL.805 Sailplane towing and banner towing ratings; FCL.810 Night rating; FCL.815 Mountain rating; FCL.820 Flight test rating. | G86: MED | K86: NOT_STARTED
A87: 010.04.03.00 | B87: 3 | C87: Aircrew Regulation - Annex IV (Part-MED)
A88: 010.04.03.01 | B88: 4 | C88: Aircrew Regulation - Annex IV (Part-MED) - Details
A89: 010.04.03.01.01 | B89: 5 | C89: Describe the relevant content of Part-MED - Medical requirements (administrative parts and requirements related to licensing only). | D89: Y | F89: Reg. (EU) 1178/2011 as amended, MED.A.001 Competent authority; MED.A.005 Scope; MED.A.045 Validity, revalidation and renewal of medical certificates | G89: LOW | K89: NOT_STARTED
A90: 010.04.03.01.02 | B90: 5 | C90: State the requirements for the issue of a medical certificate. | D90: N | F90: Reg. (EU) 1178/2011 as amended, MED.A.040 Issue, revalidation and renewal of medical certificates | G90: MED | K90: NOT_STARTED
A91: 010.04.03.01.03 | B91: 5 | C91: Name the class of medical certificate required when exercising the privileges of a CPL, MPL or ATPL. | D91: N | F91: Reg. (EU) 1178/2011 as amended, MED.A.030 Medical certificates | G91: MED | K91: NOT_STARTED
A92: 010.04.03.01.04 | B92: 5 | C92: State the actions to be taken in case of a decrease in medical fitness. | D92: N | F92: Reg. (EU) 1178/2011 as amended, MED.A.020 Decrease in medical fitness | G92: MED | K92: NOT_STARTED
A93: 010.05.00.00 | B93: 2 | C93: RULES OF THE AIR ACCORDING TO ICAO ANNEX 2 AND SERA
A94: 010.05.01.00 | B94: 3 | C94: Overview of ICAO Annex 2 and SERA (Commission Implementing Regulation (EU) No 923/2012 and its references and subsequent amendments)
A95: 010.05.01.01 | B95: 4 | C95: ICAO Annex 2 and SERA - Relationship and content
A96: 010.05.01.01.01 | B96: 5 | C96: Explain the scope and purpose of ICAO Annex 2. | D96: N | F96: ICAO Annex 2, Foreword, Applicability | G96: MED | K96: NOT_STARTED
A97: 010.05.01.01.02 | B97: 5 | C97: Explain the scope and main content of SERA. | D97: N | F97: Reg. (EU) 923/2012 SERA as amended, Article 1 Subject matter and scope | G97: MED | K97: NOT_STARTED
A98: 010.05.02.00 | B98: 3 | C98: Rules of the Air
A99: 010.05.02.01 | B99: 4 | C99: Applicability of the Rules of the Air
A100: 010.05.02.01.01 | B100: 5 | C100: Explain the principle of territorial application of the various Rules of the Air, e.g. ICAO, SERA, national rules. | D100: N | F100: ICAO Annex 2, Chapter 2, 2.1 Territorial application of the rules of the air; Article 1 'Subject matter and scope'; Reg. (EU) 923/2012 as amended, SERA.1001, SERA.2001 | G100: MED | K100: NOT_STARTED
A101: 010.05.02.01.02 | B101: 5 | C101: Explain the necessity to comply with the Rules of the Air. | D101: N | F101: Reg. (EU) 923/2012 as amended, SERA.2005 Compliance with the rules of the air, associated GM | G101: MED | K101: NOT_STARTED
...

Sheet S021
A1: 021 Aircraft General Knowledge — Airframe, Systems, Powerplant
A3: LO_ID | B3: Level | C3: LO_Text | D3: BK_Only | E3: ECQB_2026_Change_Flag | F3: ECQB_2026_Source_Note | G3: Priority | H3: Content_Type_Planned | I3: Repo_Path | J3: Agent_Assigned | K3: Coverage_Status | L3: Last_Updated | M3: Reviewed_By | N3: Notes
A4: 021.01.00.00 | B4: 2 | C4: SYSTEM DESIGN, LOADS, STRESSES, MAINTENANCE
A5: 021.01.01.00 | B5: 3 | C5: System design
A6: 021.01.01.01 | B6: 4 | C6: Design concepts
A7: 021.01.01.01.01 | B7: 5 | C7: Describe the following structural design philosophy: safe life; fail-safe (multiple load paths); damage-tolerant. | D7: Y | G7: LOW | K7: NOT_STARTED
A8: 021.01.01.01.02 | B8: 5 | C8: Explain the purpose of redundancy in aircraft design. | D8: N | G8: MED | K8: NOT_STARTED
A9: 021.01.01.02 | B9: 4 | C9: Level of certification
A10: 021.01.01.02.01 | B10: 5 | C10: Explain why some systems are duplicated or triplicated. | D10: Y | G10: LOW | K10: NOT_STARTED
A11: 021.01.01.02.02 | B11: 5 | C11: Explain that all aircraft are certified according to specifications determined by the competent authority, and that these certification specifications cover aspects such as design, material quality and build quality. | D11: Y | G11: LOW | K11: NOT_STARTED
A12: 021.01.01.02.03 | B12: 5 | C12: State that the certification specifications for aeroplanes issued by EASA are: CS-23 for Normal, Utility, Aerobatic and Commuter Aeroplanes; CS-25 for Large Aeroplanes. | D12: Y | G12: LOW | K12: NOT_STARTED
A13: 021.01.02.00 | B13: 3 | C13: Loads and stresses
A14: 021.01.02.01 | B14: 4 | C14: Stress, strain and loads
A15: 021.01.02.01.01 | B15: 5 | C15: Explain how stress and strain are always present in an aircraft structure both when parked and during manoeuvring. Remark: Stress is the internal force per unit area inside a structural part as a result of external loads. Strain is the deformation caused by the action of stress on a material. | D15: N | G15: MED | K15: NOT_STARTED
A16: 021.01.02.01.02 | B16: 5 | C16: Describe the following types of loads that an aircraft may be subjected to, when they occur, and how a pilot may affect their magnitude: static loads; dynamic loads; cyclic loads. | D16: N | G16: MED | K16: NOT_STARTED
A17: 021.01.02.01.03 | B17: 5 | C17: Describe the areas typically prone to stress that should be given particular attention during a pre-flight inspection, and highlight the limited visual cues of any deformation that may be evident. | D17: N | G17: MED | K17: NOT_STARTED
A18: 021.01.03.00 | B18: 3 | C18: Fatigue and corrosion
A19: 021.01.03.01 | B19: 4 | C19: Describe and explain fatigue and corrosion
A20: 021.01.03.01.01 | B20: 5 | C20: Describe the effects of corrosion and how it can be visually identified by a pilot during the pre-flight inspection. | D20: N | G20: MED | K20: NOT_STARTED
A21: 021.01.03.01.02 | B21: 5 | C21: Describe the operating environments where the risk of corrosion is increased and how to minimise the effects of the environmental factors. | D21: N | G21: MED | K21: NOT_STARTED
A22: 021.01.03.01.03 | B22: 5 | C22: Explain that aircraft have highly corrosive fluids on board as part of their systems and equipment. | D22: N | G22: MED | K22: NOT_STARTED
A23: 021.01.03.01.04 | B23: 5 | C23: Explain fatigue, how it affects the useful life of an aircraft, and the effect of the following factors on the development of fatigue: corrosion; number of cycles; type of flight manoeuvres; stress level; level and quality of maintenance. | D23: N | G23: MED | K23: NOT_STARTED
A24: 021.01.04.00 | B24: 3 | C24: Intentionally left blank
A25: 021.01.05.00 | B25: 3 | C25: Maintenance
A26: 021.01.05.01 | B26: 4 | C26: Maintenance methods: hard-time and on-condition monitoring
A27: 021.01.05.01.01 | B27: 5 | C27: Explain the following terms: hard-time or fixed-time maintenance; on-condition maintenance; condition monitoring. | D27: N | G27: MED | K27: NOT_STARTED
A28: 021.02.00.00 | B28: 2 | C28: AIRFRAME
A29: 021.02.01.00 | B29: 3 | C29: Attachment methods
A30: 021.02.01.01 | B30: 4 | C30: Attachment methods and detecting the development of faulty attachments
A31: 021.02.01.01.01 | B31: 5 | C31: Describe the following attachment methods used for aircraft parts and components: riveting; welding; bolting; pinning; adhesives (bonding); screwing. | D31: N | G31: MED | K31: NOT_STARTED
A32: 021.02.01.01.02 | B32: 5 | C32: Explain how the development of a faulty attachment between aircraft parts or components can be detected by a pilot during the pre-flight inspection. | D32: N | G32: MED | K32: NOT_STARTED
A33: 021.02.02.00 | B33: 3 | C33: Materials
A34: 021.02.02.01 | B34: 4 | C34: Composite and other materials
A35: 021.02.02.01.01 | B35: 5 | C35: Explain the principle of a composite material, and give examples of typical non-metallic materials used on aircraft: carbon; glass; Kevlar aramid; resin or filler. | D35: Y | G35: LOW | K35: NOT_STARTED
A36: 021.02.02.01.02 | B36: 5 | C36: State the advantages and disadvantages of composite materials compared with metal alloys by considering the following: strength-to-weight ratio; capability to tailor the strength to the direction of the load; stiffness; electrical conductivity (lightning); resistance to fatigue and corrosion; resistance to cost; discovering damage during a pre-flight inspection. | D36: Y | G36: LOW | K36: NOT_STARTED
A37: 021.02.02.01.03 | B37: 5 | C37: State that several types of materials are used on aircraft and that they are chosen based on type of structure or component and the required/desired material properties. | D37: N | G37: MED | K37: NOT_STARTED
A38: 021.02.03.00 | B38: 3 | C38: Aeroplane: wings, tail surfaces and control surfaces
A39: 021.02.03.01 | B39: 4 | C39: Design
A40: 021.02.03.01.01 | B40: 5 | C40: Describe the following types of design and explain their advantages and disadvantages: high-mounted wing; low-mounted wing; low- or mid-set tailplane; T-tail. | D40: N | G40: MED | K40: NOT_STARTED
A41: 021.02.03.02 | B41: 4 | C41: Structural components
A42: 021.02.03.02.01 | B42: 5 | C42: Describe the function of the following structural components: spar and its components (web and girder or cap); rib; stringer; skin; torsion box. | D42: N | G42: MED | K42: NOT_STARTED
A43: 021.02.03.03 | B43: 4 | C43: Loads, stresses and aeroelastic vibrations (flutter)
A44: 021.02.03.03.01 | B44: 5 | C44: Describe the vertical and horizontal loads on the ground and during normal flight. | D44: N | G44: MED | K44: NOT_STARTED
A45: 021.02.03.03.02 | B45: 5 | C45: Describe the vertical and horizontal loads during asymmetric flight following an engine failure for a multi-engine aeroplane, and how a pilot may potentially overstress the structure during the failure scenario. | D45: N | G45: MED | K45: NOT_STARTED
A46: 021.02.03.03.03 | B46: 5 | C46: Explain the principle of flutter and resonance for the wing and control surfaces. | D46: N | G46: MED | K46: NOT_STARTED
A47: 021.02.03.03.04 | B47: 5 | C47: Explain the following countermeasures used to achieve stress relief and reduce resonance: chord-wise and span-wise position of masses (e.g. engines, fuel, balance masses for wing and control balance masses); torsional stiffness; bending flexibility; fuel-balancing procedures during flight (automatic or applied by the pilot). | D47: N | G47: MED | K47: NOT_STARTED
A48: 021.02.04.00 | B48: 3 | C48: Fuselage, landing gear, doors, floor, windscreen and windows
A49: 021.02.04.01 | B49: 4 | C49: Construction, functions, loads
A50: 021.02.04.01.01 | B50: 5 | C50: Describe the following types of fuselage construction: monocoque, semi-monocoque. | D50: Y | G50: LOW | K50: NOT_STARTED
A51: 021.02.04.01.02 | B51: 5 | C51: Describe the construction and the function of the following structural components of a fuselage: frames; bulkhead; pressure bulkhead; stiffeners, stringers, longerons; skin, doublers; floor suspension (crossbeams); floor panels; firewall. | D51: N | G51: MED | K51: NOT_STARTED
A52: 021.02.04.01.03 | B52: 5 | C52: Describe the loads on the fuselage due to pressurisation. | D52: N | G52: MED | K52: NOT_STARTED
A53: 021.02.04.01.04 | B53: 5 | C53: Describe the following loads on a main landing gear: touch-down loads (vertical and horizontal); taxi loads on bogie gear (turns). | D53: N | G53: MED | K53: NOT_STARTED
A54: 021.02.04.01.05 | B54: 5 | C54: Describe the structural danger of a nose-wheel landing with respect to: fuselage loads; nose-wheel strut loads. | D54: N | G54: MED | K54: NOT_STARTED
A55: 021.02.04.01.06 | B55: 5 | C55: Describe the structural danger of a tail strike with respect to: fuselage and aft bulkhead damage (pressurisation). | D55: N | G55: MED | K55: NOT_STARTED
A56: 021.02.04.01.07 | B56: 5 | C56: Describe the door and hatch construction for pressurised and unpressurised aeroplanes including: door and frame (plug type); hinge location; locking mechanism. | D56: N | G56: MED | K56: NOT_STARTED
A57: 021.02.04.01.08 | B57: 5 | C57: Explain the advantages and disadvantages of the following fuselage cross sections: circular; double bubble; oval; rectangular. | D57: Y | G57: LOW | K57: NOT_STARTED
A58: 021.02.04.01.09 | B58: 5 | C58: Explain why flight-deck windows are constructed with different layers. | D58: N | G58: MED | K58: NOT_STARTED
A59: 021.02.04.01.10 | B59: 5 | C59: Explain the function of window heating for structural purposes. | D59: N | G59: MED | K59: NOT_STARTED
A60: 021.02.04.01.11 | B60: 5 | C60: Explain the implication of a direct-vision window (see CS 25.773(b)(3)). | D60: N | G60: MED | K60: NOT_STARTED
A61: 021.02.04.01.12 | B61: 5 | C61: Explain the need for an eye-reference position. | D61: N | G61: MED | K61: NOT_STARTED
A62: 021.02.04.01.13 | B62: 5 | C62: Explain the function of floor venting (blow-out panels). | D62: N | G62: MED | K62: NOT_STARTED
A63: 021.02.05.00 | B63: 3 | C63: Helicopter: structural aspects of flight controls
A64: 021.02.05.01 | B64: 4 | C64: Design and construction
A65: 021.02.05.02 | B65: 4 | C65: Structural components and materials
A66: 021.02.05.03 | B66: 4 | C66: Loads, stresses and aeroelastic vibrations
A67: 021.02.06.00 | B67: 3 | C67: Structural limitations
A68: 021.02.06.01 | B68: 4 | C68: Maximum structural masses
A69: 021.02.06.01.01 | B69: 5 | C69: Define and explain the following maximum structural masses: maximum ramp mass; maximum take-off mass; maximum zero fuel mass; maximum landing mass. Remark: These limitations may also be found in the relevant part of Subjects 031 ‘Mass and balance’, 032 ‘Performance (aeroplane)’ and 034 ‘Performance (helicopter)’. | D69: N | G69: MED | K69: NOT_STARTED
A70: 021.02.06.01.02 | B70: 5 | C70: Explain that airframe life is limited by fatigue, created by alternating stress and the number of load cycles. | D70: N | G70: MED | K70: NOT_STARTED
A71: 021.03.00.00 | B71: 2 | C71: HYDRAULICS
A72: 021.03.01.00 | B72: 3 | C72: Hydromechanics: basic principles
A73: 021.03.01.01 | B73: 4 | C73: Concepts and basic principles
A74: 021.03.01.01.01 | B74: 5 | C74: Explain the concept and basic principles of hydromechanics including: hydrostatic pressure; Pascal’s law; the relationship between pressure, force and area; transmission of power: multiplication of force, decrease of displacement. | D74: Y | G74: LOW | K74: NOT_STARTED
A75: 021.03.02.00 | B75: 3 | C75: Hydraulic systems
A76: 021.03.02.01 | B76: 4 | C76: Hydraulic fluids: types, characteristics, limitations
A77: 021.03.02.01.01 | B77: 5 | C77: List and explain the desirable properties of a hydraulic fluid with regard to: thermal stability; corrosiveness; flashpoint and flammability; volatility; viscosity. | D77: Y | G77: LOW | K77: NOT_STARTED
A78: 021.03.02.01.02 | B78: 5 | C78: State that hydraulic fluids are irritating to skin and eyes. | D78: Y | G78: LOW | K78: NOT_STARTED
A79: 021.03.02.01.03 | B79: 5 | C79: List the two different types of hydraulic fluids: synthetic; mineral. | D79: N | G79: MED | K79: NOT_STARTED
A80: 021.03.02.01.04 | B80: 5 | C80: State that different types of hydraulic fluids cannot be mixed. | D80: N | G80: MED | K80: NOT_STARTED
A81: 021.03.02.01.05 | B81: 5 | C81: State that at the pressures being considered, hydraulic fluid is considered incompressible. | D81: Y | G81: LOW | K81: NOT_STARTED
A82: 021.03.02.02 | B82: 4 | C82: System components: design, operation, degraded modes of operation, indications and warnings
A83: 021.03.02.02.01 | B83: 5 | C83: Explain the working principle of a hydraulic system. | D83: N | G83: MED | K83: NOT_STARTED
A84: 021.03.02.02.02 | B84: 5 | C84: Describe the difference in the principle of operation between a constant pressure system and a system pressurised only on specific demand. | D84: N | G84: MED | K84: NOT_STARTED
A85: 021.03.02.02.03 | B85: 5 | C85: State the differences in the principle of operation between a passive hydraulic system (without a pressure pump) and an active hydraulic system (with a pressure pump). | D85: N | G85: MED | K85: NOT_STARTED
A86: 021.03.02.02.04 | B86: 5 | C86: List the main advantages and disadvantages of system actuation by hydraulic or purely mechanical means with respect to: weight; size; force. | D86: Y | G86: LOW | K86: NOT_STARTED
A87: 021.03.02.02.05 | B87: 5 | C87: List the main uses of hydraulic systems. | D87: N | G87: MED | K87: NOT_STARTED
A88: 021.03.02.02.06 | B88: 5 | C88: State that hydraulic systems can be classified as either high pressure (typically 3000 psi or higher) or low pressure (typically up to 2000 psi). | D88: N | G88: MED | K88: NOT_STARTED
A89: 021.03.02.02.07 | B89: 5 | C89: State that a high-pressure hydraulic system is typically operating at 3000 psi but on some aircraft a hydraulic pressure of 4000 to 5000 psi may also be used. | D89: N | G89: MED | K89: NOT_STARTED
A90: 021.03.02.02.08 | B90: 5 | C90: Explain the working principle of a low-pressure (0–2000 psi) system. | D90: N | G90: MED | K90: NOT_STARTED
A91: 021.03.02.02.09 | B91: 5 | C91: Explain the advantages and disadvantages of a high-pressure system over a low-pressure system. | D91: N | G91: MED | K91: NOT_STARTED
A92: 021.03.02.02.10 | B92: 5 | C92: Describe the working principle and functions of pressure pumps including: constant pressure pump (swash plate or cam plate); pressure pump whose output is dependent on pump revolutions per minute (rpm) (gear type). | D92: N | G92: MED | K92: NOT_STARTED
A93: 021.03.02.02.11 | B93: 5 | C93: Explain the following different sources of hydraulic pressure, their typical application and potential operational limitations: manual; engine gearbox; electrical; air (pneumatic and ram-air turbine); hydraulic (power transfer unit) or reversible motor pumps; accessory. | D93: N | G93: MED | K93: NOT_STARTED
A94: 021.03.02.02.13 | B94: 5 | C94: Describe the working principle and functions of the following hydraulic system components: reservoir (pressurised and unpressurised); accumulators; case drain lines and fluid cooler return lines; piston actuators (single- and double-acting); hydraulic motors; filters; non-return (check) valves; relief valves; restrictor valves; elector valves (linear and basic rotary selectors, two and four ports); bypass valves; shuttle valves; fire shut‑off valves; priority valves; fuse valves; pressure and return pipes. | D94: N | G94: MED | K94: NOT_STARTED
... A100: 021.03.02.02.19 | B100: 5 | C100: State the indications and explain the implications of the following malfunctions: system leak or low level; low pressure; high temperature. | D100: N | G100: MED | K100: NOT_STARTED
A101: 021.04.00.00 | B101: 2 | C101: LANDING GEAR, WHEELS, TYRES, BRAKES
A102: 021.04.01.00 | B102: 3 | C102: Landing gear
A103: 021.04.01.01 | B103: 4 | C103: Types
A104: 021.04.01.01.01 | B104: 5 | C104: Name, for an aeroplane, the following different landing-gear configurations: nose wheel; tail wheel. | D104: Y | G104: LOW | K104: NOT_STARTED
A105: 021.04.01.02 | B105: 4 | C105: System components, design, operation, indications and warnings, on-ground/in-flight protections, emergency extension systems
A106: 021.04.01.02.01 | B106: 5 | C106: Explain the function of the following components of a landing gear: oleo leg/shock strut; axles; bogies and bogie beam; drag struts; side stays/struts; torsion links; locks (over centre); gear doors. | D106: N | G106: MED | K106: NOT_STARTED
...

Sheet S022
A1: 022 Aircraft General Knowledge — Instrumentation
A3: LO_ID | B3: Level | C3: LO_Text | D3: BK_Only | E3: ECQB_2026_Change_Flag | F3: ECQB_2026_Source_Note | G3: Priority | H3: Content_Type_Planned | I3: Repo_Path | J3: Agent_Assigned | K3: Coverage_Status | L3: Last_Updated | M3: Reviewed_By | N3: Notes
A4: 022.01.00.00 | B4: 2 | C4: SENSORS AND INSTRUMENTS
A5: 022.01.01.00 | B5: 3 | C5: Pressure gauge
A6: 022.01.01.01 | B6: 4 | C6: Units for pressure, sensor types, measurements
A7: 022.01.01.01.01 | B7: 5 | C7: Define ‘pressure’, ‘absolute pressure’ and ‘differential pressure’. | D7: Y | G7: LOW | K7: NOT_STARTED
A8: 022.01.01.01.02 | B8: 5 | C8: List the following units used for pressure measurement: Pascal; bar; inches of mercury (in Hg); pounds per square inch (psi). | D8: Y | G8: LOW | K8: NOT_STARTED
A9: 022.01.01.01.03 | B9: 5 | C9: State the relationship between the different units. | D9: Y | G9: LOW | K9: NOT_STARTED
A10: 022.01.01.01.04 | B10: 5 | C10: List and describe the following different types of sensors used according to the pressure to be measured: aneroid capsules; bellows; diaphragms; bourdon tube. | D10: N | G10: MED | K10: NOT_STARTED
A11: 022.01.01.01.05 | B11: 5 | C11: Identify pressure measurements that are applicable to an aircraft: liquid-pressure measurement (fuel, oil, hydraulic); air-pressure measurement (bleed-air systems, air-conditioning systems); engine-pressure measurement manifold pressure (MAP), engine pressure ratio (EPR)). | D11: N | G11: MED | K11: NOT_STARTED
A12: 022.01.01.01.06 | B12: 5 | C12: Identify and read pressure measurement indications both for engine indications and other systems. | D12: N | G12: MED | K12: NOT_STARTED
A13: 022.01.01.01.07 | B13: 5 | C13: Explain the implications of the following pressure measurement errors both for engine indications and other systems: loss of pressure sensing; incorrect pressure indications. | D13: N | G13: MED | K13: NOT_STARTED
A14: 022.01.02.00 | B14: 3 | C14: Temperature sensing
A15: 022.01.02.01 | B15: 4 | C15: Units for temperature, measurements
A16: 022.01.02.01.01 | B16: 5 | C16: Explain temperature. | D16: Y | G16: LOW | K16: NOT_STARTED
A17: 022.01.02.01.02 | B17: 5 | C17: List the following units that can be used for temperature measurement: Kelvin; Celsius; Fahrenheit. | D17: Y | G17: LOW | K17: NOT_STARTED
A18: 022.01.02.01.03 | B18: 5 | C18: State the relationship between these units and convert between them. | D18: Y | G18: LOW | K18: NOT_STARTED
A19: 022.01.02.01.04 | B19: 5 | C19: Identify temperature measurements that are applicable to an aircraft: gas temperature measurement (ambient air, bleed-air systems, air-conditioning systems, air inlet, exhaust gas, gas turbine outlets); liquid-temperature measurement (fuel, oil, hydraulic); component-temperature measurement (generator, transformer rectifier unit (TRU), pumps (fuel, hydraulic), power transfer unit (PTU). | D19: N | G19: MED | K19: NOT_STARTED
A20: 022.01.02.01.05 | B20: 5 | C20: Identify and read temperature measurement indications for both engine indications and other systems. | D20: N | G20: MED | K20: NOT_STARTED
A21: 022.01.03.00 | B21: 3 | C21: Fuel gauge
A22: 022.01.03.01 | B22: 4 | C22: Units for fuel, measurements, fuel gauges
A23: 022.01.03.01.01 | B23: 5 | C23: State that the quantity of fuel can be measured by volume or mass. | D23: N | G23: MED | K23: NOT_STARTED
A24: 022.01.03.01.02 | B24: 5 | C24: List the following units used for fuel quantity: kilogramme; pound; litres; gallons (US and imperial). | D24: N | G24: MED | K24: NOT_STARTED
A25: 022.01.03.01.03 | B25: 5 | C25: Convert between the various units. | D25: N | G25: MED | K25: NOT_STARTED
A26: 022.01.03.01.04 | B26: 5 | C26: Explain the parameters that can affect the measurement of the volume or mass of the fuel in a fuel tank: temperature; aircraft accelerations and attitudes; and explain how the fuel-gauge system design compensates for these changes. | D26: N | G26: MED | K26: NOT_STARTED
A27: 022.01.03.01.05 | B27: 5 | C27: Describe and explain the operating principles of the following types of fuel gauges: float system; capacitance-type of fuel-gauge system. ultrasound-type of fuel-gauge system: to be introduced at a later date. | D27: N | G27: MED | K27: NOT_STARTED
A28: 022.01.03.01.06 | B28: 5 | C28: Describe and complete a typical post-refuelling procedure for a pilot: recording the volume that was filled; converting to the appropriate unit used by the aircraft fuel gauge(s) to compare the actual indicated fuel content to the calculated fuel content; assess appropriate action if the numbers does not compare. | D28: N | G28: MED | K28: NOT_STARTED
A29: 022.01.04.00 | B29: 3 | C29: Fuel flowmeters
A30: 022.01.04.01 | B30: 4 | C30: Fuel flow, units for fuel flow, total fuel consumption
A31: 022.01.04.01.01 | B31: 5 | C31: Define ‘fuel flow’ and where it is measured. | D31: N | G31: MED | K31: NOT_STARTED
A32: 022.01.04.01.02 | B32: 5 | C32: State that fuel flow may be measured by volume or mass per unit of time. | D32: N | G32: MED | K32: NOT_STARTED
A33: 022.01.04.01.03 | B33: 5 | C33: List the following units used for fuel flow when measured by mass per hour: kilogrammes/hour; pounds/hour. | D33: N | G33: MED | K33: NOT_STARTED
A34: 022.01.04.01.04 | B34: 5 | C34: List the following units used for fuel flow when measured by volume per hour: litres/hour; imperial gallons/hour; US gallons/hour. | D34: N | G34: MED | K34: NOT_STARTED
A35: 022.01.04.01.05 | B35: 5 | C35: Explain how total fuel consumption is obtained. | D35: N | G35: MED | K35: NOT_STARTED
A36: 022.01.05.00 | B36: 3 | C36: Tachometer
A37: 022.01.05.01 | B37: 4 | C37: Types, operating principles, units for engine speed
A38: 022.01.05.01.01 | B38: 5 | C38: List the following types of tachometers, describe their basic operating principle and give examples of use: mechanical (rotating magnet); electrical (three-phase tacho-generator); electronic (impulse measurement with speed probe and phonic wheel); and describe the operating principle of each type. | D38: Y | G38: LOW | K38: NOT_STARTED
A39: 022.01.05.01.02 | B39: 5 | C39: Explain the typical units for engine speed: rpm for piston-engine aircraft; percentage for turbine-engine aircraft. | D39: N | G39: MED | K39: NOT_STARTED
A40: 022.01.05.01.03 | B40: 5 | C40: Explain that some types of rpm indicators require electrical power to provide an indication. | D40: N | G40: MED | K40: NOT_STARTED
A41: 022.01.06.00 | B41: 3 | C41: Thrust measurement
A42: 022.01.06.01 | B42: 4 | C42: Parameters, operating principle
A43: 022.01.06.01.01 | B43: 5 | C43: List and describe the following two parameters used to represent thrust: N1; EPR. | D43: N | G43: MED | K43: NOT_STARTED
A44: 022.01.06.01.02 | B44: 5 | C44: Explain the operating principle of using an engine with EPR indication and explain the consequences of incorrect or missing EPR to the operation of the engine, including reverting to N1 mode. | D44: N | G44: MED | K44: NOT_STARTED
A45: 022.01.06.01.03 | B45: 5 | C45: Give examples of display for N1 and EPR. | D45: N | G45: MED | K45: NOT_STARTED
A46: 022.01.07.00 | B46: 3 | C46: Engine torquemeter
A47: 022.01.07.01 | B47: 4 | C47: Torque, torquemeters
A48: 022.01.07.01.01 | B48: 5 | C48: Define ‘torque’. | D48: N | G48: MED | K48: NOT_STARTED
A49: 022.01.07.01.02 | B49: 5 | C49: Explain the relationship between power, torque and rpm. | D49: N | G49: MED | K49: NOT_STARTED
A50: 022.01.07.01.03 | B50: 5 | C50: List the following units used for torque: Newton meters; inch or foot pounds. | D50: N | G50: MED | K50: NOT_STARTED
A51: 022.01.07.01.04 | B51: 5 | C51: State that engine torque can be displayed as a percentage. | D51: N | G51: MED | K51: NOT_STARTED
A52: 022.01.07.01.05 | B52: 5 | C52: List and describe the following different types of torquemeters, and explain their operating principles: mechanical; electronic. | D52: Y | G52: LOW | K52: NOT_STARTED
A53: 022.01.07.01.06 | B53: 5 | C53: Compare the two systems with regard to design and weight. | D53: Y | G53: LOW | K53: NOT_STARTED
A54: 022.01.07.01.07 | B54: 5 | C54: Give examples of display. | D54: N | G54: MED | K54: NOT_STARTED
A55: 022.01.08.00 | B55: 3 | C55: Synchroscope
A56: 022.01.08.01 | B56: 4 | C56: Purpose, operating principle, display
A57: 022.01.08.01.01 | B57: 5 | C57: State the purpose of a synchroscope. | D57: N | G57: MED | K57: NOT_STARTED
A58: 022.01.08.01.02 | B58: 5 | C58: Explain the operating principle of a synchroscope. | D58: Y | G58: LOW | K58: NOT_STARTED
A59: 022.01.08.01.03 | B59: 5 | C59: Give examples of display. | D59: N | G59: MED | K59: NOT_STARTED
A60: 022.01.09.00 | B60: 3 | C60: Engine-vibration monitoring
A61: 022.01.09.01 | B61: 4 | C61: Purpose, operating principle of a vibration-monitoring system, display
A62: 022.01.09.01.01 | B62: 5 | C62: State the purpose of a vibration-monitoring system for a jet engine. | D62: N | G62: MED | K62: NOT_STARTED
A63: 022.01.09.01.02 | B63: 5 | C63: Describe the operating principle of a vibration-monitoring system using the following two types of sensors: piezoelectric crystal; magnet. | D63: Y | G63: LOW | K63: NOT_STARTED
A64: 022.01.09.01.03 | B64: 5 | C64: Explain that there is no specific unit for vibration monitoring, i.e. it is determined by specified numeric threshold values. | D64: N | G64: MED | K64: NOT_STARTED
A65: 022.01.09.01.04 | B65: 5 | C65: Give examples of display. | D65: N | G65: MED | K65: NOT_STARTED
A66: 022.01.10.00 | B66: 3 | C66: Time measurement
A67: 022.01.10.01 | B67: 4 | C67: On-board clock
A68: 022.01.10.01.01 | B68: 5 | C68: Explain that the on-board aircraft clock provides a time reference for several of the on-board systems including aircraft communications addressing and reporting system (ACARS) and engine and systems maintenance. | D68: N | G68: MED | K68: NOT_STARTED
A69: 022.02.00.00 | B69: 2 | C69: MEASUREMENT OF AIR-DATA PARAMETERS
A70: 022.02.01.00 | B70: 3 | C70: Pressure measurement
A71: 022.02.01.01 | B71: 4 | C71: Definitions
A72: 022.02.01.01.01 | B72: 5 | C72: Define the following pressure measurements and state the relationship between them: static pressure; dynamic pressure; total pressure. | D72: N | G72: MED | K72: NOT_STARTED
A73: 022.02.01.02 | B73: 4 | C73: Pitot/static system: design and errors
A74: 022.02.01.02.01 | B74: 5 | C74: Describe the design and the operating principle of a: static port/source; pitot tube; combined pitot/static probe. | D74: N | G74: MED | K74: NOT_STARTED
A75: 022.02.01.02.02 | B75: 5 | C75: For each of these indicate the various locations and describe the following associated errors and how to correct, minimise the effect of or compensate for them: position errors; instrument errors; errors due to a non-longitudinal axial flow (including manoeuvre-induced errors). | D75: N | G75: MED | K75: NOT_STARTED
A76: 022.02.01.02.03 | B76: 5 | C76: Describe a typical pitot/static system and list the possible outputs. | D76: N | G76: MED | K76: NOT_STARTED
A77: 022.02.01.02.04 | B77: 5 | C77: Explain the redundancy and the interconnections that typically exist in complex pitot/static systems found in large aircraft. | D77: N | G77: MED | K77: NOT_STARTED
A78: 022.02.01.02.05 | B78: 5 | C78: Explain the purpose of pitot/static system heating. | D78: N | G78: MED | K78: NOT_STARTED
A79: 022.02.01.02.06 | B79: 5 | C79: Describe alternate static sources and their effects when used, particularly in unpressurised aircraft. | D79: N | G79: MED | K79: NOT_STARTED
A80: 022.02.01.02.07 | B80: 5 | C80: Describe a modern pitot static system using solid-state sensors near the pitot probe or static port converting the air data to numerical data (electrical signals) before being sent to the air-data computer(s). | D80: N | G80: MED | K80: NOT_STARTED
A81: 022.02.02.00 | B81: 3 | C81: Temperature measurement
A82: 022.02.02.01 | B82: 4 | C82: Definitions
A83: 022.02.02.01.01 | B83: 5 | C83: Define the following and explain the relationship between them: outside air temperature (OAT); total air temperature (TAT); static air temperature (SAT). | D83: N | G83: MED | K83: NOT_STARTED
A84: 022.02.02.01.02 | B84: 5 | C84: Explain the term ‘ram rise’ and convert TAT to SAT. | D84: N | G84: MED | K84: NOT_STARTED
A85: 022.02.02.01.03 | B85: 5 | C85: Explain why TAT is often displayed and that TAT is the temperature input to the air-data computer. | D85: N | G85: MED | K85: NOT_STARTED
A86: 022.02.02.02 | B86: 4 | C86: Design and operation
A87: 022.02.02.02.01 | B87: 5 | C87: Indicate typical locations for both direct-reading and remote-reading temperature probes, and describe the following errors: position error; instrument error. | D87: N | G87: MED | K87: NOT_STARTED
A88: 022.02.02.02.02 | B88: 5 | C88: Explain the purpose of temperature probe heating and interpret the effect of heating on sensed temperature unless automatically compensated for. | D88: N | G88: MED | K88: NOT_STARTED
A89: 022.02.03.00 | B89: 3 | C89: Angle-of-attack (AoA) measurement
A90: 022.02.03.01 | B90: 4 | C90: Sensor types, operating principles, ice protection, displays, incorrect indications
A91: 022.02.03.01.01 | B91: 5 | C91: Describe the following two types of AoA sensors: null-seeking (slotted) probe; vane detector. | D91: N | G91: MED | K91: NOT_STARTED
A92: 022.02.03.01.02 | B92: 5 | C92: For each type, explain the operating principles. | D92: N | G92: MED | K92: NOT_STARTED
A93: 022.02.03.01.03 | B93: 5 | C93: Explain how both types are protected against ice. | D93: N | G93: MED | K93: NOT_STARTED
A94: 022.02.03.01.04 | B94: 5 | C94: Give examples of systems that use the AoA as an input, such as: air-data computer; stall warning systems; flight-envelope protection systems. | D94: N | G94: MED | K94: NOT_STARTED
A95: 022.02.03.01.05 | B95: 5 | C95: Give examples of and interpret different types of AoA displays: simple light arrays of green, amber and red lights; gauges showing a numerical scale. | D95: N | G95: MED | K95: NOT_STARTED
A96: 022.02.03.01.06 | B96: 5 | C96: Explain the implications for the pilot if the AoA indication becomes incorrect but still provides data, e.g. if the sensor is frozen in a fixed position. | D96: N | G96: MED | K96: NOT_STARTED
A97: 022.02.03.01.07 | B97: 5 | C97: Explain how an incorrect AoA measurement can affect the controllability of an aircraft with flight-envelope protection. | D97: N | G97: MED | K97: NOT_STARTED
A98: 022.02.04.00 | B98: 3 | C98: Altimeter
A99: 022.02.04.01 | B99: 4 | C99: Units, terms, types, operating principles, displays, errors, corrections
A100: 022.02.04.01.01 | B100: 5 | C100: List the following two units used for altimeters and state the relationship between them: feet; metres. | D100: N | G100: MED | K100: NOT_STARTED
A101: 022.02.04.01.02 | B101: 5 | C101: Define the following terms: height, altitude; indicated altitude, true altitude; pressure altitude, density altitude. | D101: Y | G101: LOW | K101: NOT_STARTED
...

Sheet S031
A1: 031 Mass and Balance
A3: LO_ID | B3: Level | C3: LO_Text | D3: BK_Only | E3: ECQB_2026_Change_Flag | F3: ECQB_2026_Source_Note | G3: Priority | H3: Content_Type_Planned | I3: Repo_Path | J3: Agent_Assigned | K3: Coverage_Status | L3: Last_Updated | M3: Reviewed_By | N3: Notes
A4: 031.01.00.00 | B4: 2 | C4: PURPOSE OF MASS-AND-BALANCE CONSIDERATIONS
A5: 031.01.01.00 | B5: 3 | C5: Mass limitations
A6: 031.01.01.01 | B6: 4 | C6: Importance with regard to structural limitations
A7: 031.01.01.01.01 | B7: 5 | C7: Describe the relationship between aircraft mass and structural stress. Remark: See also Subject 021 01 01 00. | D7: Y | G7: LOW | K7: NOT_STARTED
A8: 031.01.01.01.02 | B8: 5 | C8: Describe why mass must be limited to ensure adequate margins of strength. | D8: Y | G8: LOW | K8: NOT_STARTED
A9: 031.01.01.02 | B9: 4 | C9: Importance with regard to performance Remark: See also Subjects 032/034 and 081/082.
A10: 031.01.01.02.01 | B10: 5 | C10: Describe the relationship between aircraft mass and aircraft performance. | D10: N | G10: MED | K10: NOT_STARTED
A11: 031.01.01.02.02 | B11: 5 | C11: Describe why aircraft mass must be limited to ensure adequate aircraft performance. | D11: Y | G11: LOW | K11: NOT_STARTED
A12: 031.01.02.00 | B12: 3 | C12: Centre-of-gravity (CG) limitations
A13: 031.01.02.01 | B13: 4 | C13: Importance with regard to stability and controllability Remark: See also Subjects 081/082.
A14: 031.01.02.01.01 | B14: 5 | C14: Describe the relationship between CG position and stability/controllability of the aircraft. | D14: Y | G14: LOW | K14: NOT_STARTED
A15: 031.01.02.01.02 | B15: 5 | C15: Describe the consequences if CG is in front of the forward limit. | D15: N | G15: MED | K15: NOT_STARTED
A16: 031.01.02.01.03 | B16: 5 | C16: Describe the consequences if CG is behind the aft limit. | D16: N | G16: MED | K16: NOT_STARTED
A17: 031.01.02.02 | B17: 4 | C17: Importance with regard to performance Remark: See also Subjects 032/034 and 081/082.
A18: 031.01.02.02.01 | B18: 5 | C18: Describe the relationship between CG position and aircraft performance. | D18: Y | G18: LOW | K18: NOT_STARTED
A19: 031.01.02.02.02 | B19: 5 | C19: Describe the effects of CG position on performance parameters (speeds, altitude, endurance and range). | D19: N | G19: MED | K19: NOT_STARTED
A20: 031.02.00.00 | B20: 2 | C20: LOADING
A21: 031.02.01.00 | B21: 3 | C21: Terminology
A22: 031.02.01.01 | B22: 4 | C22: Mass terms
A23: 031.02.01.01.01 | B23: 5 | C23: Define the following mass terms: basic empty mass; dry operating mass; operating mass; take-off mass; landing mass; ramp/taxi mass; in-flight mass (gross mass); zero fuel mass. | D23: Y | E23: Fuel/energy scheme (basic, RCF 3%, isolated aerodrome, extra/discretionary fuel) | G23: HIGH | K23: NOT_STARTED
A24: 031.02.01.02 | B24: 4 | C24: Load terms (including fuel terms) Remark: See also Subject 033.
A25: 031.02.01.02.01 | B25: 5 | C25: Define the following load terms: payload/traffic load; block fuel; taxi fuel; take-off fuel; trip fuel; reserve fuel (contingency, alternate, final reserve and additional fuel); extra fuel. | D25: Y | E25: Fuel/energy scheme (basic, RCF 3%, isolated aerodrome, extra/discretionary fuel) | G25: HIGH | K25: NOT_STARTED
A26: 031.02.01.02.02 | B26: 5 | C26: Explain the relationship between the various load-and-mass components listed in 031 02 01 01 and 031 02 01 02. | D26: N | G26: MED | K26: NOT_STARTED
A27: 031.02.01.02.03 | B27: 5 | C27: Calculate the mass of particular components from other given components. | D27: N | G27: MED | K27: NOT_STARTED
A28: 031.02.01.02.04 | B28: 5 | C28: Convert fuel mass, fuel volume and fuel density given in different units used in aviation. | D28: N | E28: Fuel/energy scheme (basic, RCF 3%, isolated aerodrome, extra/discretionary fuel) | G28: HIGH | K28: NOT_STARTED
A29: 031.02.02.00 | B29: 3 | C29: Mass limits
A30: 031.02.02.01 | B30: 4 | C30: Structural limitations
A31: 031.02.02.01.01 | B31: 5 | C31: Define the maximum zero fuel mass. | D31: Y | E31: Fuel/energy scheme (basic, RCF 3%, isolated aerodrome, extra/discretionary fuel) | G31: HIGH | K31: NOT_STARTED
A32: 031.02.02.01.02 | B32: 5 | C32: Define the maximum ramp/taxi mass. | D32: Y | G32: LOW | K32: NOT_STARTED
A33: 031.02.02.01.03 | B33: 5 | C33: Define the maximum take-off mass. | D33: Y | G33: LOW | K33: NOT_STARTED
A34: 031.02.02.01.05 | B34: 5 | C34: Define the maximum landing mass. | D34: Y | G34: LOW | K34: NOT_STARTED
A35: 031.02.02.02 | B35: 4 | C35: Performance and regulated limitations
A36: 031.02.02.02.01 | B36: 5 | C36: Describe the following performance and regulated mass limitations: performance-limited take-off mass; performance-limited landing mass; regulated take-off mass; regulated landing mass. | D36: N | G36: MED | K36: NOT_STARTED
A37: 031.02.02.03 | B37: 4 | C37: Cargo compartment limitations
A38: 031.02.02.03.01 | B38: 5 | C38: Describe the maximum floor load (maximum load per unit of area). | D38: Y | G38: LOW | K38: NOT_STARTED
A39: 031.02.02.03.02 | B39: 5 | C39: Describe the maximum running load (maximum load per unit of fuselage length). | D39: Y | G39: LOW | K39: NOT_STARTED
A40: 031.02.03.00 | B40: 3 | C40: Mass calculations
A41: 031.02.03.01 | B41: 4 | C41: Maximum masses for take-off and landing
A42: 031.02.03.01.01 | B42: 5 | C42: Calculate the maximum mass for take-off (regulated take-off mass) given mass-and-load components and structural/ performance limits. | D42: N | G42: MED | K42: NOT_STARTED
A43: 031.02.03.01.02 | B43: 5 | C43: Calculate the maximum mass for landing (regulated landing mass) given mass-and-load components and structural/ performance limits. | D43: N | G43: MED | K43: NOT_STARTED
A44: 031.02.03.01.03 | B44: 5 | C44: Calculate the allowed mass for take-off. | D44: N | G44: MED | K44: NOT_STARTED
A45: 031.02.03.02 | B45: 4 | C45: Allowed traffic load and fuel load
A46: 031.02.03.02.01 | B46: 5 | C46: Calculate the maximum allowed traffic load and fuel load in order not to exceed the given allowed take-off mass. | D46: N | E46: Fuel/energy scheme (basic, RCF 3%, isolated aerodrome, extra/discretionary fuel) | G46: HIGH | K46: NOT_STARTED
A47: 031.02.03.02.02 | B47: 5 | C47: Calculate ‘under load’/‘over load’ given the allowed mass for take-off, operating mass and actual traffic load. | D47: N | G47: MED | K47: NOT_STARTED
A48: 031.02.03.03 | B48: 4 | C48: Use of standard masses for passengers, baggage and crew
A49: 031.02.03.03.01 | B49: 5 | C49: Extract the appropriate standard masses for passengers, baggage and crew from relevant documents or operator requirements. | D49: Y | G49: LOW | K49: NOT_STARTED
A50: 031.02.03.03.02 | B50: 5 | C50: Calculate the traffic load by using standard masses. | D50: N | G50: MED | K50: NOT_STARTED
A51: 031.03.00.00 | B51: 2 | C51: INTENTIONALLY LEFT BLANK
A52: 031.04.00.00 | B52: 2 | C52: MASS-AND-BALANCE DETAILS OF AIRCRAFT
A53: 031.04.01.00 | B53: 3 | C53: Contents of mass-and-balance documentation
A54: 031.04.01.01 | B54: 4 | C54: Datum, moment arm
A55: 031.04.01.01.01 | B55: 5 | C55: State where the datum and moment arms for aircraft can be found. | D55: Y | G55: LOW | K55: NOT_STARTED
A56: 031.04.01.01.02 | B56: 5 | C56: Extract the appropriate data from given documents. | D56: Y | G56: LOW | K56: NOT_STARTED
A57: 031.04.01.01.03 | B57: 5 | C57: Define ‘datum’ (reference point), ‘moment arm’ and ‘moment’. | D57: Y | G57: LOW | K57: NOT_STARTED
A58: 031.04.01.02 | B58: 4 | C58: CG position as distance from datum
A59: 031.04.01.02.01 | B59: 5 | C59: State where the CG position for an aircraft at basic empty mass can be found. | D59: Y | G59: LOW | K59: NOT_STARTED
A60: 031.04.01.02.02 | B60: 5 | C60: State where the CG limits for an aircraft can be found. | D60: Y | G60: LOW | K60: NOT_STARTED
A61: 031.04.01.02.03 | B61: 5 | C61: Describe the different forms in presenting CG position as distance from datum or other references. | D61: N | G61: MED | K61: NOT_STARTED
A62: 031.04.01.02.04 | B62: 5 | C62: Explain the meaning of centre of gravity (CG). | D62: N | G62: MED | K62: NOT_STARTED
A63: 031.04.01.03 | B63: 4 | C63: CG position as percentage of mean aerodynamic chord (per cent MAC) Remark: Knowledge of the definition of MAC is covered under Subject 081 01 01 05.
A64: 031.04.01.03.01 | B64: 5 | C64: Extract MAC information from aircraft documents. | D64: N | G64: MED | K64: NOT_STARTED
A65: 031.04.01.03.02 | B65: 5 | C65: Explain the principle of using per cent MAC for the description of the CG position. | D65: N | G65: MED | K65: NOT_STARTED
A66: 031.04.01.03.03 | B66: 5 | C66: Calculate the CG position as per cent MAC. | D66: N | G66: MED | K66: NOT_STARTED
A67: 031.04.01.04 | B67: 4 | C67: Longitudinal CG limits
A68: 031.04.01.04.01 | B68: 5 | C68: Extract the appropriate data from given sample documents. | D68: N | G68: MED | K68: NOT_STARTED
A69: 031.04.01.05 | B69: 4 | C69: Lateral CG limits
A70: 031.04.01.06 | B70: 4 | C70: Details of passenger and cargo compartments
A71: 031.04.01.06.01 | B71: 5 | C71: Extract the appropriate data (e.g. seating schemes, compartment dimensions and limitations) from given sample documents. | D71: N | G71: MED | K71: NOT_STARTED
A72: 031.04.01.07 | B72: 4 | C72: Details of fuel system relevant to mass-and-balance considerations
A73: 031.04.01.07.01 | B73: 5 | C73: Extract the appropriate data (e.g. fuel-tank capacities and fuel-tank positions) from given sample documents. | D73: Y | E73: Fuel/energy scheme (basic, RCF 3%, isolated aerodrome, extra/discretionary fuel) | G73: HIGH | K73: NOT_STARTED
A74: 031.04.01.07.02 | B74: 5 | C74: Explain aircraft CG movement as flight progresses given location of fuel tank (inner wing, outer wing, central, additional aft central, horizontal stabiliser) and mass of fuel consumed from that tank and aeroplane’s previous CG. | D74: N | E74: Fuel/energy scheme (basic, RCF 3%, isolated aerodrome, extra/discretionary fuel) | G74: HIGH | K74: NOT_STARTED
A75: 031.04.01.07.03 | B75: 5 | C75: Explain advantages and risks associated with fuel tanks in the aeroplane’s fin or horizontal stabiliser. | D75: N | E75: Fuel/energy scheme (basic, RCF 3%, isolated aerodrome, extra/discretionary fuel) | G75: HIGH | K75: NOT_STARTED
A76: 031.04.02.00 | B76: 3 | C76: Determination of aircraft empty mass and CG position by weighing
A77: 031.04.02.01 | B77: 4 | C77: Weighing of aircraft (general aspects)
A78: 031.04.02.01.01 | B78: 5 | C78: Describe the general procedure and regulations relating to when an aircraft should be weighed, reweighed or data recalculated. Remark: See the applicable operational requirements. | D78: N | G78: MED | K78: NOT_STARTED
A79: 031.04.02.01.02 | B79: 5 | C79: Extract and interpret entries from/in ‘mass (weight) report’ of an aircraft. | D79: Y | G79: LOW | K79: NOT_STARTED
A80: 031.04.02.02 | B80: 4 | C80: Calculation of mass and CG position of an aircraft using weighing data
A81: 031.04.02.02.01 | B81: 5 | C81: Calculate the mass and CG position of an aircraft from given reaction forces on jacking points. | D81: N | G81: MED | K81: NOT_STARTED
A82: 031.04.03.00 | B82: 3 | C82: Extraction of basic empty mass (BEM) and CG data from aircraft documentation
A83: 031.04.03.01 | B83: 4 | C83: BEM or dry operating mass (DOM)
A84: 031.04.03.01.01 | B84: 5 | C84: Extract values for BEM or DOM from given documents. | D84: Y | G84: LOW | K84: NOT_STARTED
A85: 031.04.03.02 | B85: 4 | C85: CG position or moment at BEM/DOM
A86: 031.04.03.02.01 | B86: 5 | C86: Extract values for CG position and moment at BEM or DOM from given documents. | D86: N | G86: MED | K86: NOT_STARTED
A87: 031.04.03.03 | B87: 4 | C87: Deviations from standard configuration
A88: 031.04.03.03.01 | B88: 5 | C88: Extract values from given documents for deviation from standard configuration as a result of varying crew, optional equipment, optional fuel tanks, etc. | D88: N | E88: Fuel/energy scheme (basic, RCF 3%, isolated aerodrome, extra/discretionary fuel) | G88: HIGH | K88: NOT_STARTED
A89: 031.05.00.00 | B89: 2 | C89: DETERMINATION OF CG POSITION
A90: 031.05.01.00 | B90: 3 | C90: Methods
A91: 031.05.01.01 | B91: 4 | C91: Arithmetic method
A92: 031.05.01.01.01 | B92: 5 | C92: Calculate the CG position of an aircraft by using the formula: CG position = sum of moments / total mass. | D92: N | G92: MED | K92: NOT_STARTED
A93: 031.05.01.02 | B93: 4 | C93: Graphic method
A94: 031.05.01.02.01 | B94: 5 | C94: Determine the CG position of an aircraft by using the loading graphs given in sample documents. | D94: N | G94: MED | K94: NOT_STARTED
A95: 031.05.01.03 | B95: 4 | C95: Index method
A96: 031.05.01.03.01 | B96: 5 | C96: Explain the principle of the index method. | D96: Y | G96: LOW | K96: NOT_STARTED
A97: 031.05.01.03.02 | B97: 5 | C97: Define the terms ‘index’ and ‘dry operating index’ (DOI), and calculate the DOI given the relevant formula and data. | D97: N | G97: MED | K97: NOT_STARTED
A98: 031.05.01.03.03 | B98: 5 | C98: Explain the advantage(s) of the index method. | D98: N | G98: MED | K98: NOT_STARTED
A99: 031.05.02.00 | B99: 3 | C99: Load and trim sheet
A100: 031.05.02.01 | B100: 4 | C100: General considerations
A101: 031.05.02.01.01 | B101: 5 | C101: Explain the principle and the purpose of load sheets. | D101: Y | G101: LOW | K101: NOT_STARTED
...

Sheet S032
A1: 032 Performance — Aeroplanes
A3: LO_ID | B3: Level | C3: LO_Text | D3: BK_Only | E3: ECQB_2026_Change_Flag | F3: ECQB_2026_Source_Note | G3: Priority | H3: Content_Type_Planned | I3: Repo_Path | J3: Agent_Assigned | K3: Coverage_Status | L3: Last_Updated | M3: Reviewed_By | N3: Notes
A4: 032.01.00.00 | B4: 2 | C4: GENERAL
A5: 032.01.01.00 | B5: 3 | C5: Performance legislation
A6: 032.01.01.01 | B6: 4 | C6: Applicability of airworthiness requirements of CS-23 and CS-25
A7: 032.01.01.01.01 | B7: 5 | C7: Describe the application of certification specification (CSs) with regard to the different kinds of aeroplanes. | D7: Y | G7: LOW | K7: NOT_STARTED
A8: 032.01.01.01.02 | B8: 5 | C8: Describe the general differences between aeroplanes certified according to CS-23 and CS-25. | D8: Y | G8: LOW | K8: NOT_STARTED
A9: 032.01.01.02 | B9: 4 | C9: Operational regulations and safety
A10: 032.01.01.02.01 | B10: 5 | C10: Describe the basic concept that the applicable operational requirements differ depending on aeroplane performance. | D10: Y | G10: LOW | K10: NOT_STARTED
A11: 032.01.01.02.02 | B11: 5 | C11: Describe the performance classes for commercial air transport according to the applicable operational requirements. | D11: N | G11: MED | K11: NOT_STARTED
A12: 032.01.01.03 | B12: 4 | C12: Performance and safety
A13: 032.01.01.03.01 | B13: 5 | C13: State that aeroplane performance required for commercial air transport may limit the weight of a dispatched aeroplane in order to achieve a sufficient level of safety. | D13: Y | G13: LOW | K13: NOT_STARTED
A14: 032.01.01.03.02 | B14: 5 | C14: Describe that the minimum level of safety required for commercial air transport is ensured through the combination of airworthiness requirements and operational limitations, i.e. the more stringent airworthiness requirements of CS-25 enable a wider range of operating conditions for these aeroplanes. | D14: Y | G14: LOW | K14: NOT_STARTED
A15: 032.01.01.04 | B15: 4 | C15: Performance definitions and safety factors
A16: 032.01.01.04.01 | B16: 5 | C16: Describe measured performance and explain how it is determined. | D16: Y | G16: LOW | K16: NOT_STARTED
A17: 032.01.01.04.02 | B17: 5 | C17: Describe gross performance. | D17: N | G17: MED | K17: NOT_STARTED
A18: 032.01.01.04.03 | B18: 5 | C18: Describe net performance and safety factors. | D18: N | G18: MED | K18: NOT_STARTED
A19: 032.01.01.04.04 | B19: 5 | C19: Describe that the size of a safety factor depends on the likelihood of the event and the range of the measured performance data. | D19: Y | G19: LOW | K19: NOT_STARTED
A20: 032.01.01.04.05 | B20: 5 | C20: Describe the relationship between net and gross take-off and landing distances, and net and gross climb and descent gradients. | D20: N | G20: MED | K20: NOT_STARTED
A21: 032.01.02.00 | B21: 3 | C21: General performance theory
A22: 032.01.02.01 | B22: 4 | C22: Intentionally left blank
A23: 032.01.02.02 | B23: 4 | C23: Definitions and terms
A24: 032.01.02.02.01 | B24: 5 | C24: Define the terms ‘climb angle’ and ‘climb gradient’. | D24: Y | G24: LOW | K24: NOT_STARTED
A25: 032.01.02.02.02 | B25: 5 | C25: Define the terms ‘flight-path angle’ and ‘flight-path gradient’. | D25: Y | G25: LOW | K25: NOT_STARTED
A26: 032.01.02.02.03 | B26: 5 | C26: Define the terms ‘descent angle’ and ‘descent gradient’. | D26: Y | G26: LOW | K26: NOT_STARTED
A27: 032.01.02.02.04 | B27: 5 | C27: Explain the difference between climb/descent angle and flight-path angle. | D27: Y | G27: LOW | K27: NOT_STARTED
A28: 032.01.02.02.05 | B28: 5 | C28: Define ‘absolute ceiling’. | D28: Y | G28: LOW | K28: NOT_STARTED
A29: 032.01.02.02.06 | B29: 5 | C29: Describe ‘clearway’ and ‘stopway’ according to CS-Definitions. | D29: N | G29: MED | K29: NOT_STARTED
A30: 032.01.02.02.07 | B30: 5 | C30: Describe: take-off run available (TORA); take-off distance available (TODA); accelerate-stop distance available (ASDA); and determine each from given data or appropriate aerodrome charts. | D30: N | G30: MED | K30: NOT_STARTED
A31: 032.01.02.02.08 | B31: 5 | C31: Describe ‘screen height’ including its various values. | D31: N | G31: MED | K31: NOT_STARTED
A32: 032.01.02.02.09 | B32: 5 | C32: Define the terms ‘range’ and ‘endurance’. | D32: Y | G32: LOW | K32: NOT_STARTED
A33: 032.01.02.02.10 | B33: 5 | C33: Define an aeroplane’s ‘specific range’ (SR) in terms of nautical air miles (NAM) per unit of fuel, and ‘specific range over the ground’ (SRG) in terms of nautical ground miles (NGM) per unit of fuel. | D33: N | E33: Fuel/energy scheme alignment | G33: HIGH | K33: NOT_STARTED
A34: 032.01.02.02.11 | B34: 5 | C34: Define the power available and power required. | D34: N | G34: MED | K34: NOT_STARTED
A35: 032.01.02.03 | B35: 4 | C35: Variables influencing performance
A36: 032.01.02.03.01 | B36: 5 | C36: Name the following factors that affect aeroplane performance: pressure altitude and temperature, wind, aeroplane weight, aeroplane configuration, aeroplane anti-skid status, aeroplane centre of gravity (CG), aerodrome runway surface, and aerodrome runway slope. | D36: Y | G36: LOW | K36: NOT_STARTED
A37: 032.01.02.03.02 | B37: 5 | C37: Describe how, for different density altitudes, the thrust and power available vary with speed for a propeller-driven aeroplane. | D37: Y | G37: LOW | K37: NOT_STARTED
A38: 032.01.02.03.03 | B38: 5 | C38: Describe how, for different density altitudes, the thrust and power available vary with speed for a turbojet aeroplane. | D38: Y | G38: LOW | K38: NOT_STARTED
A39: 032.01.02.03.04 | B39: 5 | C39: Describe how, for different density altitudes, the drag and power required vary with indicated airspeeds (IAS) and true airspeeds (TAS). | D39: N | G39: MED | K39: NOT_STARTED
A40: 032.01.02.03.05 | B40: 5 | C40: Describe how, for different aeroplane weights and configurations, the drag and power required vary with IAS and TAS. | D40: N | G40: MED | K40: NOT_STARTED
A41: 032.01.03.00 | B41: 3 | C41: Level flight, range and endurance
A42: 032.01.03.01 | B42: 4 | C42: Steady level flight
A43: 032.01.03.01.01 | B43: 5 | C43: Explain how drag (thrust) and power required vary with speed in straight and level flight. | D43: Y | G43: LOW | K43: NOT_STARTED
A44: 032.01.03.01.02 | B44: 5 | C44: Explain the effect of excess thrust and power on speed in level flight. | D44: Y | G44: LOW | K44: NOT_STARTED
A45: 032.01.03.01.03 | B45: 5 | C45: Interpret the ‘thrust/power required’ and ‘thrust/power available’ curves in straight and level flight. | D45: N | G45: MED | K45: NOT_STARTED
A46: 032.01.03.01.04 | B46: 5 | C46: Describe how the maximum achievable straight and level flight IAS and TAS vary with altitude. | D46: N | G46: MED | K46: NOT_STARTED
A47: 032.01.03.01.05 | B47: 5 | C47: Describe situations in which a pilot may elect to fly for ‘maximum endurance’ or ‘maximum range’. | D47: N | G47: MED | K47: NOT_STARTED
A48: 032.01.03.02 | B48: 4 | C48: Range
A49: 032.01.03.02.01 | B49: 5 | C49: Define a turbojet aeroplane’s specific fuel consumption (SFC) and describe how it affects fuel flow and specific range. | D49: N | E49: Fuel/energy scheme alignment | G49: HIGH | K49: NOT_STARTED
A50: 032.01.03.02.02 | B50: 5 | C50: Define a propeller-driven aeroplane’s SFC and describe how it affects fuel flow and specific range. | D50: N | E50: Fuel/energy scheme alignment | G50: HIGH | K50: NOT_STARTED
A51: 032.01.03.02.03 | B51: 5 | C51: Explain the optimum speed for maximum SR for a turbojet aeroplane in relation to the drag curve. | D51: N | G51: MED | K51: NOT_STARTED
A52: 032.01.03.02.04 | B52: 5 | C52: Explain the optimum speed to achieve maximum SR for a propeller-driven aeroplane in relation to the power required and drag graphs. | D52: N | G52: MED | K52: NOT_STARTED
A53: 032.01.03.02.05 | B53: 5 | C53: Explain the effect of aeroplane weight and CG position on fuel consumption, range and the optimum speed for maximum SR. | D53: N | E53: Fuel/energy scheme alignment | G53: HIGH | K53: NOT_STARTED
A54: 032.01.03.02.06 | B54: 5 | C54: State how a turbojet engine’s SFC varies with temperature and thrust setting. | D54: N | G54: MED | K54: NOT_STARTED
A55: 032.01.03.02.07 | B55: 5 | C55: Explain how SR for a turbojet aeroplane varies with altitude and under different meteorological conditions. | D55: N | G55: MED | K55: NOT_STARTED
A56: 032.01.03.02.08 | B56: 5 | C56: Explain how SRG for a propeller-driven aeroplane varies with altitude and under different meteorological conditions. | D56: N | G56: MED | K56: NOT_STARTED
A57: 032.01.03.02.09 | B57: 5 | C57: Explain the effect of weight on the optimum altitude for maximum range. | D57: N | G57: MED | K57: NOT_STARTED
A58: 032.01.03.02.10 | B58: 5 | C58: Describe the effect of wind on SRG and the optimum speed for SRG , when compared to SR, and the optimum speed for SR. | D58: N | G58: MED | K58: NOT_STARTED
A59: 032.01.03.03 | B59: 4 | C59: Maximum endurance
A60: 032.01.03.03.01 | B60: 5 | C60: Explain fuel flow in relation to TAS and thrust for a turbojet aeroplane. | D60: N | E60: Fuel/energy scheme alignment | G60: HIGH | K60: NOT_STARTED
A61: 032.01.03.03.02 | B61: 5 | C61: State the speed for maximum endurance for a turbojet aeroplane. | D61: N | G61: MED | K61: NOT_STARTED
A62: 032.01.03.03.03 | B62: 5 | C62: Explain fuel flow in relation to TAS and thrust for a propeller-driven aeroplane. | D62: N | E62: Fuel/energy scheme alignment | G62: HIGH | K62: NOT_STARTED
A63: 032.01.03.03.04 | B63: 5 | C63: State the speed for maximum endurance for a propeller-driven aeroplane and the disadvantages of holding at this speed (e.g. high angle of attack (AoA) and lack of speed stability). | D63: N | G63: MED | K63: NOT_STARTED
A64: 032.01.03.03.05 | B64: 5 | C64: Explain the effect of wind and altitude on endurance, and the maximum endurance speed for a turbojet aeroplane. | D64: N | G64: MED | K64: NOT_STARTED
A65: 032.01.03.03.06 | B65: 5 | C65: Explain the effect of wind and altitude on endurance, and the maximum endurance speed for a propeller-driven aeroplane. | D65: N | G65: MED | K65: NOT_STARTED
A66: 032.01.03.03.07 | B66: 5 | C66: Describe the benefits of managing your en-route airspeed to reduce or avoid holding time, and the operational situations when it could be used (commanded by the pilot or air traffic control (ATC), when delays at arrival airport occur). | D66: N | G66: MED | K66: NOT_STARTED
A67: 032.01.04.00 | B67: 3 | C67: Climbing
A68: 032.01.04.01 | B68: 4 | C68: Climbing (climb performance)
A69: 032.01.04.01.01 | B69: 5 | C69: Resolve the forces during a steady climb. | D69: N | G69: MED | K69: NOT_STARTED
A70: 032.01.04.01.02 | B70: 5 | C70: Define and explain the following terms: critical engine; speed for best angle of climb (VX); speed for best rate of climb (VY). | D70: N | G70: MED | K70: NOT_STARTED
A71: 032.01.04.01.03 | B71: 5 | C71: Explain climb performance in relation to the thrust available and thrust required (angle of climb), and power available and power required (rate of climb). | D71: N | G71: MED | K71: NOT_STARTED
A72: 032.01.04.01.04 | B72: 5 | C72: Explain the meaning and effect of ‘excess thrust’ and ‘excess power’ in a steady climb. | D72: N | G72: MED | K72: NOT_STARTED
A73: 032.01.04.01.05 | B73: 5 | C73: Interpret the ‘thrust/power required’ and ‘thrust/power available’ curves in a steady climb. | D73: N | G73: MED | K73: NOT_STARTED
A74: 032.01.04.01.06 | B74: 5 | C74: State the difference between climb angle and gradient. | D74: N | G74: MED | K74: NOT_STARTED
A75: 032.01.04.01.07 | B75: 5 | C75: Explain the effect of weight on the climb angle and rate of climb, and the speed for best angle and best rate of climb. | D75: N | G75: MED | K75: NOT_STARTED
A76: 032.01.04.01.08 | B76: 5 | C76: Explain the effects of pressure altitude and temperature, including an inversion on climb performance (angle and rate of climb). | D76: N | G76: MED | K76: NOT_STARTED
A77: 032.01.04.01.09 | B77: 5 | C77: Explain the effect of configuration on climb performance (angle and rate of climb, and VX and VY). | D77: N | G77: MED | K77: NOT_STARTED
A78: 032.01.04.01.10 | B78: 5 | C78: Describe the effect of engine failure on climb performance (angle and rate of climb, and VX and VY). | D78: N | G78: MED | K78: NOT_STARTED
A79: 032.01.04.01.11 | B79: 5 | C79: Calculate the all-engine and one-engine-out climb gradient from given values of engine thrust and aeroplane drag and weight. | D79: N | G79: MED | K79: NOT_STARTED
A80: 032.01.05.00 | B80: 3 | C80: Descending
A81: 032.01.05.01 | B81: 4 | C81: Descending (descent performance)
A82: 032.01.05.01.01 | B82: 5 | C82: Resolve the forces during steady descent and in the glide. | D82: N | G82: MED | K82: NOT_STARTED
A83: 032.01.05.01.02 | B83: 5 | C83: Explain descent performance in relation to thrust available and thrust required (drag), and power available and power required. | D83: N | G83: MED | K83: NOT_STARTED
A84: 032.01.05.01.03 | B84: 5 | C84: Explain the meaning of ‘excess thrust required’ (excess drag) and ‘excess power required’ in a steady descent. | D84: N | G84: MED | K84: NOT_STARTED
A85: 032.01.05.01.04 | B85: 5 | C85: Interpret the ‘thrust/power required’ and ‘thrust/power available’ curves in a steady descent. | D85: N | G85: MED | K85: NOT_STARTED
A86: 032.01.05.01.05 | B86: 5 | C86: Explain the effect of mass, altitude, wind, speed and configuration on the glide descent. | D86: N | G86: MED | K86: NOT_STARTED
A87: 032.01.05.01.06 | B87: 5 | C87: Explain the effect of mass, altitude, wind, speed and configuration on the powered descent. | D87: N | G87: MED | K87: NOT_STARTED
A88: 032.02.00.00 | B88: 2 | C88: CS-23/APPLICABLE OPERATIONAL REQUIREMENTS PERFORMANCE CLASS B - THEORY
A89: 032.02.01.00 | B89: 3 | C89: Airworthiness requirements
A90: 032.02.01.01 | B90: 4 | C90: Airworthiness requirements and definitions
A91: 032.02.01.01.01 | B91: 5 | C91: Define the following speeds: stall speeds VS, VS0 and VS1; rotation speed VR; speed at 50 ft above the take-off surface level; reference landing speed VREF. | D91: Y | G91: LOW | K91: NOT_STARTED
A92: 032.02.01.01.02 | B92: 5 | C92: Describe the limitations on VR, on the speed at 50 ft above the take-off surface and on VREF, and given the appropriate stall speed, estimate the values based on these limitations for a single-engine, class B aeroplane. | D92: N | G92: MED | K92: NOT_STARTED
A93: 032.02.01.01.03 | B93: 5 | C93: Describe the limitations on VR, on the speed at 50 ft above the take-off surface and on VREF, and given the appropriate stall speed, estimate the values based on these limitations for a multi-engine, class B aeroplane. | D93: N | G93: MED | K93: NOT_STARTED
A94: 032.02.01.01.04 | B94: 5 | C94: Describe the European Union airworthiness requirements according to CS-23 relating to aeroplane performance (stall, take-off, climb, landing). | D94: Y | G94: LOW | K94: NOT_STARTED
A95: 032.02.01.01.05 | B95: 5 | C95: Define and identify the critical engine of a multi-engine propeller aeroplane. | D95: N | G95: MED | K95: NOT_STARTED
A96: 032.02.01.01.06 | B96: 5 | C96: Explain the effect of an engine failure on the power required, the total drag (thrust required) and climb performance of a multi-engine aeroplane. | D96: N | G96: MED | K96: NOT_STARTED
A97: 032.02.01.01.07 | B97: 5 | C97: Explain the effect of engine failure on the minimum control speed of a multi-engine aeroplane under given conditions (temperature and pressure altitude). | D97: N | G97: MED | K97: NOT_STARTED
A98: 032.02.02.00 | B98: 3 | C98: Intentionally left blank
A99: 032.02.03.00 | B99: 3 | C99: Take-off and landing
A100: 032.02.03.01 | B100: 4 | C100: Take-off and landing (definitions and effects)
A101: 032.02.03.01.01 | B101: 5 | C101: Define the following distances and masses: take-off distance; landing distance; ground-roll distance; maximum allowed take-off mass; maximum allowed landing mass. | D101: Y | G101: LOW | K101: NOT_STARTED
...

Sheet S033
A1: 033 Flight Planning and Monitoring
A3: LO_ID | B3: Level | C3: LO_Text | D3: BK_Only | E3: ECQB_2026_Change_Flag | F3: ECQB_2026_Source_Note | G3: Priority | H3: Content_Type_Planned | I3: Repo_Path | J3: Agent_Assigned | K3: Coverage_Status | L3: Last_Updated | M3: Reviewed_By | N3: Notes
A4: 033.01.00.00 | B4: 2 | C4: FLIGHT PLANNING FOR VFR FLIGHTS Remark: Using the GSPRM VFR charts.
A5: 033.01.01.00 | B5: 3 | C5: VFR navigation plan
A6: 033.01.01.01 | B6: 4 | C6: Airspace, communication, visual and radio-navigation data from VFR charts
A7: 033.01.01.01.01 | B7: 5 | C7: Select routes taking the following criteria into account: classification of airspace; restricted areas; VFR semicircular rules; visually conspicuous points; radio-navigation aids. | D7: N | G7: MED | K7: NOT_STARTED
A8: 033.01.01.01.02 | B8: 5 | C8: Find the frequencies or identifiers of radio-navigation aids from charts. | D8: N | G8: MED | K8: NOT_STARTED
A9: 033.01.01.01.03 | B9: 5 | C9: Find the communication frequencies and call signs for the following: control agencies and service facilities; flight information service (FIS); weather information stations; automatic terminal information service (ATIS). | D9: N | G9: MED | K9: NOT_STARTED
A10: 033.01.01.02 | B10: 4 | C10: Planning courses, distances and cruising levels with VFR charts
A11: 033.01.01.02.01 | B11: 5 | C11: Choose visual waypoints in accordance with specified criteria (large, unique, contrast, vertical extent, etc.). | D11: N | G11: MED | K11: NOT_STARTED
A12: 033.01.01.02.02 | B12: 5 | C12: Measure courses and distances from a VFR chart. | D12: N | G12: MED | K12: NOT_STARTED
A13: 033.01.01.02.03 | B13: 5 | C13: Find the highest obstacle within a given distance on either side of the course. | D13: N | G13: MED | K13: NOT_STARTED
A14: 033.01.01.02.04 | B14: 5 | C14: Find the following data from a VFR chart and transfer them to a navigation plan: waypoints or turning points; distances; true/magnetic courses. | D14: N | G14: MED | K14: NOT_STARTED
A15: 033.01.01.02.05 | B15: 5 | C15: Calculate the minimum pressure altitude with a given obstacle clearance or true altitude from a given altitude or pressure altitude from minimum grid-area altitude using outside air temperature (OAT) and QNH. | D15: N | G15: MED | K15: NOT_STARTED
A16: 033.01.01.02.06 | B16: 5 | C16: Calculate the vertical or horizontal distance and time to climb or descend to/from a given level or altitude with given data. | D16: N | G16: MED | K16: NOT_STARTED
A17: 033.01.01.02.07 | B17: 5 | C17: Explain how to determine the position of a significant VFR point for insertion into a global navigation satellite system (GNSS) flight plan, using the distance and bearing from an existing significant point and using coordinates. | D17: N | G17: MED | K17: NOT_STARTED
A18: 033.01.01.03 | B18: 4 | C18: Aerodrome charts and aerodrome directory
A19: 033.01.01.03.01 | B19: 5 | C19: Explain the reasons for studying the visual departure procedures and the available approach procedures. | D19: Y | G19: LOW | K19: NOT_STARTED
A20: 033.01.01.03.02 | B20: 5 | C20: Find all visual procedures which can be expected at the departure, destination and alternate aerodromes. | D20: N | E20: Fuel/energy scheme: basic + RCF 3% + isolated aerodrome + revised extra/discretionary fuel | G20: HIGH | K20: NOT_STARTED
A21: 033.01.01.03.03 | B21: 5 | C21: Find all relevant aeronautical and regulatory information required for VFR flight planning from the aerodrome charts or aerodrome directory. | D21: N | G21: MED | K21: NOT_STARTED
A22: 033.01.01.04 | B22: 4 | C22: Intentionally left blank
A23: 033.01.01.05 | B23: 4 | C23: Completion of navigation plan
A24: 033.01.01.05.01 | B24: 5 | C24: Calculate the true airspeed (TAS) from given aircraft performance data, altitude and OAT. | D24: N | G24: MED | K24: NOT_STARTED
A25: 033.01.01.05.02 | B25: 5 | C25: Calculate wind correction angles (WCAs), drift and ground speeds (GS). | D25: N | G25: MED | K25: NOT_STARTED
A26: 033.01.01.05.03 | B26: 5 | C26: Calculate individual and accumulated times for each leg to destination and alternate aerodromes. | D26: N | E26: Fuel/energy scheme: basic + RCF 3% + isolated aerodrome + revised extra/discretionary fuel | G26: HIGH | K26: NOT_STARTED
A27: 033.02.00.00 | B27: 2 | C27: FLIGHT PLANNING FOR IFR FLIGHTS Remark: Using the GSPRM IFR charts.
A28: 033.02.01.00 | B28: 3 | C28: IFR navigation plan
A29: 033.02.01.01 | B29: 4 | C29: Air traffic service (ATS) routes
A30: 033.02.01.01.01 | B30: 5 | C30: Identify suitable routings by identifying all relevant aeronautical and regulatory information (including information published in the national aeronautical information publication (AIP)) required for IFR flight planning. | D30: N | G30: MED | K30: NOT_STARTED
A31: 033.02.01.01.02 | B31: 5 | C31: Identify and describe ATS routes (conventional, area navigation (RNAV), required navigation performance (RNP), conditional routes (CDRs), and direct routes). | D31: N | G31: MED | K31: NOT_STARTED
A32: 033.02.01.02 | B32: 4 | C32: Courses and distances from en-route charts
A33: 033.02.01.02.01 | B33: 5 | C33: Determine courses and distances. | D33: N | G33: MED | K33: NOT_STARTED
A34: 033.02.01.02.02 | B34: 5 | C34: Determine bearings and distances of waypoints from radio-navigation aids. | D34: N | G34: MED | K34: NOT_STARTED
A35: 033.02.01.03 | B35: 4 | C35: Altitudes
A36: 033.02.01.03.01 | B36: 5 | C36: Define the following altitudes: minimum en-route altitude (MEA); minimum obstacle clearance altitude (MOCA); minimum sector altitude (MSA); minimum off-route altitude (MORA); grid minimum off-route altitude (Grid MORA); maximum authorised altitude (MAA); minimum crossing altitude (MCA); minimum holding altitude (MHA). | D36: N | G36: MED | K36: NOT_STARTED
A37: 033.02.01.03.02 | B37: 5 | C37: Extract the following altitudes from the chart(s): MEA; MOCA; MSA; MORA; Grid MORA; MAA; MCA; MHA. | D37: N | G37: MED | K37: NOT_STARTED
A38: 033.02.01.03.03 | B38: 5 | C38: State who is responsible for terrain separation during IFR flight inside and outside controlled airspace. | D38: N | G38: MED | K38: NOT_STARTED
A39: 033.02.01.03.04 | B39: 5 | C39: State the minimum obstacle clearance requirements for en-route IFR flight inside and outside controlled airspace. | D39: N | G39: MED | K39: NOT_STARTED
A40: 033.02.01.03.05 | B40: 5 | C40: State when a temperature error correction must be applied by either the pilot or ATC. | D40: N | G40: MED | K40: NOT_STARTED
A41: 033.02.01.03.06 | B41: 5 | C41: Identify and explain the use of minimum radar vectoring altitudes. | D41: N | G41: MED | K41: NOT_STARTED
A42: 033.02.01.03.07 | B42: 5 | C42: Calculate the minimum pressure altitude required with a given obstacle clearance, magnetic track, OAT, QNH and reduced vertical separation minimum (RVSM)/non-RVSM information. | D42: N | G42: MED | K42: NOT_STARTED
A43: 033.02.01.03.08 | B43: 5 | C43: Calculate true altitude above a given datum using a given pressure altitude, OAT and QNH. | D43: N | G43: MED | K43: NOT_STARTED
A44: 033.02.01.04 | B44: 4 | C44: Standard instrument departure (SID) and standard instrument arrival (STAR) routes
A45: 033.02.01.04.01 | B45: 5 | C45: State the reasons for studying SID and STAR charts. | D45: Y | G45: LOW | K45: NOT_STARTED
A46: 033.02.01.04.02 | B46: 5 | C46: State that SID and STAR charts show procedures only in a pictorial presentation style which may not be true to scale. | D46: Y | G46: LOW | K46: NOT_STARTED
A47: 033.02.01.04.03 | B47: 5 | C47: Interpret all data and information represented on SID and STAR charts, particularly: routings; distances; courses; radials; altitudes/levels; frequencies; restrictions; RNAV waypoints and non-RNAV intersection; fly-over and fly-by waypoints. | D47: N | G47: MED | K47: NOT_STARTED
A48: 033.02.01.04.04 | B48: 5 | C48: Identify SID and STAR charts which might be relevant for a planned flight. | D48: N | G48: MED | K48: NOT_STARTED
A49: 033.02.01.04.05 | B49: 5 | C49: Define SID and STAR for RNAV only. | D49: N | G49: MED | K49: NOT_STARTED
A50: 033.02.01.04.06 | B50: 5 | C50: Describe the difference between SID/STAR, RNAV SID/STAR and RNAV SID/STAR overlay. | D50: N | G50: MED | K50: NOT_STARTED
A51: 033.02.01.05 | B51: 4 | C51: Instrument-approach charts
A52: 033.02.01.05.01 | B52: 5 | C52: State the reasons for being familiar with instrument-approach procedures (IAPs) and appropriate data for departure, destination and alternate aerodromes. | D52: Y | E52: Fuel/energy scheme: basic + RCF 3% + isolated aerodrome + revised extra/discretionary fuel | G52: HIGH | K52: NOT_STARTED
A53: 033.02.01.05.02 | B53: 5 | C53: Select IAPs appropriate for departure, destination and alternate aerodromes. | D53: N | E53: Fuel/energy scheme: basic + RCF 3% + isolated aerodrome + revised extra/discretionary fuel | G53: HIGH | K53: NOT_STARTED
A54: 033.02.01.05.03 | B54: 5 | C54: Interpret all procedures, data and information represented on instrument-approach charts, particularly: courses and radials; distances; altitudes/levels/heights; restrictions; obstructions; frequencies; speeds and times; decision altitudes/heights (DAs/Hs); (DA/H) and minimum descent altitudes/heights (MDAs/Hs); visibility and runway visual ranges (RVRs); approach-light systems. | D54: N | G54: MED | K54: NOT_STARTED
A55: 033.02.01.05.04 | B55: 5 | C55: Explain the following IAP terms: type A and B; 2D and 3D; CAT I, II and III; precision approach (conventional and ground-based augmentation system (GBAS)); non-precision approach (conventional and required navigation performance approach (RNP APCH) (lateral navigation (LNAV), LNAV/vertical navigation (VNAV), localiser performance (LP), localiser performance with vertical guidance (LPV), and required navigation performance authorisation required approach (RNP AR APCH)); approach procedure with vertical guidance (APV) (APV Baro and APV satellite-based augmentation system (SBAS)). | D55: N | G55: MED | K55: NOT_STARTED
A56: 033.02.01.06 | B56: 4 | C56: Communications and radio-navigation planning data
A57: 033.02.01.06.01 | B57: 5 | C57: Find the communication frequencies and call signs for aeronautical services for IFR flights from en-route charts. | D57: N | G57: MED | K57: NOT_STARTED
A58: 033.02.01.06.02 | B58: 5 | C58: Find the frequency or identifiers of radio-navigation aids for IFR flights from en-route charts. | D58: N | G58: MED | K58: NOT_STARTED
A59: 033.02.01.07 | B59: 4 | C59: Completion of a manual navigation plan
A60: 033.02.01.07.01 | B60: 5 | C60: Complete a navigation plan with the courses, distances and frequencies taken from charts. | D60: N | G60: MED | K60: NOT_STARTED
A61: 033.02.01.07.02 | B61: 5 | C61: Find the SID and STAR routes to be flown or to be expected. | D61: N | G61: MED | K61: NOT_STARTED
A62: 033.02.01.07.03 | B62: 5 | C62: Determine the position of top of climb (TOC) and top of descent (TOD) from given appropriate data. | D62: N | G62: MED | K62: NOT_STARTED
A63: 033.02.01.07.04 | B63: 5 | C63: Determine variation and calculate magnetic/true courses. | D63: N | G63: MED | K63: NOT_STARTED
A64: 033.02.01.07.05 | B64: 5 | C64: Calculate TAS from given aircraft performance data, altitude and OAT. | D64: N | G64: MED | K64: NOT_STARTED
A65: 033.02.01.07.06 | B65: 5 | C65: Calculate wind correction angles (WCAs)/drift and ground speeds (GSs). | D65: N | G65: MED | K65: NOT_STARTED
A66: 033.02.01.07.07 | B66: 5 | C66: Calculate individual and accumulated times for each leg to destination and alternate aerodromes. | D66: N | E66: Fuel/energy scheme: basic + RCF 3% + isolated aerodrome + revised extra/discretionary fuel | G66: HIGH | K66: NOT_STARTED
A67: 033.02.01.07.08 | B67: 5 | C67: Describe the advantages of global navigation satellite system/flight management computer (GNSS/FMC) equipment regarding: automatic calculation and display of tracks and leg distances; additional route information in the database (minimum altitudes, approach procedures); time and fuel estimates over waypoints; ability to adjust speed to arrive over a waypoint at a defined time; time and fuel revisions based on predicted and actual wind. | D67: N | E67: Fuel/energy scheme: basic + RCF 3% + isolated aerodrome + revised extra/discretionary fuel | G67: HIGH | K67: NOT_STARTED
A68: 033.02.01.07.09 | B68: 5 | C68: Describe the limitations of using GNSS/FMC equipment: pilot-inputted errors (flight levels, wind, temperature, fuel); the effect of other than predicted wind on fuel and time estimates; the effect of aircraftʼs non-standard configuration on flight management system (FMS) predictions. | D68: N | E68: Fuel/energy scheme: basic + RCF 3% + isolated aerodrome + revised extra/discretionary fuel | G68: HIGH | K68: NOT_STARTED
A69: 033.03.00.00 | B69: 2 | C69: FUEL PLANNING — OPERATIONAL REQUIREMENTS
A70: 033.03.01.00 | B70: 3 | C70: General
A71: 033.03.01.01 | B71: 4 | C71: Fuel planning (general)
A72: 033.03.01.01.01 | B72: 5 | C72: Convert to volume, mass and density given in different units which are commonly used in aviation. | D72: N | G72: MED | K72: NOT_STARTED
A73: 033.03.01.01.02 | B73: 5 | C73: Determine relevant data, such as fuel capacity, fuel flow/ consumption at different power/thrust settings, altitudes and atmospheric conditions, from the flight manual. | D73: N | E73: Fuel/energy scheme: basic + RCF 3% + isolated aerodrome + revised extra/discretionary fuel | G73: HIGH | K73: NOT_STARTED
A74: 033.03.01.01.03 | B74: 5 | C74: Calculate the attainable flight time/range from given average fuel flow/consumption and available amount of fuel. | D74: N | E74: Fuel/energy scheme: basic + RCF 3% + isolated aerodrome + revised extra/discretionary fuel | G74: HIGH | K74: NOT_STARTED
A75: 033.03.01.01.04 | B75: 5 | C75: Calculate the required fuel from given average fuel flow/ consumption and required time/range to be flown. | D75: N | E75: Fuel/energy scheme: basic + RCF 3% + isolated aerodrome + revised extra/discretionary fuel | G75: HIGH | K75: NOT_STARTED
A76: 033.03.01.01.05 | B76: 5 | C76: Calculate the required fuel for a VFR flight from given forecast meteorological conditions. | D76: N | E76: Fuel/energy scheme: basic + RCF 3% + isolated aerodrome + revised extra/discretionary fuel | G76: HIGH | K76: NOT_STARTED
A77: 033.03.01.01.06 | B77: 5 | C77: State the minimum amount of remaining fuel required on arrival at the destination and alternate aerodromes/ heliports. | D77: N | E77: Fuel/energy scheme: basic + RCF 3% + isolated aerodrome + revised extra/discretionary fuel | G77: HIGH | K77: NOT_STARTED
A78: 033.03.01.01.07 | B78: 5 | C78: Explain and describe how to calculate nautical air miles (NAM) from nautical ground miles (NGM). | D78: N | G78: MED | K78: NOT_STARTED
A79: 033.03.01.01.08 | B79: 5 | C79: Calculate the required fuel for an IFR flight from given forecast meteorological conditions. | D79: N | E79: Fuel/energy scheme: basic + RCF 3% + isolated aerodrome + revised extra/discretionary fuel | G79: HIGH | K79: NOT_STARTED
A80: 033.03.02.00 | B80: 3 | C80: Pre-flight fuel planning for commercial flights
A81: 033.03.02.01 | B81: 4 | C81: Taxi fuel
A82: 033.03.02.01.01 | B82: 5 | C82: Determine the fuel required for engine start and taxiing by consulting the fuel-usage tables or graphs from the flight manual taking into account all the relevant conditions. | D82: N | E82: Fuel/energy scheme: basic + RCF 3% + isolated aerodrome + revised extra/discretionary fuel | G82: HIGH | K82: NOT_STARTED
A83: 033.03.02.02 | B83: 4 | C83: Trip fuel
A84: 033.03.02.02.01 | B84: 5 | C84: Define trip fuel and name the segments of flight for which the trip fuel is relevant. | D84: N | E84: Fuel/energy scheme: basic + RCF 3% + isolated aerodrome + revised extra/discretionary fuel | G84: HIGH | K84: NOT_STARTED
A85: 033.03.02.02.02 | B85: 5 | C85: Determine the trip fuel for the flight by using data from the fuel tables or graphs from the flight manual. | D85: N | E85: Fuel/energy scheme: basic + RCF 3% + isolated aerodrome + revised extra/discretionary fuel | G85: HIGH | K85: NOT_STARTED
A86: 033.03.02.03 | B86: 4 | C86: Reserve fuel and its components
A87: 033.03.02.03.01 | B87: 5 | C87: Explain the reasons for having contingency fuel. | D87: N | E87: Fuel/energy scheme: basic + RCF 3% + isolated aerodrome + revised extra/discretionary fuel | G87: HIGH | K87: NOT_STARTED
A88: 033.03.02.03.02 | B88: 5 | C88: Calculate the contingency fuel according to the applicable operational requirements. | D88: N | E88: Fuel/energy scheme: basic + RCF 3% + isolated aerodrome + revised extra/discretionary fuel | G88: HIGH | K88: NOT_STARTED
A89: 033.03.02.03.03 | B89: 5 | C89: Explain the reasons and regulations for having alternate fuel and name the segments of flight for which the alternate fuel is relevant. | D89: N | E89: Fuel/energy scheme: basic + RCF 3% + isolated aerodrome + revised extra/discretionary fuel | G89: HIGH | K89: NOT_STARTED
A90: 033.03.02.03.04 | B90: 5 | C90: Calculate the alternate fuel in accordance with the applicable operational requirements and relevant data from the navigation plan and the flight manual. | D90: N | E90: Fuel/energy scheme: basic + RCF 3% + isolated aerodrome + revised extra/discretionary fuel | G90: HIGH | K90: NOT_STARTED
A91: 033.03.02.03.05 | B91: 5 | C91: Explain the reasons and regulations for having final reserve fuel. | D91: N | E91: Fuel/energy scheme: basic + RCF 3% + isolated aerodrome + revised extra/discretionary fuel | G91: HIGH | K91: NOT_STARTED
A92: 033.03.02.03.06 | B92: 5 | C92: Calculate the final reserve fuel for an aircraft in accordance with the applicable operational requirements and by using relevant data from the flight manual. | D92: N | E92: Fuel/energy scheme: basic + RCF 3% + isolated aerodrome + revised extra/discretionary fuel | G92: HIGH | K92: NOT_STARTED
A93: 033.03.02.03.07 | B93: 5 | C93: Explain the reasons and regulations for having additional fuel. | D93: N | E93: Fuel/energy scheme: basic + RCF 3% + isolated aerodrome + revised extra/discretionary fuel | G93: HIGH | K93: NOT_STARTED
A94: 033.03.02.03.08 | B94: 5 | C94: Calculate the additional fuel for a flight in accordance with the applicable operational requirements. | D94: N | E94: Fuel/energy scheme: basic + RCF 3% + isolated aerodrome + revised extra/discretionary fuel | G94: HIGH | K94: NOT_STARTED
A95: 033.03.02.04 | B95: 4 | C95: Extra fuel
A96: 033.03.02.04.01 | B96: 5 | C96: Explain the reasons and regulations for having extra fuel in accordance with the applicable operational requirements. | D96: N | E96: Fuel/energy scheme: basic + RCF 3% + isolated aerodrome + revised extra/discretionary fuel | G96: HIGH | K96: NOT_STARTED
A97: 033.03.02.04.02 | B97: 5 | C97: Calculate the possible extra fuel under given conditions. | D97: N | E97: Fuel/energy scheme: basic + RCF 3% + isolated aerodrome + revised extra/discretionary fuel | G97: HIGH | K97: NOT_STARTED
A98: 033.03.02.04.03 | B98: 5 | C98: Explain the fuel penalty incurred when loading extra fuel (i.e. the additional fuel consumption due to increased mass). | D98: N | E98: Fuel/energy scheme: basic + RCF 3% + isolated aerodrome + revised extra/discretionary fuel | G98: HIGH | K98: NOT_STARTED
A99: 033.03.02.05 | B99: 4 | C99: Calculation of total fuel and completion of the fuel section of the navigation plan (fuel plan)
A100: 033.03.02.05.01 | B100: 5 | C100: Calculate the total fuel required for a given flight. | D100: N | E100: Fuel/energy scheme: basic + RCF 3% + isolated aerodrome + revised extra/discretionary fuel | G100: HIGH | K100: NOT_STARTED
A101: 033.03.02.05.02 | B101: 5 | C101: Complete the fuel plan. | D101: N | E101: Fuel/energy scheme: basic + RCF 3% + isolated aerodrome + revised extra/discretionary fuel | G101: HIGH | K101: NOT_STARTED
...

Sheet S040
A1: 040 Human Performance and Limitations
A3: LO_ID | B3: Level | C3: LO_Text | D3: BK_Only | E3: ECQB_2026_Change_Flag | F3: ECQB_2026_Source_Note | G3: Priority | H3: Content_Type_Planned | I3: Repo_Path | J3: Agent_Assigned | K3: Coverage_Status | L3: Last_Updated | M3: Reviewed_By | N3: Notes
A4: 040.01.00.00 | B4: 2 | C4: HUMAN FACTORS: BASIC CONCEPTS
A5: 040.01.01.00 | B5: 3 | C5: Human factors in aviation
A6: 040.01.01.01 | B6: 4 | C6: Becoming a competent pilot
A7: 040.01.01.01.01 | B7: 5 | C7: State that competence is based on knowledge, skills and attitudes of the individual pilot, and list the ICAO eight core competencies: application of procedures; communication; aircraft flight path management, automation; aircraft flight path management, manual control; leadership and teamwork; problem-solving and decision-making; situation awareness; workload management. | D7: N | G7: MED | K7: NOT_STARTED
A8: 040.01.02.00 | B8: 3 | C8: Intentionally left blank
A9: 040.01.03.00 | B9: 3 | C9: Flight safety concepts
A10: 040.01.03.01 | B10: 4 | C10: Threat and error management (TEM) model and SHELL model
A11: 040.01.03.01.01 | B11: 5 | C11: Explain the three components of the TEM model. | D11: N | G11: MED | K11: NOT_STARTED
A12: 040.01.03.01.02 | B12: 5 | C12: Explain and give examples of latent threats. | D12: N | G12: MED | K12: NOT_STARTED
A13: 040.01.03.01.03 | B13: 5 | C13: Explain and give examples of environmental threats. | D13: N | G13: MED | K13: NOT_STARTED
A14: 040.01.03.01.04 | B14: 5 | C14: Explain and give examples of organisational threats. | D14: N | G14: MED | K14: NOT_STARTED
A15: 040.01.03.01.05 | B15: 5 | C15: Explain and give a definition of ‘error’ according to the TEM model of ICAO Doc 9683 (Part II, Chapter 2). | D15: N | G15: MED | K15: NOT_STARTED
A16: 040.01.03.01.06 | B16: 5 | C16: Give examples of different countermeasures which may be used in order to manage threats, errors, and undesired aircraft states. | D16: N | G16: MED | K16: NOT_STARTED
A17: 040.01.03.01.07 | B17: 5 | C17: Explain and give examples of procedural error, communication errors, and aircraft handling errors. | D17: N | G17: MED | K17: NOT_STARTED
A18: 040.01.03.01.08 | B18: 5 | C18: Explain and give examples of ‘undesired aircraft states’. | D18: N | G18: MED | K18: NOT_STARTED
A19: 040.01.03.01.09 | B19: 5 | C19: State the components of the SHELL model. | D19: N | G19: MED | K19: NOT_STARTED
A20: 040.01.03.01.10 | B20: 5 | C20: State the relevance of the SHELL model to the work in the cockpit. | D20: N | G20: MED | K20: NOT_STARTED
A21: 040.01.04.00 | B21: 3 | C21: Safety culture
A22: 040.01.04.01 | B22: 4 | C22: Safety culture and safety management
A23: 040.01.04.01.01 | B23: 5 | C23: Distinguish between ‘open cultures’ and ‘closed cultures’. | D23: N | G23: MED | K23: NOT_STARTED
A24: 040.01.04.01.02 | B24: 5 | C24: Illustrate how safety culture is reflected in national culture. | D24: N | G24: MED | K24: NOT_STARTED
A25: 040.01.04.01.03 | B25: 5 | C25: Discuss the established expression ‘safety first’ in a commercial entity. | D25: N | G25: MED | K25: NOT_STARTED
A26: 040.01.04.01.04 | B26: 5 | C26: Explain James Reason’s ‘Swiss Cheese Model’. | D26: N | G26: MED | K26: NOT_STARTED
A27: 040.01.04.01.05 | B27: 5 | C27: State the important factors that promote a good safety culture. | D27: N | G27: MED | K27: NOT_STARTED
A28: 040.01.04.01.06 | B28: 5 | C28: Distinguish between ‘just culture’ and ‘non-punitive culture’. | D28: N | G28: MED | K28: NOT_STARTED
A29: 040.01.04.01.07 | B29: 5 | C29: Name the five components which form safety culture (according to James Reason: informed culture, reporting culture, learning culture, just culture, flexible culture). | D29: N | G29: MED | K29: NOT_STARTED
A30: 040.01.04.01.08 | B30: 5 | C30: Name the basic concepts of safety management system (SMS) (including hazard identification and risk management) and its relationship with safety culture in order to: define how the organisation is set up to manage risks; identify workplace risk and implement suitable controls; implement effective communication across all levels of the organisation. | D30: N | G30: MED | K30: NOT_STARTED
A31: 040.02.00.00 | B31: 2 | C31: Basics of aviation physiology and health maintenance
A32: 040.02.01.00 | B32: 3 | C32: Basics of flight physiology
A33: 040.02.01.01 | B33: 4 | C33: The atmosphere
A34: 040.02.01.01.01 | B34: 5 | C34: State that the volume percentage of the gases in ambient air will remain constant at all altitudes at which conventional aircraft operate. | D34: N | G34: MED | K34: NOT_STARTED
A35: 040.02.01.02 | B35: 4 | C35: Respiratory and circulatory system
A36: 040.02.01.02.01 | B36: 5 | C36: List the main components of the respiratory system and their function. | D36: N | G36: MED | K36: NOT_STARTED
A37: 040.02.01.02.02 | B37: 5 | C37: Identify the different volumes of air in the lungs and state the normal respiratory rate. | D37: N | G37: MED | K37: NOT_STARTED
A38: 040.02.01.02.03 | B38: 5 | C38: Explain the role of carbon dioxide in the control and regulation of respiration. | D38: N | G38: MED | K38: NOT_STARTED
A39: 040.02.01.02.04 | B39: 5 | C39: Describe the basic processes of external respiration and internal respiration. | D39: N | G39: MED | K39: NOT_STARTED
A40: 040.02.01.02.05 | B40: 5 | C40: List the factors that determine pulse rate. | D40: N | G40: MED | K40: NOT_STARTED
A41: 040.02.01.02.06 | B41: 5 | C41: Name the major components of the circulatory system and describe their function. | D41: N | G41: MED | K41: NOT_STARTED
A42: 040.02.01.02.07 | B42: 5 | C42: State the values for a normal pulse rate and the average cardiac output (heart rate × stroke volume) of an adult at rest. | D42: N | G42: MED | K42: NOT_STARTED
A43: 040.02.01.02.08 | B43: 5 | C43: Define ‘systolic’ and ‘diastolic’ blood pressure. | D43: N | G43: MED | K43: NOT_STARTED
A44: 040.02.01.02.09 | B44: 5 | C44: State the normal blood pressure ranges and units of measurement. | D44: N | G44: MED | K44: NOT_STARTED
A45: 040.02.01.02.10 | B45: 5 | C45: List the main constituents of blood and describe their functions. | D45: N | G45: MED | K45: NOT_STARTED
A46: 040.02.01.02.11 | B46: 5 | C46: Stress the function of haemoglobin in the circulatory system. | D46: N | G46: MED | K46: NOT_STARTED
A47: 040.02.01.02.12 | B47: 5 | C47: Define ‘anaemia’ and state its common causes. | D47: N | G47: MED | K47: NOT_STARTED
... A87: 040.02.01.02.52 | B87: 5 | C87: Explain immediate countermeasures on suspicion of carbon-monoxide poisoning and how poisoning can be treated later on the ground. | D87: N | G87: MED | K87: NOT_STARTED
A88: 040.02.01.03 | B88: 4 | C88: High-altitude environment
A89: 040.02.01.03.01 | B89: 5 | C89: State how an increase in altitude may change the proportion of ozone in the atmosphere and that aircraft can be equipped with special ozone removers. | D89: N | G89: MED | K89: NOT_STARTED
A90: 040.02.01.03.02 | B90: 5 | C90: State the sources of radiation at high altitude. | D90: N | G90: MED | K90: NOT_STARTED
A91: 040.02.01.03.03 | B91: 5 | C91: List the effects of excessive exposure to radiation. | D91: N | G91: MED | K91: NOT_STARTED
A92: 040.02.01.03.04 | B92: 5 | C92: List the factors that affect the relative humidity of both the atmosphere and cabin air. | D92: N | G92: MED | K92: NOT_STARTED
A93: 040.02.01.03.05 | B93: 5 | C93: List the effects of low humidity on human body to be spurious thirst, dry eyes, skin and mucous membranes, and indicate measures that can be taken: drinking water, using eye drops and aqueous creams. | D93: N | G93: MED | K93: NOT_STARTED
A94: 040.02.02.00 | B94: 3 | C94: People and the environment: the sensory system
A95: 040.02.02.01 | B95: 4 | C95: The different senses
A96: 040.02.02.01.01 | B96: 5 | C96: List the different senses. | D96: N | G96: MED | K96: NOT_STARTED
A97: 040.02.02.02 | B97: 4 | C97: Central, peripheral and autonomic nervous system
A98: 040.02.02.02.01 | B98: 5 | C98: Define the term ‘sensory threshold’. | D98: N | G98: MED | K98: NOT_STARTED
A99: 040.02.02.02.02 | B99: 5 | C99: Define the term ‘sensitivity’, especially in the context of vision. | D99: N | G99: MED | K99: NOT_STARTED
A100: 040.02.02.02.03 | B100: 5 | C100: Give examples of sensory adaptation. | D100: N | G100: MED | K100: NOT_STARTED
A101: 040.02.02.02.04 | B101: 5 | C101: Define the term ‘habituation’ and state its implication for flight safety. | D101: N | G101: MED | K101: NOT_STARTED
A102: 040.02.02.03 | B102: 4 | C102: Vision
A103: 040.02.02.03.01 | B103: 5 | C103: Name the most important parts of the eye and the pathway to the visual cortex. | D103: N | G103: MED | K103: NOT_STARTED
A104: 040.02.02.03.02 | B104: 5 | C104: State the basic functions of the parts of the eye. | D104: N | G104: MED | K104: NOT_STARTED
A105: 040.02.02.03.03 | B105: 5 | C105: Define ‘accommodation’. | D105: N | G105: MED | K105: NOT_STARTED
A106: 040.02.02.03.04 | B106: 5 | C106: Distinguish between the functions of the rod and cone cells. | D106: N | G106: MED | K106: NOT_STARTED
A107: 040.02.02.03.05 | B107: 5 | C107: Describe the distribution of rod and cone cells in the retina and explain their relevance to vision. | D107: N | G107: MED | K107: NOT_STARTED
A108: 040.02.02.03.06 | B108: 5 | C108: Explain the terms ‘visual acuity’, ‘visual field’, ‘central vision’, ‘peripheral vision’ and ‘the fovea’, and explain their function in the process of vision. | D108: N | G108: MED | K108: NOT_STARTED
A109: 040.02.02.03.07 | B109: 5 | C109: List the factors that may degrade visual acuity and the importance of ‘lookout’. | D109: N | G109: MED | K109: NOT_STARTED
A110: 040.02.02.03.08 | B110: 5 | C110: State the limitations of night vision and the different scanning techniques at both night and day. | D110: N | G110: MED | K110: NOT_STARTED
A111: 040.02.02.03.09 | B111: 5 | C111: State the time necessary for the eye to adapt both to bright light and the dark. | D111: N | G111: MED | K111: NOT_STARTED
A112: 040.02.02.03.10 | B112: 5 | C112: State the effect of hypoxia, smoking and altitude in excess of 5 000 ft on night vision. | D112: N | G112: MED | K112: NOT_STARTED
A113: 040.02.02.03.11 | B113: 5 | C113: Explain the nature of colour blindness. | D113: N | G113: MED | K113: NOT_STARTED
A114: 040.02.02.03.12 | B114: 5 | C114: Distinguish between monocular and binocular vision. | D114: N | G114: MED | K114: NOT_STARTED
... A124: 040.02.02.03.22 | B124: 5 | C124: Explain the significance of the ‘blind spot’ on the retina in detecting other traffic in flight. | D124: N | G124: MED | K124: NOT_STARTED
A125: 040.02.02.04 | B125: 4 | C125: Hearing
A126: 040.02.02.04.01 | B126: 5 | C126: State the basic parts and functions of the outer, the middle and the inner ear. | D126: N | G126: MED | K126: NOT_STARTED
A127: 040.02.02.04.02 | B127: 5 | C127: Differentiate between the functions of the vestibular apparatus and the cochlea in the inner ear. | D127: N | G127: MED | K127: NOT_STARTED
A128: 040.02.02.04.03 | B128: 5 | C128: Define the main causes of the following hearing defects/loss: ‘conductive deafness’; ‘noise-induced hearing loss’ (NIHL); ‘presbycusis’. | D128: N | G128: MED | K128: NOT_STARTED
A129: 040.02.02.04.04 | B129: 5 | C129: Summarise the effects of environmental noise on hearing. | D129: N | G129: MED | K129: NOT_STARTED
A130: 040.02.02.04.05 | B130: 5 | C130: State the decibel level of received noise that will cause NIHL. | D130: N | G130: MED | K130: NOT_STARTED
A131: 040.02.02.04.06 | B131: 5 | C131: Identify the potential occupational risks that may cause hearing loss. | D131: N | G131: MED | K131: NOT_STARTED
A132: 040.02.02.04.07 | B132: 5 | C132: List the main sources of hearing loss in the flying environment. | D132: N | G132: MED | K132: NOT_STARTED
A133: 040.02.02.04.08 | B133: 5 | C133: List the precautions that may be taken to reduce the probability of onset of hearing loss. | D133: N | G133: MED | K133: NOT_STARTED
A134: 040.02.02.05 | B134: 4 | C134: Equilibrium
A135: 040.02.02.05.01 | B135: 5 | C135: List the main elements of the vestibular apparatus. | D135: N | G135: MED | K135: NOT_STARTED
A136: 040.02.02.05.02 | B136: 5 | C136: State the functions of the vestibular apparatus on the ground and in flight. | D136: N | G136: MED | K136: NOT_STARTED
A137: 040.02.02.05.03 | B137: 5 | C137: Distinguish between the component parts of the vestibular apparatus in the detection of linear and angular acceleration as well as on gravity. | D137: N | G137: MED | K137: NOT_STARTED
A138: 040.02.02.05.04 | B138: 5 | C138: Explain how the semicircular canals are stimulated. | D138: N | G138: MED | K138: NOT_STARTED
A139: 040.02.02.05.05 | B139: 5 | C139: Describe air sickness and its accompanying symptoms. | D139: N | G139: MED | K139: NOT_STARTED
A140: 040.02.02.05.06 | B140: 5 | C140: List the causes of air sickness. | D140: N | G140: MED | K140: NOT_STARTED
A141: 040.02.02.05.07 | B141: 5 | C141: Describe the necessary actions to be taken to counteract the symptoms of air sickness. | D141: N | G141: MED | K141: NOT_STARTED
A142: 040.02.02.06 | B142: 4 | C142: Integration of sensory inputs
A143: 040.02.02.06.01 | B143: 5 | C143: State the interaction between vision, equilibrium, proprioception and hearing to obtain spatial orientation in flight. | D143: N | G143: MED | K143: NOT_STARTED
A144: 040.02.02.06.02 | B144: 5 | C144: Define the term ‘illusion’. | D144: N | G144: MED | K144: NOT_STARTED
A145: 040.02.02.06.03 | B145: 5 | C145: Give examples of visual illusions based on shape constancy, size constancy, aerial perspective, atmospheric perspective, the absence of focal or ambient cues, autokinesis, vectional false horizons, field myopia, and surface planes. | D145: N | G145: MED | K145: NOT_STARTED
A146: 040.02.02.06.04 | B146: 5 | C146: Relate these illusions to problems that may be experienced in flight and identify the danger attached to them. | D146: N | G146: MED | K146: NOT_STARTED
A147: 040.02.02.06.05 | B147: 5 | C147: List approach and landing illusions for slope of the runway, black-hole approach, and terrain around runway, and state the danger involved with recommendations to avoid or counteract the problems with high or low approach or flare at the wrong time. | D147: N | G147: MED | K147: NOT_STARTED
A148: 040.02.02.06.06 | B148: 5 | C148: State the problems associated with flickering lights (strobe lights, anti-collision lights, propellers and rotors under certain light conditions, etc.). | D148: N | G148: MED | K148: NOT_STARTED
A149: 040.02.02.06.07 | B149: 5 | C149: Describe vestibular illusions caused by the angular accelerations (the Leans, Coriolis) and linear accelerations (somatogravic, G-effect). | D149: N | G149: MED | K149: NOT_STARTED
...

Sheet S050
A1: 050 Meteorology
A3: LO_ID | B3: Level | C3: LO_Text | D3: BK_Only | E3: ECQB_2026_Change_Flag | F3: ECQB_2026_Source_Note | G3: Priority | H3: Content_Type_Planned | I3: Repo_Path | J3: Agent_Assigned | K3: Coverage_Status | L3: Last_Updated | M3: Reviewed_By | N3: Notes
A4: 050.01.00.00 | B4: 2 | C4: THE ATMOSPHERE
A5: 050.01.01.00 | B5: 3 | C5: Composition, extent, vertical division
A6: 050.01.01.01 | B6: 4 | C6: Structure of the atmosphere
A7: 050.01.01.01.01 | B7: 5 | C7: Describe the vertical division of the atmosphere up to flight level (FL) 650, based on the temperature variations with height. | D7: N | G7: MED | K7: NOT_STARTED
A8: 050.01.01.01.02 | B8: 5 | C8: List the different layers and their main qualitative characteristics up to FL 650. | D8: N | G8: MED | K8: NOT_STARTED
A9: 050.01.01.02 | B9: 4 | C9: Troposphere
A10: 050.01.01.02.01 | B10: 5 | C10: Describe the troposphere. | D10: N | G10: MED | K10: NOT_STARTED
A11: 050.01.01.02.02 | B11: 5 | C11: Describe the main characteristics of the tropopause. | D11: N | G11: MED | K11: NOT_STARTED
A12: 050.01.01.02.03 | B12: 5 | C12: Describe the proportions of the most important gases in the air in the troposphere. | D12: N | G12: MED | K12: NOT_STARTED
A13: 050.01.01.02.04 | B13: 5 | C13: Describe the variations of the FL and temperature of the tropopause from the poles to the equator. | D13: N | G13: MED | K13: NOT_STARTED
A14: 050.01.01.02.05 | B14: 5 | C14: Describe the breaks in the tropopause along the boundaries of the main air masses. | D14: N | G14: MED | K14: NOT_STARTED
A15: 050.01.01.02.06 | B15: 5 | C15: Indicate the variations of the FL of the tropopause with the seasons and the variations of atmospheric pressure. | D15: N | G15: MED | K15: NOT_STARTED
A16: 050.01.01.03 | B16: 4 | C16: Stratosphere
A17: 050.01.01.03.01 | B17: 5 | C17: Describe the stratosphere up to FL 650. | D17: N | G17: MED | K17: NOT_STARTED
A18: 050.01.01.03.02 | B18: 5 | C18: Describe that ozone can occur at jet cruise altitudes and that it constitutes a hazard. | D18: N | G18: MED | K18: NOT_STARTED
A19: 050.01.02.00 | B19: 3 | C19: Air temperature
A20: 050.01.02.01 | B20: 4 | C20: Definition and units
A21: 050.01.02.01.01 | B21: 5 | C21: Define ‘air temperature’. | D21: N | G21: MED | K21: NOT_STARTED
A22: 050.01.02.01.02 | B22: 5 | C22: List the units of measurement of air temperature used in aviation meteorology (Celsius, Fahrenheit, Kelvin). (Refer to Subject 050 10 01 01) | D22: Y | G22: LOW | K22: NOT_STARTED
A23: 050.01.02.02 | B23: 4 | C23: Vertical distribution of temperature
A24: 050.01.02.02.01 | B24: 5 | C24: Describe the mean vertical distribution of temperature up to FL 650. | D24: N | G24: MED | K24: NOT_STARTED
A25: 050.01.02.02.02 | B25: 5 | C25: Mention the general causes of the cooling of the air in the troposphere with increasing altitude. | D25: N | G25: MED | K25: NOT_STARTED
A26: 050.01.02.02.03 | B26: 5 | C26: Calculate the temperature and temperature deviations (in relation to International Standard Atmosphere (ISA)) at specified levels. | D26: N | G26: MED | K26: NOT_STARTED
A27: 050.01.02.03 | B27: 4 | C27: Transfer of heat
A28: 050.01.02.03.01 | B28: 5 | C28: Explain how local cooling or warming processes result in transfer of heat. | D28: N | G28: MED | K28: NOT_STARTED
A29: 050.01.02.03.02 | B29: 5 | C29: Describe radiation. | D29: N | G29: MED | K29: NOT_STARTED
A30: 050.01.02.03.03 | B30: 5 | C30: Describe solar radiation reaching the Earth. | D30: N | G30: MED | K30: NOT_STARTED
A31: 050.01.02.03.04 | B31: 5 | C31: Describe the filtering effect of the atmosphere on solar radiation. | D31: N | G31: MED | K31: NOT_STARTED
A32: 050.01.02.03.05 | B32: 5 | C32: Describe terrestrial radiation. | D32: N | G32: MED | K32: NOT_STARTED
A33: 050.01.02.03.06 | B33: 5 | C33: Explain how terrestrial radiation is absorbed by some components of the atmosphere. | D33: N | G33: MED | K33: NOT_STARTED
A34: 050.01.02.03.07 | B34: 5 | C34: Explain the effect of absorption and radiation in connection with clouds. | D34: N | G34: MED | K34: NOT_STARTED
A35: 050.01.02.03.08 | B35: 5 | C35: Explain the process of conduction. | D35: N | G35: MED | K35: NOT_STARTED
A36: 050.01.02.03.09 | B36: 5 | C36: Explain the role of conduction in the cooling and warming of the atmosphere. | D36: N | G36: MED | K36: NOT_STARTED
A37: 050.01.02.03.10 | B37: 5 | C37: Explain the process of convection. | D37: N | G37: MED | K37: NOT_STARTED
A38: 050.01.02.03.11 | B38: 5 | C38: Name the situations in which convection occurs. | D38: N | G38: MED | K38: NOT_STARTED
A39: 050.01.02.03.12 | B39: 5 | C39: Explain the process of advection. | D39: N | G39: MED | K39: NOT_STARTED
... A42: 050.01.02.03.15 | B42: 5 | C42: Describe the transfer of latent heat. | D42: N | G42: MED | K42: NOT_STARTED
A43: 050.01.02.04 | B43: 4 | C43: Lapse rates
A44: 050.01.02.04.01 | B44: 5 | C44: Describe qualitatively and quantitatively the temperature lapse rates of the troposphere (mean value 0.65 degrees C/100 m or 2 degrees C/1 000 ft and actual values). | D44: N | G44: MED | K44: NOT_STARTED
A45: 050.01.02.05 | B45: 4 | C45: Development of inversions, types of inversions
A46: 050.01.02.05.01 | B46: 5 | C46: Describe the development and types of inversions. | D46: N | G46: MED | K46: NOT_STARTED
A47: 050.01.02.05.02 | B47: 5 | C47: Explain the characteristics of inversions and of an isothermal layer concerning stability and vertical motions. | D47: N | G47: MED | K47: NOT_STARTED
A48: 050.01.02.05.03 | B48: 5 | C48: Explain the reasons for the formation of the following inversions: ground inversion (nocturnal radiation/advection), subsidence inversion, frontal inversion, inversion above friction layer, valley inversion. | D48: N | G48: MED | K48: NOT_STARTED
A49: 050.01.02.06 | B49: 4 | C49: Temperature near the Earth’s surface, insolation, surface effects, effect of clouds, effect of wind
A50: 050.01.02.06.01 | B50: 5 | C50: Explain the cooling/warming of the surface of the Earth by radiation. | D50: N | G50: MED | K50: NOT_STARTED
A51: 050.01.02.06.02 | B51: 5 | C51: Explain the cooling/warming of the air by molecular or turbulent heat transfer to/from the earth or sea surfaces. | D51: N | G51: MED | K51: NOT_STARTED
A52: 050.01.02.06.03 | B52: 5 | C52: Describe qualitatively the influence of the clouds on the cooling and warming of the surface and the air near the surface. | D52: N | G52: MED | K52: NOT_STARTED
A53: 050.01.02.06.04 | B53: 5 | C53: Explain the influence of the wind on the cooling and warming of the air near the surfaces. | D53: N | G53: MED | K53: NOT_STARTED
A54: 050.01.03.00 | B54: 3 | C54: Atmospheric pressure
A55: 050.01.03.01 | B55: 4 | C55: Barometric pressure, isobars
A56: 050.01.03.01.01 | B56: 5 | C56: Define ‘atmospheric pressure’. | D56: N | G56: MED | K56: NOT_STARTED
A57: 050.01.03.01.02 | B57: 5 | C57: List the units of measurement of the atmospheric pressure used in aviation (hPa, inches of mercury). (Refer to Subject 050 10 01 01) | D57: Y | G57: LOW | K57: NOT_STARTED
A58: 050.01.03.01.03 | B58: 5 | C58: Describe the principle of the barometers (mercury barometer, aneroid barometer). | D58: Y | G58: LOW | K58: NOT_STARTED
A59: 050.01.03.01.04 | B59: 5 | C59: Define isobars and identify them on surface weather charts. | D59: N | G59: MED | K59: NOT_STARTED
A60: 050.01.03.01.05 | B60: 5 | C60: Define ‘high’, ‘low’, ‘trough’, ‘ridge’, ‘col’. | D60: N | G60: MED | K60: NOT_STARTED
A61: 050.01.03.02 | B61: 4 | C61: Pressure variation with height, contours (isohypses)
A62: 050.01.03.02.01 | B62: 5 | C62: Explain the pressure variation with height. | D62: N | G62: MED | K62: NOT_STARTED
A63: 050.01.03.02.02 | B63: 5 | C63: Describe quantitatively the variation of the barometric lapse rate. Remark: An approximation of the average value for the barometric lapse rate near mean sea level (MSL) is 30 ft (9 m) per 1 hPa. | D63: N | G63: MED | K63: NOT_STARTED
A64: 050.01.03.02.03 | B64: 5 | C64: State that (under conditions of ISA) pressure is approximately 50 per cent of MSL at 18 000 ft and density is approximately 50 per cent of MSL at 22 000 ft and 25 per cent of MSL at 40 000 ft. | D64: N | G64: MED | K64: NOT_STARTED
A65: 050.01.03.03 | B65: 4 | C65: Reduction of pressure to QFF (MSL)
A66: 050.01.03.03.01 | B66: 5 | C66: Define ‘QFF’. | D66: N | G66: MED | K66: NOT_STARTED
A67: 050.01.03.03.02 | B67: 5 | C67: Explain the reduction of measured pressure (QFE) to QFF (MSL). | D67: N | G67: MED | K67: NOT_STARTED
A68: 050.01.03.03.03 | B68: 5 | C68: Mention the use of QFF for surface weather charts. | D68: N | G68: MED | K68: NOT_STARTED
A69: 050.01.03.04 | B69: 4 | C69: Relationship between surface pressure centres and pressure centres aloft
A70: 050.01.03.04.01 | B70: 5 | C70: Illustrate with a vertical cross section of isobaric surfaces the relationship between surface pressure systems and upper-air pressure systems. | D70: N | G70: MED | K70: NOT_STARTED
A71: 050.01.04.00 | B71: 3 | C71: Air density
A72: 050.01.04.01 | B72: 4 | C72: Relationship between pressure, temperature and density
A73: 050.01.04.01.01 | B73: 5 | C73: Describe the relationship between pressure, temperature and density. | D73: N | G73: MED | K73: NOT_STARTED
A74: 050.01.04.01.02 | B74: 5 | C74: Describe the vertical variation of the air density in the atmosphere. | D74: N | G74: MED | K74: NOT_STARTED
A75: 050.01.05.00 | B75: 3 | C75: International Standard Atmosphere (ISA)
A76: 050.01.05.01 | B76: 4 | C76: International Standard Atmosphere (ISA)
A77: 050.01.05.01.01 | B77: 5 | C77: Explain the use of standardised values for the atmosphere. | D77: N | G77: MED | K77: NOT_STARTED
A78: 050.01.05.01.02 | B78: 5 | C78: List the main values of the ISA MSL pressure, MSL temperature, the vertical temperature lapse rate up to FL 650, height and temperature of the tropopause. | D78: N | G78: MED | K78: NOT_STARTED
A79: 050.01.06.00 | B79: 3 | C79: Altimetry
A80: 050.01.06.01 | B80: 4 | C80: Terminology and definitions
A81: 050.01.06.01.01 | B81: 5 | C81: Define the following terms and explain how they are related to each other: height, altitude, pressure altitude, FL, pressure level, true altitude, true height, elevation, QNH, QFE, and standard altimeter setting. | D81: N | G81: MED | K81: NOT_STARTED
A82: 050.01.06.01.02 | B82: 5 | C82: Describe the terms ‘transition altitude’, ‘transition level’, ‘transition layer’, ‘terrain clearance’, ‘lowest usable flight level’. | D82: N | G82: MED | K82: NOT_STARTED
A83: 050.01.06.02 | B83: 4 | C83: Altimeter settings
A84: 050.01.06.02.01 | B84: 5 | C84: Name the altimeter settings associated to height, altitude, pressure altitude and FL. | D84: N | G84: MED | K84: NOT_STARTED
A85: 050.01.06.02.02 | B85: 5 | C85: Describe the altimeter-setting procedures. | D85: N | G85: MED | K85: NOT_STARTED
A86: 050.01.06.03 | B86: 4 | C86: Calculations
A87: 050.01.06.03.01 | B87: 5 | C87: Calculate the different readings on the altimeter when the pilot uses different settings (QNH, 1013.25, QFE). | D87: N | G87: MED | K87: NOT_STARTED
A88: 050.01.06.03.02 | B88: 5 | C88: Illustrate with a numbered example the changes of altimeter setting and the associated changes in reading when the pilot climbs through the transition altitude or descends through the transition level. | D88: N | G88: MED | K88: NOT_STARTED
A89: 050.01.06.03.03 | B89: 5 | C89: Derive the reading of the altimeter of an aircraft on the ground when the pilot uses the different settings. | D89: N | G89: MED | K89: NOT_STARTED
A90: 050.01.06.03.04 | B90: 5 | C90: Explain the influence of the air temperature on the distance between the ground and the level read on the altimeter and between two FLs. | D90: N | G90: MED | K90: NOT_STARTED
A91: 050.01.06.03.05 | B91: 5 | C91: Explain the influence of pressure areas on true altitude. | D91: N | G91: MED | K91: NOT_STARTED
A92: 050.01.06.03.06 | B92: 5 | C92: Determine the true altitude/height for a given altitude/height and a given ISA temperature deviation. | D92: N | G92: MED | K92: NOT_STARTED
A93: 050.01.06.03.07 | B93: 5 | C93: Calculate the terrain clearance and the lowest usable FL for given atmospheric temperature and pressure conditions. | D93: N | G93: MED | K93: NOT_STARTED
A94: 050.01.06.03.08 | B94: 5 | C94: State that the 4 per cent-rule can be used to calculate true altitude from indicated altitude, and also indicated altitude from true altitude (not precise but sufficient due to the approximation of the 4 per cent-rule.) | D94: N | G94: MED | K94: NOT_STARTED
A95: 050.01.06.04 | B95: 4 | C95: Effect of accelerated airflow due to topography
A96: 050.01.06.04.01 | B96: 5 | C96: Describe qualitatively how the effect of accelerated airflow due to topography (the Bernoulli effect) affects altimetry. | D96: N | G96: MED | K96: NOT_STARTED
A97: 050.02.00.00 | B97: 2 | C97: WIND
A98: 050.02.01.00 | B98: 3 | C98: Definition and measurement of wind
A99: 050.02.01.01 | B99: 4 | C99: Definition and measurement
A100: 050.02.01.01.01 | B100: 5 | C100: Define ‘wind’ and ‘surface wind’. | D100: N | G100: MED | K100: NOT_STARTED
A101: 050.02.01.01.02 | B101: 5 | C101: State the units of wind directions (degrees true in reports; degrees magnetic from tower) and speed (kt, m/s). | D101: N | G101: MED | K101: NOT_STARTED
A102: 050.02.01.01.03 | B102: 5 | C102: Describe that the reported wind is an average wind derived from measurements with an anemometer at a height of 10 m over 2 min for local routine and special reports and ATS units, and over 10 min for aerodrome routine meteorological reports (METARs) and aerodrome special meteorological reports (SPECIs). | D102: N | G102: MED | K102: NOT_STARTED
A103: 050.02.02.00 | B103: 3 | C103: Primary cause of wind
...

Sheet S061
A1: 061 General Navigation
A3: LO_ID | B3: Level | C3: LO_Text | D3: BK_Only | E3: ECQB_2026_Change_Flag | F3: ECQB_2026_Source_Note | G3: Priority | H3: Content_Type_Planned | I3: Repo_Path | J3: Agent_Assigned | K3: Coverage_Status | L3: Last_Updated | M3: Reviewed_By | N3: Notes
A4: 061.01.00.00 | B4: 2 | C4: BASICS OF NAVIGATION
A5: 061.01.01.00 | B5: 3 | C5: The Earth
A6: 061.01.01.01 | B6: 4 | C6: Form
A7: 061.01.01.01.01 | B7: 5 | C7: State that the geoid is an irregular shape based on the surface of the oceans influenced only by gravity and centrifugal force. | D7: Y | G7: LOW | K7: NOT_STARTED
A8: 061.01.01.01.02 | B8: 5 | C8: State that a number of different ellipsoids are used to describe the shape of the Earth for mapping but that WGS-84 is the reference ellipsoid required for geographical coordinates. | D8: Y | G8: LOW | K8: NOT_STARTED
A9: 061.01.01.01.03 | B9: 5 | C9: State that the circumference of the Earth is approximately 40 000 km or approximately 21 600 NM. | D9: N | G9: MED | K9: NOT_STARTED
A10: 061.01.01.02 | B10: 4 | C10: Earth rotation
A11: 061.01.01.02.01 | B11: 5 | C11: Describe the rotation of the Earth around its own spin axis and the plane of the ecliptic (including the relationship of the spin axis to the plane of the ecliptic). | D11: Y | G11: LOW | K11: NOT_STARTED
A12: 061.01.01.02.02 | B12: 5 | C12: Explain the effect that the inclination of the Earth’s spin axis has on insolation and duration of daylight. | D12: N | G12: MED | K12: NOT_STARTED
A13: 061.01.02.00 | B13: 3 | C13: Position
A14: 061.01.02.01 | B14: 4 | C14: Position reference system
A15: 061.01.02.01.01 | B15: 5 | C15: State that geodetic latitude and longitude is used to define a position on the WGS-84 ellipsoid. | D15: Y | G15: LOW | K15: NOT_STARTED
A16: 061.01.02.01.02 | B16: 5 | C16: Define geographic (geodetic) latitude and parallels of latitude. | D16: N | G16: MED | K16: NOT_STARTED
A17: 061.01.02.01.03 | B17: 5 | C17: Calculate the difference in latitude between any two given positions. | D17: N | G17: MED | K17: NOT_STARTED
A18: 061.01.02.01.04 | B18: 5 | C18: Define geographic (geodetic) longitude and meridians. | D18: N | G18: MED | K18: NOT_STARTED
A19: 061.01.02.01.05 | B19: 5 | C19: Calculate the difference in longitude between any two given positions. | D19: N | G19: MED | K19: NOT_STARTED
A20: 061.01.03.00 | B20: 3 | C20: Direction
A21: 061.01.03.01 | B21: 4 | C21: Datums
A22: 061.01.03.01.01 | B22: 5 | C22: Define ‘true north’ (TN). | D22: Y | G22: LOW | K22: NOT_STARTED
A23: 061.01.03.01.02 | B23: 5 | C23: Measure a true direction on any given aeronautical chart. | D23: N | G23: MED | K23: NOT_STARTED
A24: 061.01.03.01.03 | B24: 5 | C24: Define ‘magnetic north’ (MN). | D24: Y | G24: LOW | K24: NOT_STARTED
A25: 061.01.03.01.04 | B25: 5 | C25: Define and apply variation. | D25: N | G25: MED | K25: NOT_STARTED
A26: 061.01.03.01.05 | B26: 5 | C26: Explain changes of variation with time and position. | D26: N | G26: MED | K26: NOT_STARTED
A27: 061.01.03.01.06 | B27: 5 | C27: Define ‘compass north’ (CN). | D27: Y | G27: LOW | K27: NOT_STARTED
A28: 061.01.03.01.07 | B28: 5 | C28: Apply deviation. | D28: N | G28: MED | K28: NOT_STARTED
A29: 061.01.03.02 | B29: 4 | C29: Track and heading
A30: 061.01.03.02.01 | B30: 5 | C30: Calculate XWC by: trigonometry; and MDR. | D30: N | G30: MED | K30: NOT_STARTED
A31: 061.01.03.02.02 | B31: 5 | C31: Explain and apply the concepts of drift and WCA. | D31: N | G31: MED | K31: NOT_STARTED
A32: 061.01.03.02.03 | B32: 5 | C32: Calculate the actual track with appropriate data of heading and drift. | D32: N | G32: MED | K32: NOT_STARTED
A33: 061.01.03.02.04 | B33: 5 | C33: Calculate TKE with appropriate data of WCA and drift. | D33: N | G33: MED | K33: NOT_STARTED
A34: 061.01.03.02.05 | B34: 5 | C34: Calculate the heading change at an off-course fix to directly reach the next waypoint using the 1:60 rule. | D34: N | G34: MED | K34: NOT_STARTED
A35: 061.01.03.02.06 | B35: 5 | C35: Calculate the average drift angle based upon an off-course fix observation. | D35: N | G35: MED | K35: NOT_STARTED
A36: 061.01.04.00 | B36: 3 | C36: Distance
A37: 061.01.04.01 | B37: 4 | C37: WGS-84 ellipsoid
A38: 061.01.04.01.01 | B38: 5 | C38: State that 1 NM is equal to 1.852 km, which is the average distance of 1' of latitude change on the WGS-84 ellipsoid. | D38: Y | G38: LOW | K38: NOT_STARTED
A39: 061.01.04.01.02 | B39: 5 | C39: State that 1' of longitude change at the equator on the WGS-84 ellipsoid is approximately equal to 1 NM. | D39: N | G39: MED | K39: NOT_STARTED
A40: 061.01.04.02 | B40: 4 | C40: Units
A41: 061.01.04.02.01 | B41: 5 | C41: Convert between units of distance (nautical mile (NM), kilometre (km), statute mile (SM), feet (ft), inches (in)). | D41: N | G41: MED | K41: NOT_STARTED
A42: 061.01.04.03 | B42: 4 | C42: Graticule distances
A43: 061.01.04.03.01 | B43: 5 | C43: Calculate the distance between positions on the same meridian, on opposite (antipodal) meridians, on the same parallel of latitude, and calculate new latitude/longitude when given distances north-south and east-west. | D43: N | G43: MED | K43: NOT_STARTED
A44: 061.01.04.04 | B44: 4 | C44: Air mile
A45: 061.01.04.04.01 | B45: 5 | C45: Evaluate the effect of wind and altitude on air distance. | D45: N | G45: MED | K45: NOT_STARTED
A46: 061.01.04.04.02 | B46: 5 | C46: Convert between ground distance (NM) and air distance (NAM) using the formula: NAM = NM × TAS/GS. | D46: N | G46: MED | K46: NOT_STARTED
A47: 061.01.05.00 | B47: 3 | C47: Speed
A48: 061.01.05.01 | B48: 4 | C48: True airspeed (TAS)
A49: 061.01.05.01.01 | B49: 5 | C49: Calculate TAS from CAS, and CAS from TAS by: mechanical computer; and rule of thumb (2 per cent per 1 000 ft). | D49: N | G49: MED | K49: NOT_STARTED
A50: 061.01.05.02 | B50: 4 | C50: Mach number (M)
A51: 061.01.05.02.01 | B51: 5 | C51: Calculate TAS from M, and M from TAS. | D51: N | G51: MED | K51: NOT_STARTED
A52: 061.01.05.03 | B52: 4 | C52: CAS/TAS/M relationship
A53: 061.01.05.03.01 | B53: 5 | C53: Deduce the CAS, TAS and M relationship in climb/descent/cruise (flying at constant CAS or M). | D53: N | G53: MED | K53: NOT_STARTED
A54: 061.01.05.04 | B54: 4 | C54: Ground speed (GS)
A55: 061.01.05.04.01 | B55: 5 | C55: Calculate headwind component (HWC) and tailwind component (TWC) by: trigonometry; and MDR. | D55: N | G55: MED | K55: NOT_STARTED
A56: 061.01.05.04.02 | B56: 5 | C56: Apply HWC and TWC to determine GS from TAS and vice versa. | D56: N | G56: MED | K56: NOT_STARTED
A57: 061.01.05.04.03 | B57: 5 | C57: Explain the relationship between GS and TAS with increasing WCA. | D57: Y | G57: LOW | K57: NOT_STARTED
A58: 061.01.05.04.04 | B58: 5 | C58: Calculate GS with: mechanical computer (TOV solution); and MDR (given track, TAS and WV). | D58: N | G58: MED | K58: NOT_STARTED
A59: 061.01.05.04.05 | B59: 5 | C59: Perform GS, distance and time calculations. | D59: N | G59: MED | K59: NOT_STARTED
A60: 061.01.05.04.06 | B60: 5 | C60: Calculate revised GS to reach a waypoint at a specific time. | D60: N | G60: MED | K60: NOT_STARTED
A61: 061.01.05.04.07 | B61: 5 | C61: Calculate the average GS based on two observed fixes. | D61: N | G61: MED | K61: NOT_STARTED
A62: 061.01.05.05 | B62: 4 | C62: Flight log
A63: 061.01.05.05.01 | B63: 5 | C63: Enter revised navigational en-route data, for the legs concerned, into the flight plan (e.g. updated wind and GS and correspondingly losses or gains in time and fuel consumption). | D63: N | G63: MED | K63: NOT_STARTED
A64: 061.01.05.06 | B64: 4 | C64: Gradient versus rate of climb/descent
A65: 061.01.05.06.01 | B65: 5 | C65: Estimate average climb/descent gradient (per cent) or glide path degrees according to the following rule of thumb: Gradient in degrees = (vertical distance (ft) / 100) / ground distance (NM)) Gradient in per cent = (vertical distance (ft) / 60) / ground distance (NM)) Gradient in degrees = arctan (altitude difference (ft) / ground distance (ft)). N.B. These rules of thumb approximate 1 NM to 6 000 ft and are based on the 1:60 rule. | D65: N | G65: MED | K65: NOT_STARTED
A66: 061.01.05.06.02 | B66: 5 | C66: Calculate rate of descent (ROD) on a given glide-path angle or gradient using the following rule of thumb formulae: ROD (ft/min) = GP degrees × GS (NM/min) × 100 ROD (ft/min) = GP per cent × GS (kt) | D66: N | G66: MED | K66: NOT_STARTED
A67: 061.01.05.06.03 | B67: 5 | C67: Calculate climb/descent gradient (ft/NM, per cent and degrees), GS or vertical speed according to the following formula: Vertical speed (ft/min) = (GS (kt) × gradient (ft/NM)) / 60. | D67: N | G67: MED | K67: NOT_STARTED
A68: 061.01.05.06.04 | B68: 5 | C68: State that it is necessary to determine the position of the aircraft accurately before commencing descent in order to ensure safe ground clearance. | D68: Y | G68: LOW | K68: NOT_STARTED
A69: 061.01.06.00 | B69: 3 | C69: Triangle of velocities (TOV)
A70: 061.01.06.01 | B70: 4 | C70: Construction
A71: 061.01.06.01.01 | B71: 5 | C71: Draw and correctly label the TOV. | D71: N | G71: MED | K71: NOT_STARTED
A72: 061.01.06.02 | B72: 4 | C72: Solutions
A73: 061.01.06.02.01 | B73: 5 | C73: Resolve the TOV for: heading and GS (with mechanical computer and MDR); WV (with mechanical computer); and track and GS (with mechanical computer and MDR. | D73: N | G73: MED | K73: NOT_STARTED
A74: 061.01.07.00 | B74: 3 | C74: Dead reckoning (DR)
A75: 061.01.07.01 | B75: 4 | C75: Dead reckoning (DR) technique
A76: 061.01.07.01.01 | B76: 5 | C76: Determine a DR position. | D76: N | G76: MED | K76: NOT_STARTED
A77: 061.01.07.01.02 | B77: 5 | C77: Evaluate the difference between a DR and a fix position. | D77: N | G77: MED | K77: NOT_STARTED
A78: 061.01.07.01.03 | B78: 5 | C78: Define ‘speed factor’ (SF). Speed divided by 60, used for mental flight-path calculations. | D78: N | G78: MED | K78: NOT_STARTED
A79: 061.01.07.01.04 | B79: 5 | C79: Calculate wind correction angle (WCA) using the formula: WCA = XWC (crosswind component)/SF | D79: N | G79: MED | K79: NOT_STARTED
A80: 061.01.08.00 | B80: 3 | C80: Navigation in climb and descent
A81: 061.01.08.01 | B81: 4 | C81: Average airspeed
A82: 061.01.08.01.01 | B82: 5 | C82: Average TAS used for climb problems is calculated at the altitude 2/3 of the cruising altitude. | D82: N | G82: MED | K82: NOT_STARTED
A83: 061.01.08.01.02 | B83: 5 | C83: Average TAS used for descent problems is calculated at the altitude 1/2 of the descent altitude. | D83: N | G83: MED | K83: NOT_STARTED
A84: 061.01.08.02 | B84: 4 | C84: Average wind velocity (WV)
A85: 061.01.08.02.01 | B85: 5 | C85: WV used for climb problems is the WV at the altitude 2/3 of the cruising altitude. | D85: N | G85: MED | K85: NOT_STARTED
A86: 061.01.08.02.02 | B86: 5 | C86: WV used for descent problems is the WV at the altitude 1/2 of the descent altitude. | D86: N | G86: MED | K86: NOT_STARTED
A87: 061.01.08.02.03 | B87: 5 | C87: Calculate the average climb/descent GS from given TAS at various altitudes, and WV at various altitudes and true track. | D87: N | G87: MED | K87: NOT_STARTED
A88: 061.01.08.03 | B88: 4 | C88: Ground speed (GS)/distance covered during climb or descent
A89: 061.01.08.03.01 | B89: 5 | C89: State that most aircraft operating handbooks supply graphical material to calculate climb and descent problems. | D89: Y | G89: LOW | K89: NOT_STARTED
A90: 061.01.08.03.02 | B90: 5 | C90: Calculate the flying time and distance during climb/descent from given average rate of climb/descent and using average GS using the following formulae valid for a 3-degree-glide path: rate of descent = (GS × 10) / 2 rate of descent = speed factor (SF) × glide-path angle × 100 | D90: N | G90: MED | K90: NOT_STARTED
A91: 061.01.08.03.03 | B91: 5 | C91: Given distance, speed and present altitude, calculate the rate of climb/descent in order to reach a certain position at a given altitude. | D91: N | G91: MED | K91: NOT_STARTED
A92: 061.01.08.03.04 | B92: 5 | C92: Given speed, rate of climb/descent and altitude, calculate the distance required in order to reach a certain position at a given altitude. | D92: N | G92: MED | K92: NOT_STARTED
A93: 061.01.08.03.05 | B93: 5 | C93: Given speed, distance to go and altitude to climb/descent, calculate the rate of climb/descent. | D93: N | G93: MED | K93: NOT_STARTED
A94: 061.02.00.00 | B94: 2 | C94: VISUAL FLIGHT RULES (VFR) NAVIGATION
A95: 061.02.01.00 | B95: 3 | C95: Ground features
A96: 061.02.01.01 | B96: 4 | C96: Ground features
A97: 061.02.01.01.01 | B97: 5 | C97: Recognise which elements would make a ground feature suitable for use for VFR navigation. | D97: N | G97: MED | K97: NOT_STARTED
A98: 061.02.01.02 | B98: 4 | C98: Visual identification
A99: 061.02.01.02.01 | B99: 5 | C99: Describe the problems of VFR navigation at lower levels and the causes of reduced visibility. | D99: N | G99: MED | K99: NOT_STARTED
A100: 061.02.01.02.02 | B100: 5 | C100: Describe the problems of VFR navigation at night. | D100: N | G100: MED | K100: NOT_STARTED
A101: 061.02.02.00 | B101: 3 | C101: VFR navigation techniques
...

Sheet S062
A1: 062 Radio Navigation
A3: LO_ID | B3: Level | C3: LO_Text | D3: BK_Only | E3: ECQB_2026_Change_Flag | F3: ECQB_2026_Source_Note | G3: Priority | H3: Content_Type_Planned | I3: Repo_Path | J3: Agent_Assigned | K3: Coverage_Status | L3: Last_Updated | M3: Reviewed_By | N3: Notes
A4: 062.01.00.00 | B4: 2 | C4: BASIC RADIO PROPAGATION THEORY
A5: 062.01.01.00 | B5: 3 | C5: Basic principles
A6: 062.01.01.01 | B6: 4 | C6: Electromagnetic waves
A7: 062.01.01.01.01 | B7: 5 | C7: State that radio waves travel at the speed of light, being approximately 300 000 km/s. | D7: Y | G7: LOW | K7: NOT_STARTED
A8: 062.01.01.01.02 | B8: 5 | C8: Define a ‘cycle’: a complete series of values of a periodical process. | D8: Y | G8: LOW | K8: NOT_STARTED
A9: 062.01.01.02 | B9: 4 | C9: Frequency, wavelength, amplitude, phase angle
A10: 062.01.01.02.01 | B10: 5 | C10: Define ‘frequency’: the number of cycles occurring in 1 second expressed in Hertz (Hz). | D10: Y | G10: LOW | K10: NOT_STARTED
A11: 062.01.01.02.02 | B11: 5 | C11: Define ‘wavelength’: the physical distance travelled by a radio wave during one cycle of transmission. | D11: Y | G11: LOW | K11: NOT_STARTED
A12: 062.01.01.02.03 | B12: 5 | C12: Define ‘amplitude’: the maximum deflection in an oscillation or wave. | D12: Y | G12: LOW | K12: NOT_STARTED
A13: 062.01.01.02.04 | B13: 5 | C13: State that the relationship between wavelength and frequency is: wavelength (lamda) = speed of light (c) / frequency (f). | D13: Y | G13: LOW | K13: NOT_STARTED
A14: 062.01.01.02.05 | B14: 5 | C14: Define ‘phase angle’: the fraction of one wavelength expressed in degrees from 000 degrees to 360 degrees . | D14: Y | G14: LOW | K14: NOT_STARTED
A15: 062.01.01.02.06 | B15: 5 | C15: Define ‘phase angle difference/shift’: the angular difference between the corresponding points of two cycles of equal wavelength, which is measurable in degrees. | D15: Y | G15: LOW | K15: NOT_STARTED
A16: 062.01.01.03 | B16: 4 | C16: Frequency bands, sidebands, single sideband
A17: 062.01.01.03.01 | B17: 5 | C17: List the bands of the frequency spectrum for electromagnetic waves: very low frequency (VLF): 3-30 kHz; low frequency (LF): 30-300 kHz; medium frequency (MF): 300-3 000 kHz; high frequency (HF): 3-30 MHz; very high frequency (VHF): 30-300 MHz; ultra-high frequency (UHF): 300-3 000 MHz; super high frequency (SHF): 3-30 GHz; extremely high frequency (EHF): 30-300 GHz. | D17: N | G17: MED | K17: NOT_STARTED
A18: 062.01.01.03.02 | B18: 5 | C18: State that when a carrier wave is modulated, the resultant radiation consists of the carrier frequency plus additional upper and lower sidebands. | D18: N | G18: MED | K18: NOT_STARTED
A19: 062.01.01.03.03 | B19: 5 | C19: State that HF meteorological information for aircraft in flight (VOLMET) and HF two-way communication use a single sideband. | D19: N | G19: MED | K19: NOT_STARTED
A20: 062.01.01.03.04 | B20: 5 | C20: State that the following abbreviations (classifications according to International Telecommunication Union (ITU) regulations) are used for aviation applications: N0N: carrier without modulation as used by non-directional radio beacons (NDBs); A1A: carrier with keyed Morse code modulation as used by NDBs; A2A: carrier with amplitude modulated Morse code as used by NDBs; A3E: carrier with amplitude modulated speech used for communication (VHF-COM). | D20: N | G20: MED | K20: NOT_STARTED
A21: 062.01.01.04 | B21: 4 | C21: Pulse characteristics
A22: 062.01.01.04.01 | B22: 5 | C22: Define the following terms that are associated with a pulse string: pulse length; pulse power; continuous power. | D22: N | G22: MED | K22: NOT_STARTED
A23: 062.01.01.05 | B23: 4 | C23: Carrier, modulation
A24: 062.01.01.05.01 | B24: 5 | C24: Define ‘carrier wave’: the radio wave acting as the carrier or transporter. | D24: Y | G24: LOW | K24: NOT_STARTED
A25: 062.01.01.05.02 | B25: 5 | C25: Define ‘modulation’: the technical term for the process of impressing and transporting information by radio waves. | D25: Y | G25: LOW | K25: NOT_STARTED
A26: 062.01.01.06 | B26: 4 | C26: Kinds of modulation (amplitude, frequency, pulse, phase)
A27: 062.01.01.06.01 | B27: 5 | C27: Define ‘amplitude modulation’: the information that is impressed onto the carrier wave by altering the amplitude of the carrier. | D27: Y | G27: LOW | K27: NOT_STARTED
A28: 062.01.01.06.02 | B28: 5 | C28: Define ‘frequency modulation’: the information that is impressed onto the carrier wave by altering the frequency of the carrier. | D28: Y | G28: LOW | K28: NOT_STARTED
A29: 062.01.01.06.03 | B29: 5 | C29: Describe ‘pulse modulation’: a modulation form used in radar by transmitting short pulses followed by larger interruptions. | D29: Y | G29: LOW | K29: NOT_STARTED
A30: 062.01.01.06.04 | B30: 5 | C30: Describe ‘phase modulation’: a modulation form used in GPS where the phase of the carrier wave is reversed. | D30: Y | G30: LOW | K30: NOT_STARTED
A31: 062.01.02.00 | B31: 3 | C31: Antennas
A32: 062.01.02.01 | B32: 4 | C32: Characteristics
A33: 062.01.02.01.01 | B33: 5 | C33: Define ‘antenna’: an antenna or aerial is an electrical device which converts electric power into radio waves, and vice versa. | D33: Y | G33: LOW | K33: NOT_STARTED
A34: 062.01.02.01.02 | B34: 5 | C34: State that the simplest type of antenna is a dipole, which is a wire of length equal to one half of the wavelength. | D34: Y | G34: LOW | K34: NOT_STARTED
A35: 062.01.02.01.03 | B35: 5 | C35: State that an electromagnetic wave always consists of an oscillating electric (E) and an oscillating magnetic (H) field which propagates at the speed of light. | D35: Y | G35: LOW | K35: NOT_STARTED
A36: 062.01.02.01.04 | B36: 5 | C36: State that the E and H fields are perpendicular to each other. The oscillations are perpendicular to the propagation direction and are in-phase. | D36: Y | G36: LOW | K36: NOT_STARTED
A37: 062.01.02.02 | B37: 4 | C37: Polarisation
A38: 062.01.02.02.01 | B38: 5 | C38: State that the polarisation of an electromagnetic wave describes the orientation of the plane of oscillation of the electrical component of the wave with regard to its direction of propagation. | D38: Y | G38: LOW | K38: NOT_STARTED
A39: 062.01.02.03 | B39: 4 | C39: Types of antennas
A40: 062.01.02.03.01 | B40: 5 | C40: Name the common different types of directional antennas: loop antenna used in old automatic direction-finding (ADF) receivers; parabolic antenna used in weather radars; slotted planar array used in more modern weather radars. | D40: N | G40: MED | K40: NOT_STARTED
A41: 062.01.02.03.02 | B41: 5 | C41: Explain ‘antenna shadowing’. | D41: N | G41: MED | K41: NOT_STARTED
A42: 062.01.02.03.03 | B42: 5 | C42: Explain the importance of antenna placement on aircraft. | D42: N | G42: MED | K42: NOT_STARTED
A43: 062.01.03.00 | B43: 3 | C43: Wave propagation
A44: 062.01.03.01 | B44: 4 | C44: Structure of the ionosphere and its effect on radio waves
A45: 062.01.03.01.01 | B45: 5 | C45: State that the ionosphere is the ionised component of the Earth’s upper atmosphere from approximately 60 to 400 km above the surface, which is vertically structured in three regions or layers. | D45: Y | G45: LOW | K45: NOT_STARTED
A46: 062.01.03.01.02 | B46: 5 | C46: State that the layers of the ionosphere are named D, E and F layers, and their depth varies with time. | D46: Y | G46: LOW | K46: NOT_STARTED
A47: 062.01.03.01.03 | B47: 5 | C47: State that electromagnetic waves refracted from the E and F layers of the ionosphere are called sky waves. | D47: Y | G47: LOW | K47: NOT_STARTED
A48: 062.01.03.01.04 | B48: 5 | C48: Explain how the different layers of the ionosphere influence wave propagation. | D48: Y | G48: LOW | K48: NOT_STARTED
A49: 062.01.03.02 | B49: 4 | C49: Ground waves
A50: 062.01.03.02.01 | B50: 5 | C50: Define ‘ground or surface waves’: the electromagnetic waves travelling along the surface of the Earth. | D50: Y | G50: LOW | K50: NOT_STARTED
A51: 062.01.03.03 | B51: 4 | C51: Space waves
A52: 062.01.03.03.01 | B52: 5 | C52: Define ‘space waves’: the electromagnetic waves travelling through the air directly from the transmitter to the receiver. | D52: Y | G52: LOW | K52: NOT_STARTED
A53: 062.01.03.04 | B53: 4 | C53: Propagation with the frequency bands
A54: 062.01.03.04.01 | B54: 5 | C54: State that radio waves in VHF, UHF, SHF and EHF propagate as space waves. | D54: N | G54: MED | K54: NOT_STARTED
A55: 062.01.03.04.02 | B55: 5 | C55: State that radio waves in LF, MF and HF propagate as surface/ground waves and sky waves. | D55: N | G55: MED | K55: NOT_STARTED
A56: 062.01.03.05 | B56: 4 | C56: Doppler principle
A57: 062.01.03.05.01 | B57: 5 | C57: State that the Doppler effect is the phenomenon where the frequency of a wave will increase or decrease if there is relative motion between the transmitter and the receiver. | D57: Y | G57: LOW | K57: NOT_STARTED
A58: 062.01.03.06 | B58: 4 | C58: Factors affecting propagation
A59: 062.01.03.06.01 | B59: 5 | C59: Define ‘skip distance’: the distance between the transmitter and the point on the surface of the Earth where the first sky wave return arrives. | D59: Y | G59: LOW | K59: NOT_STARTED
A60: 062.01.03.06.02 | B60: 5 | C60: State that skip zone/dead space is the distance between the limit of the surface wave and the sky wave. | D60: N | G60: MED | K60: NOT_STARTED
A61: 062.01.03.06.03 | B61: 5 | C61: Describe ‘fading’: when a receiver picks up two signals with the same frequency, and the signals will interfere with each other causing changes in the resultant signal strength and polarisation. | D61: N | G61: MED | K61: NOT_STARTED
A62: 062.01.03.06.04 | B62: 5 | C62: State that radio waves in the VHF band and above are limited in range as they are not reflected by the ionosphere and do not have a surface wave. | D62: N | G62: MED | K62: NOT_STARTED
A63: 062.01.03.06.05 | B63: 5 | C63: Describe the physical phenomena ‘reflection’, ‘refraction’, ‘diffraction’, ‘absorption’ and ‘interference’. | D63: Y | G63: LOW | K63: NOT_STARTED
A64: 062.01.03.06.06 | B64: 5 | C64: State that multipath is when the signal arrives at the receiver via more than one path (the signal being reflected from surfaces near the receiver). | D64: N | G64: MED | K64: NOT_STARTED
A65: 062.02.00.00 | B65: 2 | C65: RADIO AIDS
A66: 062.02.01.00 | B66: 3 | C66: Ground direction finding (DF)
A67: 062.02.01.01 | B67: 4 | C67: Principles
A68: 062.02.01.01.01 | B68: 5 | C68: Describe the use of a ground DF. | D68: Y | G68: LOW | K68: NOT_STARTED
A69: 062.02.01.01.02 | B69: 5 | C69: Explain the limitation of range because of the path of the VHF signal. | D69: N | G69: MED | K69: NOT_STARTED
A70: 062.02.01.02 | B70: 4 | C70: Presentation and interpretation
A71: 062.02.01.02.01 | B71: 5 | C71: Define the term ‘QDM’: the magnetic bearing to the station. | D71: N | G71: MED | K71: NOT_STARTED
A72: 062.02.01.02.02 | B72: 5 | C72: Define the term ‘QDR’: the magnetic bearing from the station. | D72: N | G72: MED | K72: NOT_STARTED
A73: 062.02.01.02.03 | B73: 5 | C73: Explain that by using more than one ground station, the position of an aircraft can be determined and transmitted to the pilot. | D73: N | G73: MED | K73: NOT_STARTED
A74: 062.02.01.03 | B74: 4 | C74: Coverage and range
A75: 062.02.01.03.01 | B75: 5 | C75: Use the formula: 1.23 × sqrt transmitter height in feet plus 1.23 × sqrt receiver height in feet to calculate the range in NM. | D75: N | G75: MED | K75: NOT_STARTED
A76: 062.02.01.04 | B76: 4 | C76: Errors and accuracy
A77: 062.02.01.04.01 | B77: 5 | C77: Explain why synchronous transmissions will cause errors. | D77: Y | G77: LOW | K77: NOT_STARTED
A78: 062.02.01.04.02 | B78: 5 | C78: Describe the effect of ‘multipath signals’. | D78: Y | G78: LOW | K78: NOT_STARTED
A79: 062.02.01.04.03 | B79: 5 | C79: Explain that VDF information is divided into the following classes according to ICAO Annex 10: Class A: accurate to a range within plus/minus 2 degrees ; Class B: accurate to a range within plus/minus 5 degrees ; Class C: accurate to a range within plus/minus 10 degrees ; Class D: accurate to less than Class C. | D79: N | G79: MED | K79: NOT_STARTED
A80: 062.02.02.00 | B80: 3 | C80: Non-directional radio beacon (NDB)/automatic direction finding (ADF)
A81: 062.02.02.01 | B81: 4 | C81: Principles
A82: 062.02.02.01.01 | B82: 5 | C82: Define the acronym ‘NDB’: non-directional radio beacon. | D82: Y | G82: LOW | K82: NOT_STARTED
A83: 062.02.02.01.02 | B83: 5 | C83: Define the acronym ‘ADF’: automatic direction-finding equipment. | D83: Y | G83: LOW | K83: NOT_STARTED
A84: 062.02.02.01.03 | B84: 5 | C84: State that the NDB is the ground part of the system. | D84: Y | G84: LOW | K84: NOT_STARTED
A85: 062.02.02.01.04 | B85: 5 | C85: State that the ADF is the airborne part of the system. | D85: Y | G85: LOW | K85: NOT_STARTED
A86: 062.02.02.01.05 | B86: 5 | C86: State that the NDB operates in the LF and MF frequency bands. | D86: N | G86: MED | K86: NOT_STARTED
A87: 062.02.02.01.06 | B87: 5 | C87: State that the frequency band assigned to aeronautical NDBs according to ICAO Annex 10 is 190-1750 kHz. | D87: N | G87: MED | K87: NOT_STARTED
A88: 062.02.02.01.07 | B88: 5 | C88: Define a ‘locator beacon’: an LF/MF NDB used as an aid to final approach usually with a range of 10-25 NM. | D88: N | G88: MED | K88: NOT_STARTED
A89: 062.02.02.01.08 | B89: 5 | C89: State that certain commercial radio stations transmit within the frequency band of the NDB. | D89: Y | G89: LOW | K89: NOT_STARTED
A90: 062.02.02.01.09 | B90: 5 | C90: State that according to ICAO Annex 10, an NDB station has an automatic ground monitoring system. | D90: Y | G90: LOW | K90: NOT_STARTED
A91: 062.02.02.01.10 | B91: 5 | C91: Describe the use of NDBs for navigation. | D91: N | G91: MED | K91: NOT_STARTED
A92: 062.02.02.01.11 | B92: 5 | C92: Describe the procedure to identify an NDB station. | D92: N | G92: MED | K92: NOT_STARTED
A93: 062.02.02.01.12 | B93: 5 | C93: Interpret the term ‘cone of confusion’ in respect of an NDB. | D93: Y | G93: LOW | K93: NOT_STARTED
... A97: 062.02.02.01.16 | B97: 5 | C97: State that on modern aircraft, the BFO is activated automatically. | D97: Y | G97: LOW | K97: NOT_STARTED
A98: 062.02.02.02 | B98: 4 | C98: Presentation and interpretation
A99: 062.02.02.02.01 | B99: 5 | C99: Name the types of indicators commonly in use: electronic display; radio magnetic indicator (RMI); fixed-card ADF (radio compass); moving-card ADF. | D99: Y | G99: LOW | K99: NOT_STARTED
A100: 062.02.02.02.02 | B100: 5 | C100: Interpret the indications given on RMI, fixed-card and moving-card ADF displays. | D100: N | G100: MED | K100: NOT_STARTED
A101: 062.02.02.02.03 | B101: 5 | C101: Given a display, interpret the relevant ADF information. | D101: N | G101: MED | K101: NOT_STARTED
A102: 062.02.02.02.04 | B102: 5 | C102: Calculate the true bearing from the compass heading and relative bearing. | D102: N | G102: MED | K102: NOT_STARTED
A103: 062.02.02.02.05 | B103: 5 | C103: Convert the compass bearing into magnetic bearing and true bearing. | D103: N | G103: MED | K103: NOT_STARTED
A104: 062.02.02.02.06 | B104: 5 | C104: Describe how to fly the following in-flight ADF procedures: homing and tracking, and explain the influence of wind; interception of inbound QDM and outbound QDR; changing from one QDM/QDR to another; determining station passage and the abeam point. | D104: N | G104: MED | K104: NOT_STARTED
...

Sheet S070
